Workbook

Sheet Planilha6
A1: Linha do Tempo | B1: Valores | C1: Previsão | D1: Limite de Confiança Inferior | E1: Limite de Confiança Superior
A2: 45658 | B2: 159260.53
A3: 45689 | B3: 205465.7
A4: 45717 | B4: 212696.97
A5: 45748 | B5: 225882.05
A6: 45778 | B6: 252020.4
A7: 45809 | B7: 159826.26
A8: 45839 | B8: 205248.67
A9: 45870 | B9: 183735.51
A10: 45901 | B10: 202938.1
A11: 45931 | B11: 178379.29
A12: 45962 | B12: 184310.95
A13: 45992 | B13: 198779.59
... A16: 46082 | B16: 183424.12
A17: 46113 | B17: 214380.68 | C17: 214380.68 | D17: 214380.68 | E17: 214380.68
A18: 46143 | C18: =_xlfn.FORECAST.ETS(A18,$B$2:$B$17,$A$2:$A$17,1,1) -> 184769.44 | D18: =C18-_xlfn.FORECAST.ETS.CONFINT(A18,$B$2:$B$17,$A$2:$A$17,0.95,1,1) -> 113467.07 | E18: =C18+_xlfn.FORECAST.ETS.CONFINT(A18,$B$2:$B$17,$A$2:$A$17,0.95,1,1) -> 256071.8
A19: 46174 | C19: =_xlfn.FORECAST.ETS(A19,$B$2:$B$17,$A$2:$A$17,1,1) -> 182596.94 | D19: =C19-_xlfn.FORECAST.ETS.CONFINT(A19,$B$2:$B$17,$A$2:$A$17,0.95,1,1) -> 102846.56 | E19: =C19+_xlfn.FORECAST.ETS.CONFINT(A19,$B$2:$B$17,$A$2:$A$17,0.95,1,1) -> 262347.32
A20: 46204 | C20: =_xlfn.FORECAST.ETS(A20,$B$2:$B$17,$A$2:$A$17,1,1) -> 180424.44 | D20: =C20-_xlfn.FORECAST.ETS.CONFINT(A20,$B$2:$B$17,$A$2:$A$17,0.95,1,1) -> 93009.8 | E20: =C20+_xlfn.FORECAST.ETS.CONFINT(A20,$B$2:$B$17,$A$2:$A$17,0.95,1,1) -> 267839.07
A21: 46235 | C21: =_xlfn.FORECAST.ETS(A21,$B$2:$B$17,$A$2:$A$17,1,1) -> 178251.93 | D21: =C21-_xlfn.FORECAST.ETS.CONFINT(A21,$B$2:$B$17,$A$2:$A$17,0.95,1,1) -> 83765.834 | E21: =C21+_xlfn.FORECAST.ETS.CONFINT(A21,$B$2:$B$17,$A$2:$A$17,0.95,1,1) -> 272738.04

Sheet Planilha7
A1: Linha do Tempo | B1: Valores | C1: Previsão | D1: Limite de Confiança Inferior | E1: Limite de Confiança Superior
A2: 45658 | B2: 217.89
A3: 45689 | B3: 7973.12
A4: 45717 | B4: 5366.17
A5: 45748 | B5: -20347.55
A6: 45778 | B6: 10741.17
A7: 45809 | B7: -13284.03
A8: 45839 | B8: 2867.78
A9: 45870 | B9: -641.37
A10: 45901 | B10: 8471.35
A11: 45931 | B11: -8746.69
A12: 45962 | B12: 402.92
A13: 45992 | B13: 71166.29
... A16: 46082 | B16: 2497.14
A17: 46113 | B17: -2426.66 | C17: -2426.66 | D17: -2426.66 | E17: -2426.66
A18: 46143 | C18: =_xlfn.FORECAST.ETS(A18,$B$2:$B$17,$A$2:$A$17,1,1) -> -3277.4478 | D18: =C18-_xlfn.FORECAST.ETS.CONFINT(A18,$B$2:$B$17,$A$2:$A$17,0.95,1,1) -> -51978.622 | E18: =C18+_xlfn.FORECAST.ETS.CONFINT(A18,$B$2:$B$17,$A$2:$A$17,0.95,1,1) -> 45423.726
A19: 46174 | C19: =_xlfn.FORECAST.ETS(A19,$B$2:$B$17,$A$2:$A$17,1,1) -> -3489.7571 | D19: =C19-_xlfn.FORECAST.ETS.CONFINT(A19,$B$2:$B$17,$A$2:$A$17,0.95,1,1) -> -52191.15 | E19: =C19+_xlfn.FORECAST.ETS.CONFINT(A19,$B$2:$B$17,$A$2:$A$17,0.95,1,1) -> 45211.636
A20: 46204 | C20: =_xlfn.FORECAST.ETS(A20,$B$2:$B$17,$A$2:$A$17,1,1) -> -3702.0665 | D20: =C20-_xlfn.FORECAST.ETS.CONFINT(A20,$B$2:$B$17,$A$2:$A$17,0.95,1,1) -> -52403.849 | E20: =C20+_xlfn.FORECAST.ETS.CONFINT(A20,$B$2:$B$17,$A$2:$A$17,0.95,1,1) -> 44999.716
A21: 46235 | C21: =_xlfn.FORECAST.ETS(A21,$B$2:$B$17,$A$2:$A$17,1,1) -> -3914.3758 | D21: =C21-_xlfn.FORECAST.ETS.CONFINT(A21,$B$2:$B$17,$A$2:$A$17,0.95,1,1) -> -52616.767 | E21: =C21+_xlfn.FORECAST.ETS.CONFINT(A21,$B$2:$B$17,$A$2:$A$17,0.95,1,1) -> 44788.015
A22: 46266 | C22: =_xlfn.FORECAST.ETS(A22,$B$2:$B$17,$A$2:$A$17,1,1) -> -4126.6852 | D22: =C22-_xlfn.FORECAST.ETS.CONFINT(A22,$B$2:$B$17,$A$2:$A$17,0.95,1,1) -> -52829.953 | E22: =C22+_xlfn.FORECAST.ETS.CONFINT(A22,$B$2:$B$17,$A$2:$A$17,0.95,1,1) -> 44576.583

Sheet Home
B1: FINANCEIRO | Q1: NFE
A4: =IF(C4="ANUAL",DATE(2026,1,1),DATE(2026,MATCH(C4,{"JANEIRO";"FEVEREIRO";"MARÇO";"ABRIL";"MAIO";"JUNHO";"JULHO";"AGOSTO";"SETEMBRO";"OUTUBRO";"NOVEMBRO";"DEZEMBRO"},0),1)) -> 46023 | B4: Mês | C4: Anual | P4: =IF(R4="ANUAL",DATE(2026,1,1),DATE(2026,MATCH(R4,{"JANEIRO";"FEVEREIRO";"MARÇO";"ABRIL";"MAIO";"JUNHO";"JULHO";"AGOSTO";"SETEMBRO";"OUTUBRO";"NOVEMBRO";"DEZEMBRO"},0),1)) -> 46023 | Q4: Mês | R4: Anual
A5: =IF(C4="ANUAL",DATE(2026,12,31),EOMONTH(DATE(2026,MATCH(C4,{"JANEIRO";"FEVEREIRO";"MARÇO";"ABRIL";"MAIO";"JUNHO";"JULHO";"AGOSTO";"SETEMBRO";"OUTUBRO";"NOVEMBRO";"DEZEMBRO"},0),1),0)) -> 46387 | P5: =IF(R4="ANUAL",DATE(2026,12,31),EOMONTH(DATE(2026,MATCH(R4,{"JANEIRO";"FEVEREIRO";"MARÇO";"ABRIL";"MAIO";"JUNHO";"JULHO";"AGOSTO";"SETEMBRO";"OUTUBRO";"NOVEMBRO";"DEZEMBRO"},0),1),0)) -> 46387
B7: MAX LED | Q7: MAX LED
B8: ENTRADAS TOTAIS | F8: SAIDAS TOTAIS | J8: TOTAL | Q8: ENTRADAS TOTAIS | U8: SAIDAS TOTAIS | Y8: TOTAL
B9: =SUMIFS('ENTRADAS - FIN - ilumi'!D:D,'ENTRADAS - FIN - ilumi'!A:A,">="&A4,'ENTRADAS - FIN - ilumi'!A:A,"<="&A5)+SUMIFS('Entradas- fin- import'!D:D,'Entradas- fin- import'!A:A,">="&A4,'Entradas- fin- import'!A:A,"<="&A5) -> 1086398.6 | F9: =SUMIFS('Saidas-fin-import'!D:D,'Saidas-fin-import'!A:A,">="&A4,'Saidas-fin-import'!A:A,"<="&A5)+SUMIFS('SAIDAS-FIN-ilumi'!D:D,'SAIDAS-FIN-ilumi'!A:A,">="&A4,'SAIDAS-FIN-ilumi'!A:A,"<="&A5) -> 1166871.2 | J9: =B9+D10-F9 -> -80472.59 | Q9: =SUMIFS('SAÍDA NFE ILUMI'!D:D,'SAÍDA NFE ILUMI'!A:A,">="&P4,'SAÍDA NFE ILUMI'!A:A,"<="&P5)+SUMIFS('Saídas-NFE-import'!D:D,'Saídas-NFE-import'!A:A,">="&P4,'Saídas-NFE-import'!A:A,"<="&P5) -> 1120588.9 | U9: =SUMIFS('Entradas-NFE-Import'!D:D,'Entradas-NFE-Import'!A:A,">="&P4,'Entradas-NFE-Import'!A:A,"<="&P5)+SUMIFS('ENTRADA NFE ILUMI'!D:D,'ENTRADA NFE ILUMI'!A:A,">="&P4,'ENTRADA NFE ILUMI'!A:A,"<="&P5) -> 624281.03 | Y9: =Q9-U9 -> 496307.84
B12: MAX LED ILUMINAÇÃO | Q12: MAX LED ILUMINAÇÃO
B13: ENTRADAS | F13: SAIDAS | J13: TOTAL | Q13: ENTRADAS | U13: SAIDAS | Y13: TOTAL
B14: =SUMIFS('ENTRADAS - FIN - ilumi'!D:D,'ENTRADAS - FIN - ilumi'!A:A,">="&A4,'ENTRADAS - FIN - ilumi'!A:A,"<="&A5) -> 810757.63 | F14: =SUMIFS('SAIDAS-FIN-ilumi'!D:D,'SAIDAS-FIN-ilumi'!A:A,">="&A4,'SAIDAS-FIN-ilumi'!A:A,"<="&A5) -> 830291.43 | J14: =B14+D15-F14 -> -19533.8 | Q14: =SUMIFS('SAÍDA NFE ILUMI'!D:D,'SAÍDA NFE ILUMI'!A:A,">="&P4,'SAÍDA NFE ILUMI'!A:A,"<="&P5) -> 805816.77 | U14: =SUMIFS('ENTRADA NFE ILUMI'!D:D,'ENTRADA NFE ILUMI'!A:A,">="&P4,'ENTRADA NFE ILUMI'!A:A,"<="&P5) -> 465723.83 | Y14: =Q14-U14 -> 340092.94
B17: MAX LED IMPORTAÇÃO | Q17: MAX LED IMPORTAÇÃO
B18: ENTRADAS | F18: SAIDAS | J18: TOTAL | Q18: ENTRADAS | U18: SAIDAS | Y18: TOTAL
B19: =SUMIFS('Entradas- fin- import'!D:D,'Entradas- fin- import'!A:A,">="&A4,'Entradas- fin- import'!A:A,"<="&A5) -> 275640.99 | F19: =SUMIFS('Saidas-fin-import'!D:D,'Saidas-fin-import'!A:A,">="&A4,'Saidas-fin-import'!A:A,"<="&A5) -> 336579.78 | J19: =B19+D20-F19 -> -60938.79 | Q19: =SUMIFS('Saídas-NFE-import'!D:D,'Saídas-NFE-import'!A:A,">="&P4,'Saídas-NFE-import'!A:A,"<="&P5) -> 314772.1 | U19: =SUMIFS('Entradas-NFE-Import'!D:D,'Entradas-NFE-Import'!A:A,">="&P4,'Entradas-NFE-Import'!A:A,"<="&P5) -> 158557.2 | Y19: =Q19-U19 -> 156214.9
B23: MAX LED ILUMINAÇÃO | H23: MAX LED IMPORTAÇÃO
B24: MÊS | C24: Receita | D24: Saida | E24: TOTAL | H24: MÊS | I24: Receita | J24: Saída | K24: TOTAL
B25: Janeiro | C25: =SUMIF('ENTRADAS - FIN - ilumi'!F:F,"Janeiro",'ENTRADAS - FIN - ilumi'!D:D) -> 132275.4 | D25: =SUMIF('SAIDAS-FIN-ilumi'!F:F,"Janeiro",'SAIDAS-FIN-ilumi'!D:D) -> 116350.31 | E25: =D15+C25-D25 -> 15925.09 | H25: Janeiro | I25: =SUMIF('Entradas- fin- import'!E:E,"Janeiro",'Entradas- fin- import'!D:D) -> 13593.52 | J25: =SUMIF('Saidas-fin-import'!E:E,"Janeiro",'Saidas-fin-import'!D:D) -> 74876.93 | K25: =I25-J25 -> -61283.41
B26: Fevereiro | C26: =SUMIF('ENTRADAS - FIN - ilumi'!F:F,"Fevereiro",'ENTRADAS - FIN - ilumi'!D:D) -> 126679.25 | D26: =SUMIF('SAIDAS-FIN-ilumi'!F:F,"FEVEREIRO",'SAIDAS-FIN-ilumi'!D:D) -> 133410.26 | E26: =D16+C26-D26 -> -6731.01 | H26: Fevereiro | I26: =SUMIF('Entradas- fin- import'!E:E,"FEVEREIRO",'Entradas- fin- import'!D:D) -> 37091.38 | J26: =SUMIF('Saidas-fin-import'!E:E,"FEVEREIRO",'Saidas-fin-import'!D:D) -> 44764.38 | K26: =I26-J26 -> -7673
B27: Março | C27: =SUMIF('ENTRADAS - FIN - ilumi'!F:F,"MARÇO",'ENTRADAS - FIN - ilumi'!D:D) -> 183424.12 | D27: =SUMIF('SAIDAS-FIN-ilumi'!F:F,"MARÇO",'SAIDAS-FIN-ilumi'!D:D) -> 192968.08 | E27: =D17+C27-D27 -> -9543.96 | H27: Março | I27: =SUMIF('Entradas- fin- import'!E:E,"MARÇO",'Entradas- fin- import'!D:D) -> 37723.49 | J27: =SUMIF('Saidas-fin-import'!E:E,"MARÇO",'Saidas-fin-import'!D:D) -> 35226.35 | K27: =I27-J27 -> 2497.14
B28: Abril | C28: =SUMIF('ENTRADAS - FIN - ilumi'!F:F,"Abril",'ENTRADAS - FIN - ilumi'!D:D) -> 214380.68 | D28: =SUMIF('SAIDAS-FIN-ilumi'!F:F,"ABRIL",'SAIDAS-FIN-ilumi'!D:D) -> 231574.3 | E28: =D18+C28-D28 -> -17193.62 | H28: Abril | I28: =SUMIF('Entradas- fin- import'!E:E,"ABRIL",'Entradas- fin- import'!D:D) -> 105609.12 | J28: =SUMIF('Saidas-fin-import'!E:E,"ABRIL",'Saidas-fin-import'!D:D) -> 108035.78 | K28: =I28-J28 -> -2426.66
B29: Maio | C29: =SUMIF('ENTRADAS - FIN - ilumi'!F:F,"Maio",'ENTRADAS - FIN - ilumi'!D:D) -> 153998.18 | D29: =SUMIF('SAIDAS-FIN-ilumi'!F:F,"MAIO",'SAIDAS-FIN-ilumi'!D:D) -> 155988.48 | E29: =D19+C29-D29 -> -1990.3 | H29: Maio | I29: =SUMIF('Entradas- fin- import'!E:E,"MAIO",'Entradas- fin- import'!D:D) -> 80008.32 | J29: =SUMIF('Saidas-fin-import'!E:E,"MAIO",'Saidas-fin-import'!D:D) -> 70645.67 | K29: =I29-J29 -> 9362.65
B30: Junho | C30: =SUMIF('ENTRADAS - FIN - ilumi'!F:F,"Junho",'ENTRADAS - FIN - ilumi'!D:D) -> 0 | D30: =SUMIF('SAIDAS-FIN-ilumi'!F:F,"JUNHO",'SAIDAS-FIN-ilumi'!D:D) -> 0 | E30: - | H30: Junho | I30: =SUMIF('Entradas- fin- import'!E:E,"JUNHO",'Entradas- fin- import'!D:D) -> 0 | J30: =SUMIF('Saidas-fin-import'!E:E,"JUNHO",'Saidas-fin-import'!D:D) -> 0 | K30: -
B31: Julho | C31: =SUMIF('ENTRADAS - FIN - ilumi'!F:F,"Julho",'ENTRADAS - FIN - ilumi'!D:D) -> 0 | D31: =SUMIF('SAIDAS-FIN-ilumi'!F:F,"JULHO",'SAIDAS-FIN-ilumi'!D:D) -> 0 | E31: - | H31: Julho | I31: =SUMIF('Entradas- fin- import'!E:E,"JULHO",'Entradas- fin- import'!D:D) -> 0 | J31: =SUMIF('Saidas-fin-import'!E:E,"JULHO",'Saidas-fin-import'!D:D) -> 0 | K31: -
B32: Agosto | C32: =SUMIF('ENTRADAS - FIN - ilumi'!F:F,"Agosto",'ENTRADAS - FIN - ilumi'!D:D) -> 0 | D32: =SUMIF('SAIDAS-FIN-ilumi'!F:F,"AGOSTO",'SAIDAS-FIN-ilumi'!D:D) -> 0 | E32: - | H32: Agosto | I32: =SUMIF('Entradas- fin- import'!E:E,"AGOSTO",'Entradas- fin- import'!D:D) -> 0 | J32: =SUMIF('Saidas-fin-import'!E:E,"AGOSTO",'Saidas-fin-import'!D:D) -> 0 | K32: -
B33: Setembro | C33: =SUMIF('ENTRADAS - FIN - ilumi'!F:F,"Setembro",'ENTRADAS - FIN - ilumi'!D:D) -> 0 | D33: =SUMIF('SAIDAS-FIN-ilumi'!F:F,"SETEMBRO",'SAIDAS-FIN-ilumi'!D:D) -> 0 | E33: - | H33: Setembro | I33: =SUMIF('Entradas- fin- import'!E:E,"SETEMBRO",'Entradas- fin- import'!D:D) -> 0 | J33: =SUMIF('Saidas-fin-import'!E:E,"SETEMBRO",'Saidas-fin-import'!D:D) -> 0 | K33: -
B34: Outubro | C34: =SUMIF('ENTRADAS - FIN - ilumi'!F:F,"Outubro",'ENTRADAS - FIN - ilumi'!D:D) -> 0 | D34: =SUMIF('SAIDAS-FIN-ilumi'!F:F,"OUTUBRO",'SAIDAS-FIN-ilumi'!D:D) -> 0 | E34: - | H34: Outubro | I34: =SUMIF('Entradas- fin- import'!E:E,"OUTUBRO",'Entradas- fin- import'!D:D) -> 0 | J34: =SUMIF('Saidas-fin-import'!E:E,"OUTUBRO",'Saidas-fin-import'!D:D) -> 0 | K34: -
B35: Novembro | C35: =SUMIF('ENTRADAS - FIN - ilumi'!F:F,"Novembro",'ENTRADAS - FIN - ilumi'!D:D) -> 0 | D35: =SUMIF('SAIDAS-FIN-ilumi'!F:F,"NOVEMBRO",'SAIDAS-FIN-ilumi'!D:D) -> 0 | E35: - | H35: Novembro | I35: =SUMIF('Entradas- fin- import'!E:E,"NVEMBRO",'Entradas- fin- import'!D:D) -> 0 | J35: =SUMIF('Saidas-fin-import'!E:E,"NOVEMBRO",'Saidas-fin-import'!D:D) -> 0 | K35: -
B36: Dezembro | C36: =SUMIF('ENTRADAS - FIN - ilumi'!F:F,"Dezembro",'ENTRADAS - FIN - ilumi'!D:D) -> 0 | D36: =SUMIF('SAIDAS-FIN-ilumi'!F:F,"DEZEMBRO",'SAIDAS-FIN-ilumi'!D:D) -> 0 | E36: - | H36: Dezembro | I36: =SUMIF('Entradas- fin- import'!E:E,"DEZEMBRO",'Entradas- fin- import'!D:D) -> 0 | J36: =SUMIF('Saidas-fin-import'!E:E,"DEZEMBRO",'Saidas-fin-import'!D:D) -> 0 | K36: -
B37: Total | C37: =SUM(C25:C36) -> 810757.63 | D37: =SUM(D25:D36) -> 830291.43 | E37: =SUM(E25:E28) -> -17543.5 | H37: Total | I37: =SUM(I25:I36) -> 274025.83 | J37: =SUM(J25:J36) -> 333549.11 | K37: =SUM(K25:K36) -> -59523.28
B54: Projeções Max Led Iluminação | H54: Projeções Max Led Importação
C55: Entradas | D55: Saidas | E55: Total | I55: Entradas | J55: Saidas | K55: Total
B56: 45658 | C56: 159260.53 | D56: 175562.16 | E56: =C56-D56 -> -16301.63 | H56: 45658 | I56: 19591.87 | J56: 19373.98 | K56: =I56-J56 -> 217.89
B57: 45689 | C57: 205465.7 | D57: 187413.04 | E57: =C57-D57 -> 18052.66 | H57: 45689 | I57: 57998.11 | J57: 50024.99 | K57: =I57-J57 -> 7973.12
B58: 45717 | C58: 212696.97 | D58: 235789.98 | E58: =C58-D58 -> -23093.01 | H58: 45717 | I58: 56487.68 | J58: 51121.51 | K58: =I58-J58 -> 5366.17
B59: 45748 | C59: 225882.05 | D59: 204028.74 | E59: =C59-D59 -> 21853.31 | H59: 45748 | I59: 61782.7 | J59: 82130.25 | K59: =I59-J59 -> -20347.55
B60: 45778 | C60: 252020.4 | D60: 225748.62 | E60: =C60-D60 -> 26271.78 | H60: 45778 | I60: 39163.78 | J60: 28422.61 | K60: =I60-J60 -> 10741.17
B61: 45809 | C61: 159826.26 | D61: 201481.58 | E61: =C61-D61 -> -41655.32 | H61: 45809 | I61: 17138.87 | J61: 30422.9 | K61: =I61-J61 -> -13284.03
B62: 45839 | C62: 205248.67 | D62: 214354.38 | E62: =C62-D62 -> -9105.71 | H62: 45839 | I62: 68605.59 | J62: 65737.81 | K62: =I62-J62 -> 2867.78
B63: 45870 | C63: 183735.51 | D63: 191802.78 | E63: =C63-D63 -> -8067.27 | H63: 45870 | I63: 84229.75 | J63: 84871.12 | K63: =I63-J63 -> -641.37
B64: 45901 | C64: 202938.1 | D64: 204295.82 | E64: =C64-D64 -> -1357.72 | H64: 45901 | I64: 126144.65 | J64: 117673.3 | K64: =I64-J64 -> 8471.35
B65: 45931 | C65: 178379.29 | D65: 167394.79 | E65: =C65-D65 -> 10984.5 | H65: 45931 | I65: 61637.75 | J65: 70384.44 | K65: =I65-J65 -> -8746.69
B66: 45962 | C66: 184310.95 | D66: 183155.39 | E66: =C66-D66 -> 1155.56 | H66: 45962 | I66: 58123.77 | J66: 57720.85 | K66: =I66-J66 -> 402.92
B67: 45992 | C67: 198779.59 | D67: 179590.32 | E67: =C67-D67 -> 19189.27 | H67: 45992 | I67: 150258.42 | J67: 79092.13 | K67: =I67-J67 -> 71166.29
... B71: 46113 | C71: 214380.68 | D71: 231574.3 | E71: =C71-D71 -> -17193.62 | H71: 46113 | I71: 105609.12 | J71: 108035.78 | K71: =I71-J71 -> -2426.66
B72: 46143 | C72: =AVERAGE(C56:C71)+C90 -> 349223.3 | D72: =AVERAGE(D54:D69)+D90 -> 342064.34 | E72: =C72-D72 -> 7158.9576 | H72: 46143 | I72: =AVERAGE(I56:I71)+I90 -> 130889.41 | J72: =AVERAGE(J56:J71)+J90 -> 81389.118 | K72: =I72-J72 -> 49500.29
B73: 46174 | C73: =AVERAGE(C56:C72)+C91 -> 302449.43 | D73: =AVERAGE(D55:D70)+D91 -> 293406.06 | E73: =C73-D73 -> 9043.3779 | H73: 46174 | I73: =AVERAGE(I57:I71)+I91 -> 135291.85 | J73: =AVERAGE(J56:J72)+J91 -> 88995.856 | K73: =I73-J73 -> 46295.992
B74: 46204 | C74: =AVERAGE(C56:C73)+C92 -> 229714.06 | D74: =AVERAGE(D56:D71)-D92 -> 134474.89 | E74: =C74-D74 -> 95239.161 | H74: 46204 | I74: =AVERAGE(I56:I71)+I92 -> 69630.008 | J74: =AVERAGE(J56:J73)-J92 -> 43356.854 | K74: =I74-J74 -> 26273.155
B75: 46235 | C75: =AVERAGE(C56:C74)+C93 -> 209498.81 | D75: =AVERAGE(D57:D72)-D93 -> 149595.29 | E75: =C75-D75 -> 59903.516 | H75: 46235 | I75: =AVERAGE(I56:I71)+I93 -> 62715.108 | J75: =AVERAGE(J56:J74)-J93 -> 52436.138 | K75: =I75-J75 -> 10278.97
B76: 46266 | C76: =AVERAGE(C56:C75)+C94 -> 205809.45 | D76: =AVERAGE(D58:D73)-D94 -> 156219.85 | E76: =C76-D76 -> 49589.599 | H76: 46266 | I76: =AVERAGE(I56:I71)+I94 -> 62198.778 | J76: =AVERAGE(J56:J71)-J94 -> 51053.798 | K76: =I76-J76 -> 11144.98
B89: Mês | C89: A Receber Iluminação | D89: A Pagar Iluminação | E89: Saldo | H89: Mês | I89: A Receber Importação | J89: A Pagar Importação | K89: Saldo
B90: mai/26 | C90: {=SUMPRODUCT((MID('[1]A receer iluminação'!$E$2:$E$271,4,2)="05")*(MID('[1]A receer iluminação'!$E$2:$E$271,7,4)="2026")*('[1]A receer iluminação'!$D$2:$D$271))} -> 160141.83 | D90: {=SUMPRODUCT((MID('[1]a pagar iluminação'!$G$2:$G$384,4,2)="05")*(MID('[1]a pagar iluminação'!$G$2:$G$384,7,4)="2026")*('[1]a pagar iluminação'!$F$2:$F$384))} -> 154894.47 | E90: =C90-D90 -> 5247.36 | H90: mai/26 | I90: {=SUMPRODUCT((VALUE(MID('[1]a reverber importação'!$G$2:$G$40,4,2))=5)*(VALUE(MID('[1]a reverber importação'!$G$2:$G$40,7,4))=2026)*('[1]a reverber importação'!$F$2:$F$40))} -> 68690.63 | J90: {=SUMPRODUCT((VALUE(MID('[1]a pagar importaçãp'!$G$2:$G$55,4,2))=5)*(VALUE(MID('[1]a pagar importaçãp'!$G$2:$G$55,7,4))=2026)*('[1]a pagar importaçãp'!$F$2:$F$55))} -> 18896.66 | K90: =I90-J90 -> 49793.97
B91: jun/26 | C91: {=SUMPRODUCT((MID('[1]A receer iluminação'!$E$2:$E$271,4,2)="06")*(MID('[1]A receer iluminação'!$E$2:$E$271,7,4)="2026")*('[1]A receer iluminação'!$D$2:$D$271))} -> 103947.86 | D91: {=SUMPRODUCT((MID('[1]a pagar iluminação'!$G$2:$G$384,4,2)="06")*(MID('[1]a pagar iluminação'!$G$2:$G$384,7,4)="2026")*('[1]a pagar iluminação'!$F$2:$F$384))} -> 105849.64 | E91: =C91-D91 -> -1901.78 | H91: 46199 | I91: {=SUMPRODUCT((VALUE(MID('[1]a reverber importação'!$G$2:$G$40,4,2))=6)*(VALUE(MID('[1]a reverber importação'!$G$2:$G$40,7,4))=2026)*('[1]a reverber importação'!$F$2:$F$40))} -> 70252.61 | J91: {=SUMPRODUCT((VALUE(MID('[1]a pagar importaçãp'!$G$2:$G$55,4,2))=6)*(VALUE(MID('[1]a pagar importaçãp'!$G$2:$G$55,7,4))=2026)*('[1]a pagar importaçãp'!$F$2:$F$55))} -> 25391.83 | K91: =I91-J91 -> 44860.78
B92: jul/26 | C92: {=SUMPRODUCT((MID('[1]A receer iluminação'!$E$2:$E$271,4,2)="07")*(MID('[1]A receer iluminação'!$E$2:$E$271,7,4)="2026")*('[1]A receer iluminação'!$D$2:$D$271))} -> 25437.6 | D92: {=SUMPRODUCT((MID('[1]a pagar iluminação'!$G$2:$G$384,4,2)="07")*(MID('[1]a pagar iluminação'!$G$2:$G$384,7,4)="2026")*('[1]a pagar iluminação'!$F$2:$F$384))} -> 55832.64 | E92: =C92-D92 -> -30395.04 | H92: 46229 | I92: {=SUMPRODUCT((VALUE(MID('[1]a reverber importação'!$G$2:$G$40,4,2))=7)*(VALUE(MID('[1]a reverber importação'!$G$2:$G$40,7,4))=2026)*('[1]a reverber importação'!$F$2:$F$40))} -> 7431.23 | J92: {=SUMPRODUCT((VALUE(MID('[1]a pagar importaçãp'!$G$2:$G$55,4,2))=7)*(VALUE(MID('[1]a pagar importaçãp'!$G$2:$G$55,7,4))=2026)*('[1]a pagar importaçãp'!$F$2:$F$55))} -> 21657.83 | K92: =I92-J92 -> -14226.6
B93: ago/26 | C93: {=SUMPRODUCT((MID('[1]A receer iluminação'!$E$2:$E$271,4,2)="08")*(MID('[1]A receer iluminação'!$E$2:$E$271,7,4)="2026")*('[1]A receer iluminação'!$D$2:$D$271))} -> 3883.53 | D93: {=SUMPRODUCT((MID('[1]a pagar iluminação'!$G$2:$G$384,4,2)="08")*(MID('[1]a pagar iluminação'!$G$2:$G$384,7,4)="2026")*('[1]a pagar iluminação'!$F$2:$F$384))} -> 51118.63 | E93: =C93-D93 -> -47235.1 | H93: ago/26 | I93: {=SUMPRODUCT((VALUE(MID('[1]a reverber importação'!$G$2:$G$40,4,2))=8)*(VALUE(MID('[1]a reverber importação'!$G$2:$G$40,7,4))=2026)*('[1]a reverber importação'!$F$2:$F$40))} -> 516.33 | J93: {=SUMPRODUCT((VALUE(MID('[1]a pagar importaçãp'!$G$2:$G$55,4,2))=8)*(VALUE(MID('[1]a pagar importaçãp'!$G$2:$G$55,7,4))=2026)*('[1]a pagar importaçãp'!$F$2:$F$55))} -> 11438.66 | K93: =I93-J93 -> -10922.33
B94: set/26 | C94: {=SUMPRODUCT((MID('[1]A receer iluminação'!$E$2:$E$271,4,2)="09")*(MID('[1]A receer iluminação'!$E$2:$E$271,7,4)="2026")*('[1]A receer iluminação'!$D$2:$D$271))} -> 0 | D94: {=SUMPRODUCT((MID('[1]a pagar iluminação'!$G$2:$G$384,4,2)="09")*(MID('[1]a pagar iluminação'!$G$2:$G$384,7,4)="2026")*('[1]a pagar iluminação'!$F$2:$F$384))} -> 51118.63 | E94: =C94-D94 -> -51118.63 | H94: set/26 | I94: {=SUMPRODUCT((VALUE(MID('[1]a reverber importação'!$G$2:$G$40,4,2))=9)*(VALUE(MID('[1]a reverber importação'!$G$2:$G$40,7,4))=2026)*('[1]a reverber importação'!$F$2:$F$40))} -> 0 | J94: {=SUMPRODUCT((VALUE(MID('[1]a pagar importaçãp'!$G$2:$G$55,4,2))=9)*(VALUE(MID('[1]a pagar importaçãp'!$G$2:$G$55,7,4))=2026)*('[1]a pagar importaçãp'!$F$2:$F$55))} -> 11438.66 | K94: =I94-J94 -> -11438.66
B95: TOTAL | C95: =SUM(C90:C94) -> 293410.82 | D95: =SUM(D90:D94) -> 418814.01 | E95: =C95-D95 -> -125403.19 | H95: TOTAL | I95: =SUM(I90:I94) -> 146890.8 | J95: =SUM(J90:J94) -> 88823.64 | K95: =I95-J95 -> 58067.16
C105: =(D110/D111) -> 3125
C106: =C105+(1+0.65*0.1075) -> 3126.0699
C107: Max Iluminação | I107: Empréstimo Max Importação
C109: Capital de Giro Bradesco | E109: Capital de Giro Itaú | I109: Pronamp | K109: Capital de Giro FGI
C110: Valor Total | D110: 150000 | E110: Valor Total | F110: 92187.62 | I110: Valor Total inicial | J110: 116965.8 | K110: Valor Total inicial | L110: 139755.03
C111: Total de parcelas | D111: 48 | E111: Total de parcelas | F111: 48 | I111: Total de parcelas | J111: 48 | K111: Total de parcelas | L111: 48
C112: Parcelas pagas | D112: =COUNTIF('SAIDAS-FIN-ilumi'!C:C,"EMPRÉSTIMO CAPITAL DE GIRO BRADESCO")+41 -> 46 | E112: Parcelas pagas | F112: =COUNTIF('SAIDAS-FIN-ilumi'!C:C,"EMPRÉSTIMO CAPITAL DE GIRO ITAÚ")+2 -> 4 | I112: Parcelas pagas | J112: =COUNTIF('Saidas-fin-import'!E:E,"EMPRÉSTIMO PRONAMP")+14 -> 14 | K112: Parcelas pagas | L112: =COUNTIF('Saidas-fin-import'!E:E,"EMPRÉSTIMOS FGI")+2 -> 2
C113: Valor Parcela c/ juros | D113: =C105+C106 -> 6251.0699 | E113: Valor Parcela c/ juros | F113: =(F110/F111)*(1+0.49%+10.75%) -> 2136.4481 | I113: Valor Parcela c/ juros | J113: =(J110/J111)*(1+1.62%+10.75%) -> 2738.2181 | K113: Valor Parcela c/ juros | L113: =(L110/L111)*(1+1.62%) -> 2958.7304
C114: Parcelas restantes | D114: =D111-D112 -> 2 | E114: Parcelas restantes | F114: =F111-F112 -> 44 | I114: Parcelas restantes | J114: =J111-J112 -> 34 | K114: Parcelas restantes | L114: =L111-L112 -> 46
C115: Valor restante | D115: =SUMIF('SAIDAS-FIN-ilumi'!C:C,"EMPRÉSTIMO CAPITAL DE GIRO BRADESCO",'SAIDAS-FIN-ilumi'!D:D) -> 31535 | E115: Valor restante | F115: =F110-F116 -> 82811.23 | I115: Valor pago | J115: =SUMIF('Saidas-fin-import'!E:E,"EMPRÉSTIMO PRONAMP",'Saidas-fin-import'!F:F)+47315.47 -> 47315.47 | K115: Valor pago | L115: =SUMIF('Saidas-fin-import'!E:E,"EMPRÉSTIMOS FGI",'Saidas-fin-import'!F:F)+5275.86 -> 5275.86
C116: Valor PAGO | D116: =D110-D115 -> 118465 | E116: Valor pago | F116: =SUMIF('SAIDAS-FIN-ilumi'!C:C,"EMPRÉSTIMO CAPITAL DE GIRO ITAÚ",'SAIDAS-FIN-ilumi'!D:D)+4272.9 -> 9376.39 | I116: Valor restante | J116: =J110-J115 -> 69650.33 | K116: Valor restante | L116: =L110-L115 -> 134479.17
C117: Acrescimo | D117: =(D115+D116)*0.75 -> 112500 | E117: Acrescimo | F117: =(F116+F115)*0.59 -> 54390.696 | I117: Acrescimo | J117: =(J115+J116)*1.172 -> 137083.92 | K117: Acrescimo | L117: =(L115+L116)*1.62 -> 226403.15
C118: valor final com acrescimmo | D118: =D110+D117 -> 262500 | E118: valor final com acrescimmo | F118: =F110+F117 -> 146578.32 | I118: Valor final com acrescimmo | J118: =J110+J117 -> 254049.72 | L118: =L110+L117 -> 366158.18
C119: Data inicial | D119: 44988 | E119: Data inicial | F119: 46106 | I119: Data inicial | J119: 45994 | K119: Data inicial | L119: 46024
C120: Data Final prevista | D120: =EDATE(D119,D111) -> 46449 | E120: Data Final prevista | F120: =EDATE(F119,F111) -> 47567 | I120: Data Final prevista | J120: 47133 | K120: Data Final prevista | L120: 47455

Sheet Planilha2
A1: Linha do Tempo | B1: Valores | C1: Previsão | D1: Limite de Confiança Inferior | E1: Limite de Confiança Superior
A2: 45658 | B2: -16301.63
A3: 45689 | B3: 18052.66
A4: 45717 | B4: -23093.01
A5: 45748 | B5: 21853.31
A6: 45778 | B6: 26271.78
A7: 45809 | B7: -41655.32
A8: 45839 | B8: -9105.71
A9: 45870 | B9: -8067.27
A10: 45901 | B10: -1357.72
A11: 45931 | B11: 10984.5
A12: 45962 | B12: 1155.56
A13: 45992 | B13: 19189.27
... A16: 46082 | B16: -9543.96
A17: 46113 | B17: -17193.62 | C17: -17193.62 | D17: -17193.62 | E17: -17193.62
A18: 46143 | C18: =_xlfn.FORECAST.ETS(A18,$B$2:$B$17,$A$2:$A$17,1,1) -> -3062.1006 | D18: =C18-_xlfn.FORECAST.ETS.CONFINT(A18,$B$2:$B$17,$A$2:$A$17,0.95,1,1) -> -43764.003 | E18: =C18+_xlfn.FORECAST.ETS.CONFINT(A18,$B$2:$B$17,$A$2:$A$17,0.95,1,1) -> 37639.802
A19: 46174 | C19: =_xlfn.FORECAST.ETS(A19,$B$2:$B$17,$A$2:$A$17,1,1) -> -2984.5892 | D19: =C19-_xlfn.FORECAST.ETS.CONFINT(A19,$B$2:$B$17,$A$2:$A$17,0.95,1,1) -> -44013.419 | E19: =C19+_xlfn.FORECAST.ETS.CONFINT(A19,$B$2:$B$17,$A$2:$A$17,0.95,1,1) -> 38044.241
A20: 46204 | C20: =_xlfn.FORECAST.ETS(A20,$B$2:$B$17,$A$2:$A$17,1,1) -> -2907.0778 | D20: =C20-_xlfn.FORECAST.ETS.CONFINT(A20,$B$2:$B$17,$A$2:$A$17,0.95,1,1) -> -44265.358 | E20: =C20+_xlfn.FORECAST.ETS.CONFINT(A20,$B$2:$B$17,$A$2:$A$17,0.95,1,1) -> 38451.203
A21: 46235 | C21: =_xlfn.FORECAST.ETS(A21,$B$2:$B$17,$A$2:$A$17,1,1) -> -2829.5664 | D21: =C21-_xlfn.FORECAST.ETS.CONFINT(A21,$B$2:$B$17,$A$2:$A$17,0.95,1,1) -> -44519.8 | E21: =C21+_xlfn.FORECAST.ETS.CONFINT(A21,$B$2:$B$17,$A$2:$A$17,0.95,1,1) -> 38860.667
A22: 46266 | C22: =_xlfn.FORECAST.ETS(A22,$B$2:$B$17,$A$2:$A$17,1,1) -> -2752.0551 | D22: =C22-_xlfn.FORECAST.ETS.CONFINT(A22,$B$2:$B$17,$A$2:$A$17,0.95,1,1) -> -44776.725 | E22: =C22+_xlfn.FORECAST.ETS.CONFINT(A22,$B$2:$B$17,$A$2:$A$17,0.95,1,1) -> 39272.615
A23: 46296 | C23: =_xlfn.FORECAST.ETS(A23,$B$2:$B$17,$A$2:$A$17,1,1) -> -2674.5437 | D23: =C23-_xlfn.FORECAST.ETS.CONFINT(A23,$B$2:$B$17,$A$2:$A$17,0.95,1,1) -> -45036.113 | E23: =C23+_xlfn.FORECAST.ETS.CONFINT(A23,$B$2:$B$17,$A$2:$A$17,0.95,1,1) -> 39687.026

Sheet Planilha4
B3: Mês | C3: Entradas | D3: Saídas | E3: Resultado | F3: % da Receita | I3: Mês | J3: Entradas | K3: Saídas | L3: Resultado | M3: % da Receita | P3: Entradas | Q3: Saidas | R3: Total
B4: Janeiro | C4: R$ 19.591,87 | D4: R$ 19.373,98 | E4: R$ 217,89 | F4: 2.4% | I4: Janeiro | J4: R$ 159.260,53 | K4: R$ 175.562,16 | L4: -R$ 16.301,63 | M4: 6.7% | O4: 45658 | P4: 159260.53 | Q4: 175562.16 | R4: =P4-Q4 -> -16301.63 | S4: =_xlfn.PERCENTOF(P4,Q4) -> 0.90714611 | T4: 1.0188
B5: Fevereiro | C5: R$ 57.998,11 | D5: R$ 50.024,99 | E5: R$ 7.973,12 | F5: 7.2% | I5: Fevereiro | J5: R$ 205.465,70 | K5: R$ 187.413,04 | L5: R$ 18.052,66 | M5: 8.7% | O5: 45689 | P5: 205465.7 | Q5: 187413.04 | R5: =P5-Q5 -> 18052.66 | S5: =_xlfn.PERCENTOF(P5,Q5) -> 1.0963255
B6: Março | C6: R$ 56.487,68 | D6: R$ 51.121,51 | E6: R$ 5.366,17 | F6: 7.1% | I6: Março | J6: R$ 212.696,97 | K6: R$ 235.789,98 | L6: -R$ 23.093,01 | M6: 9.0% | O6: 45717 | P6: 212696.97 | Q6: 235789.98 | R6: =P6-Q6 -> -23093.01 | S6: =_xlfn.PERCENTOF(P6,Q6) -> 0.90206111
B7: Abril | C7: R$ 61.782,70 | D7: R$ 82.130,25 | E7: -R$ 20.347,55 | F7: 7.7% | I7: Abril | J7: R$ 225.882,05 | K7: R$ 204.028,74 | L7: R$ 21.853,31 | M7: 9.5% | O7: 45748 | P7: 225882.05 | Q7: 204028.74 | R7: =P7-Q7 -> 21853.31 | S7: =_xlfn.PERCENTOF(P7,Q7) -> 1.107109
B8: Maio | C8: R$ 39.163,78 | D8: R$ 28.422,61 | E8: R$ 10.741,17 | F8: 4.9% | I8: Maio | J8: R$ 252.020,40 | K8: R$ 225.748,62 | L8: R$ 26.271,78 | M8: 10.6% | O8: 45778 | P8: 252020.4 | Q8: 225748.62 | R8: =P8-Q8 -> 26271.78 | S8: =_xlfn.PERCENTOF(P8,Q8) -> 1.1163763
B9: Junho | C9: R$ 17.138,87 | D9: R$ 30.422,90 | E9: -R$ 13.284,03 | F9: 2.1% | I9: Junho | J9: R$ 159.826,26 | K9: R$ 201.481,58 | L9: -R$ 41.655,32 | M9: 6.7% | O9: 45809 | P9: 159826.26 | Q9: 201481.58 | R9: =P9-Q9 -> -41655.32 | S9: =_xlfn.PERCENTOF(P9,Q9) -> 0.79325495
B10: Julho | C10: R$ 68.605,59 | D10: R$ 65.737,81 | E10: R$ 2.867,78 | F10: 8.6% | I10: Julho | J10: R$ 205.248,67 | K10: R$ 214.354,38 | L10: -R$ 9.105,71 | M10: 8.7% | O10: 45839 | P10: 205248.67 | Q10: 214354.38 | R10: =P10-Q10 -> -9105.71 | S10: =_xlfn.PERCENTOF(P10,Q10) -> 0.9575203
B11: Agosto | C11: R$ 84.229,75 | D11: R$ 84.871,12 | E11: -R$ 641,37 | F11: 10.5% | I11: Agosto | J11: R$ 183.735,51 | K11: R$ 191.802,78 | L11: -R$ 8.067,27 | M11: 7.8% | O11: 45870 | P11: 183735.51 | Q11: 191802.78 | R11: =P11-Q11 -> -8067.27 | S11: =_xlfn.PERCENTOF(P11,Q11) -> 0.95793977
B12: Setembro | C12: R$ 126.144,65 | D12: R$ 117.673,30 | E12: R$ 8.471,35 | F12: 15.7% | I12: Setembro | J12: 202938.1 | K12: 204295.82 | L12: =J12-K12 -> -1357.72 | M12: 8.6% | O12: 45901 | P12: 202938.1 | Q12: 204295.82 | R12: =P12-Q12 -> -1357.72 | S12: =_xlfn.PERCENTOF(P12,Q12) -> 0.99335415
B13: Outubro | C13: R$ 61.637,75 | D13: R$ 70.384,44 | E13: -R$ 8.746,69 | F13: 7.7% | I13: Outubro | J13: 178.379,29 | K13: R$ 167.394,79 | L13: =J13-K13 -> #VALUE! | M13: 7.5% | O13: 45931 | P13: 178379.29 | Q13: 167394.79 | R13: =P13-Q13 -> 10984.5 | S13: =_xlfn.PERCENTOF(P13,Q13) -> 1.0656203
B14: Novembro | C14: R$ 58.123,77 | D14: R$ 57.720,85 | E14: R$ 402,92 | F14: 7.3% | I14: Novembro | J14: 184310.95 | K14: R$ 183.155,39 | L14: =J14-K14 -> #VALUE! | M14: 7.8% | O14: 45962 | P14: 184310.95 | Q14: 183155.39 | R14: =P14-Q14 -> 1155.56 | S14: =_xlfn.PERCENTOF(P14,Q14) -> 1.0063092
B15: Dezembro | C15: R$ 150.258,42 | D15: R$ 79.092,13 | E15: R$ 71.166,29 | F15: 18.8% | I15: Dezembro | J15: 198779.59 | K15: 179.590,32 | L15: =J15-K15 -> #VALUE! | M15: 8.4% | O15: 45992 | P15: 198779.59 | Q15: 179590.32 | R15: =P15-Q15 -> 19189.27 | S15: =_xlfn.PERCENTOF(P15,Q15) -> 1.1068502
I16: 46023 | J16: =SUMIF('ENTRADAS - FIN - ilumi'!F:F,"Janeiro",'ENTRADAS - FIN - ilumi'!D:D) -> 132275.4 | K16: =SUMIF('SAIDAS-FIN-ilumi'!F:F,"Janeiro",'SAIDAS-FIN-ilumi'!D:D) -> 116350.31 | L16: =D13+J16-K16 -> #VALUE! | M16: =IF(D13=0,0,(L16-D13)/D13) -> #VALUE! | O16: 46023 | P16: 132275.4 | Q16: 116350.31 | R16: =P16-Q16 -> 15925.09 | S16: =_xlfn.PERCENTOF(P16,Q16) -> 1.1368719
I17: 46054 | J17: =SUMIF('ENTRADAS - FIN - ilumi'!F:F,"Fevereiro",'ENTRADAS - FIN - ilumi'!D:D) -> 126679.25 | K17: =SUMIF('SAIDAS-FIN-ilumi'!F:F,"Fevereiro",'SAIDAS-FIN-ilumi'!D:D) -> 133410.26 | L17: =L16+J17-K17 -> #VALUE! | M17: =IF(D13=0,0,(L17-D13)/D13) -> #VALUE! | O17: 46054 | P17: 126679.25 | Q17: 133410.26 | R17: =P17-Q17 -> -6731.01 | S17: =_xlfn.PERCENTOF(P17,Q17) -> 0.94954653
I18: 46082 | J18: =SUMIF('ENTRADAS - FIN - ilumi'!F:F,"Março",'ENTRADAS - FIN - ilumi'!D:D) -> 183424.12 | K18: =SUMIF('SAIDAS-FIN-ilumi'!F:F,"Março",'SAIDAS-FIN-ilumi'!D:D) -> 192968.08 | L18: =L17+J18-K18 -> #VALUE! | M18: =IF(D13=0,0,(L18-D13)/D13) -> #VALUE! | O18: 46082 | P18: 183424.12 | Q18: 192968.08 | R18: =P18-Q18 -> -9543.96 | S18: =_xlfn.PERCENTOF(P18,Q18) -> 0.95054125
I19: 46113 | J19: =SUMIF('ENTRADAS - FIN - ilumi'!F:F,"Abril",'ENTRADAS - FIN - ilumi'!D:D) -> 214380.68 | K19: =SUMIF('SAIDAS-FIN-ilumi'!F:F,"Abril",'SAIDAS-FIN-ilumi'!D:D) -> 231574.3 | L19: =L18+J19-K19 -> #VALUE! | M19: =IF(D13=0,0,(L19-D13)/D13) -> #VALUE! | O19: 46113 | P19: 214380.68 | Q19: 231574.3 | R19: =P19-Q19 -> -17193.62 | S19: =_xlfn.PERCENTOF(P19,Q19) -> 0.92575333
C20: 19591.87 | D20: 19373.98 | E20: =C20-D20 -> 217.89 | O20: 46143 | P20: =_xlfn.FORECAST.LINEAR(O20,P8:P19,O8:O19)*1.083 -> 175445.05 | Q20: =AVERAGE(Q8:Q19) -> 186843.89 | R20: =P20-Q20 -> -11398.833 | S20: =_xlfn.PERCENTOF(P20,Q20) -> 0.93899274
C21: 57998.11 | D21: 50024.99 | E21: =C21-D21 -> 7973.12 | I21: 45658 | J21: =C20+P4 -> 178852.4 | K21: =D20+Q4 -> 194936.14 | L21: =J21-K21 -> -16083.74 | O21: 46174 | P21: =_xlfn.FORECAST.LINEAR(O21,P9:P20,O9:O20)*1.083 -> 187195.64 | Q21: =AVERAGE(Q9:Q20) -> 183601.82 | R21: =P21-Q21 -> 3593.8143 | S21: =_xlfn.PERCENTOF(P21,Q21) -> 1.019574
C22: 56487.68 | D22: 51121.51 | E22: =C22-D22 -> 5366.17 | I22: 45689 | J22: =C21+P5 -> 263463.81 | K22: =D21+Q5 -> 237438.03 | L22: =J22-K22 -> 26025.78 | O22: 46204 | P22: =_xlfn.FORECAST.LINEAR(O22,P10:P21,O10:O21)*1.083 -> 185870.74 | Q22: =AVERAGE(Q10:Q21) -> 182111.85 | R22: =P22-Q22 -> 3758.8907 | S22: =_xlfn.PERCENTOF(P22,Q22) -> 1.0206406
C23: 61782.7 | D23: 82130.25 | E23: =C23-D23 -> -20347.55 | I23: 45717 | J23: =C22+P6 -> 269184.65 | K23: =D22+Q6 -> 286911.49 | L23: =J23-K23 -> -17726.84 | O23: 46235 | P23: =_xlfn.FORECAST.LINEAR(O23,P11:P22,O11:O22)*1.083 -> 193165.15 | Q23: =AVERAGE(Q11:Q22) -> 179424.97 | R23: =P23-Q23 -> 13740.178 | S23: =_xlfn.PERCENTOF(P23,Q23) -> 1.076579
C24: 39163.78 | D24: 28422.61 | E24: =C24-D24 -> 10741.17 | I24: 45748 | J24: =C23+P7 -> 287664.75 | K24: =D23+Q7 -> 286158.99 | L24: =J24-K24 -> 1505.76
C25: 17138.87 | D25: 30422.9 | E25: =C25-D25 -> -13284.03 | I25: 45778 | J25: =C24+P8 -> 291184.18 | K25: =D24+Q8 -> 254171.23 | L25: =J25-K25 -> 37012.95
C26: 68605.59 | D26: 65737.81 | E26: =C26-D26 -> 2867.78 | I26: 45809 | J26: =C25+P9 -> 176965.13 | K26: =D25+Q9 -> 231904.48 | L26: =J26-K26 -> -54939.35
C27: 84229.75 | D27: 84871.12 | E27: =C27-D27 -> -641.37 | I27: 45839 | J27: =C26+P10 -> 273854.26 | K27: =D26+Q10 -> 280092.19 | L27: =J27-K27 -> -6237.93
C28: 126144.65 | D28: 117673.3 | E28: =C28-D28 -> 8471.35 | I28: 45870 | J28: =C27+P11 -> 267965.26 | K28: =D27+Q11 -> 276673.9 | L28: =J28-K28 -> -8708.64
C29: 61637.75 | D29: 70384.44 | E29: =C29-D29 -> -8746.69 | I29: 45901 | J29: =C28+P12 -> 329082.75 | K29: =D28+Q12 -> 321969.12 | L29: =J29-K29 -> 7113.63
C30: 58123.77 | D30: 57720.85 | E30: =C30-D30 -> 402.92 | I30: 45931 | J30: =C29+P13 -> 240017.04 | K30: =D29+Q13 -> 237779.23 | L30: =J30-K30 -> 2237.81
C31: 150258.42 | D31: 79092.13 | E31: =C31-D31 -> 71166.29 | I31: 45962 | J31: =C30+P14 -> 242434.72 | K31: =D30+Q14 -> 240876.24 | L31: =J31-K31 -> 1558.48
C32: 13593.52 | D32: 74876.93 | E32: =C32-D32 -> -61283.41 | I32: 45992 | J32: =C31+P15 -> 349038.01 | K32: =D31+Q15 -> 258682.45 | L32: =J32-K32 -> 90355.56
C33: 37091.38 | D33: 44764.38 | E33: =C33-D33 -> -7673 | I33: 46023 | J33: =C32+P16 -> 145868.92 | K33: =D32+Q16 -> 191227.24 | L33: =J33-K33 -> -45358.32
C34: 37723.49 | D34: 35226.35 | E34: =C34-D34 -> 2497.14 | I34: 46054 | J34: =C33+P17 -> 163770.63 | K34: =D33+Q17 -> 178174.64 | L34: =J34-K34 -> -14404.01
C35: 105609.12 | D35: 108035.78 | E35: =C35-D35 -> -2426.66 | I35: 46082 | J35: =C34+P18 -> 221147.61 | K35: =D34+Q18 -> 228194.43 | L35: =J35-K35 -> -7046.82
I36: 46113 | J36: =C35+P19 -> 319989.8 | K36: =D35+Q19 -> 339610.08 | L36: =J36-K36 -> -19620.28
I37: 46143 | J37: =_xlfn.FORECAST.LINEAR(I37,J21:J36,I21:I36)*1.083 -> 269520.26 | K37: =AVERAGE(K21:K36) -> 252799.99 | L37: =J37-K37 -> 16720.268
I38: 46174 | J38: =_xlfn.FORECAST.LINEAR(I38,J22:J37,I22:I37)*1.083 -> 262741.42 | K38: =AVERAGE(K22:K37) -> 256416.48 | L38: =J38-K38 -> 6324.9333
I39: 46204 | J39: =_xlfn.FORECAST.LINEAR(I39,J23:J38,I23:I38)*1.083 -> 265397.97 | K39: =AVERAGE(K23:K38) -> 257602.64 | L39: =J39-K39 -> 7795.3366
I40: 46235 | J40: =_xlfn.FORECAST.LINEAR(I40,J24:J39,I24:I39)*1.083 -> 269643.02 | K40: =AVERAGE(K24:K39) -> 255770.83 | L40: =J40-K40 -> 13872.19
I41: 46266 | J41: =_xlfn.FORECAST.LINEAR(I41,J25:J40,I25:I40)*1.083 -> 278206.61 | K41: =AVERAGE(K25:K40) -> 253871.57 | L41: =J41-K41 -> 24335.037

Sheet Planilha5
A1: Linha do Tempo | B1: Valores | C1: Previsão | D1: Limite de Confiança Inferior | E1: Limite de Confiança Superior
A2: 45658 | B2: 178852.4
A3: 45689 | B3: 263463.81
A4: 45717 | B4: 269184.65
A5: 45748 | B5: 287664.75
A6: 45778 | B6: 291184.18
A7: 45809 | B7: 176965.13
A8: 45839 | B8: 273854.26
A9: 45870 | B9: 267965.26
A10: 45901 | B10: 329082.75
A11: 45931 | B11: 240017.04
A12: 45962 | B12: 242434.72
A13: 45992 | B13: 349038.01
... A16: 46082 | B16: 221147.61
A17: 46113 | B17: 319989.8 | C17: 319989.8 | D17: 319989.8 | E17: 319989.8
A18: 46143 | C18: =_xlfn.FORECAST.ETS(A18,$B$2:$B$17,$A$2:$A$17,1,1) -> 263468.53 | D18: =C18-_xlfn.FORECAST.ETS.CONFINT(A18,$B$2:$B$17,$A$2:$A$17,0.95,1,1) -> 121874.18 | E18: =C18+_xlfn.FORECAST.ETS.CONFINT(A18,$B$2:$B$17,$A$2:$A$17,0.95,1,1) -> 405062.88
A19: 46174 | C19: =_xlfn.FORECAST.ETS(A19,$B$2:$B$17,$A$2:$A$17,1,1) -> 263381.68 | D19: =C19-_xlfn.FORECAST.ETS.CONFINT(A19,$B$2:$B$17,$A$2:$A$17,0.95,1,1) -> 105011.01 | E19: =C19+_xlfn.FORECAST.ETS.CONFINT(A19,$B$2:$B$17,$A$2:$A$17,0.95,1,1) -> 421752.35
A20: 46204 | C20: =_xlfn.FORECAST.ETS(A20,$B$2:$B$17,$A$2:$A$17,1,1) -> 263294.83 | D20: =C20-_xlfn.FORECAST.ETS.CONFINT(A20,$B$2:$B$17,$A$2:$A$17,0.95,1,1) -> 89704.259 | E20: =C20+_xlfn.FORECAST.ETS.CONFINT(A20,$B$2:$B$17,$A$2:$A$17,0.95,1,1) -> 436885.41
A21: 46235 | C21: =_xlfn.FORECAST.ETS(A21,$B$2:$B$17,$A$2:$A$17,1,1) -> 263207.98 | D21: =C21-_xlfn.FORECAST.ETS.CONFINT(A21,$B$2:$B$17,$A$2:$A$17,0.95,1,1) -> 75574.685 | E21: =C21+_xlfn.FORECAST.ETS.CONFINT(A21,$B$2:$B$17,$A$2:$A$17,0.95,1,1) -> 450841.28

Sheet Max Led Consolidada
A1: Max Led consolidada
A4: DRE Financeiro | D4: Período Inicial: | E4: =IF(B8="ANUAL",DATE(2026,1,1),DATE(2026,MATCH(B8,{"JANEIRO";"FEVEREIRO";"MARÇO";"ABRIL";"MAIO";"JUNHO";"JULHO";"AGOSTO";"SETEMBRO";"OUTUBRO";"NOVEMBRO";"DEZEMBRO"},0),1)) -> 46143 | H4: DRE NFE | L4: Período Inicial: | M4: =IF(I8="ANUAL",DATE(2026,1,1),DATE(2026,MATCH(I8,{"JANEIRO";"FEVEREIRO";"MARÇO";"ABRIL";"MAIO";"JUNHO";"JULHO";"AGOSTO";"SETEMBRO";"OUTUBRO";"NOVEMBRO";"DEZEMBRO"},0),1)) -> 46023 | R4: Previsões financeiro Max Led Conjunto
D5: Período Final: | E5: =IF(B8="ANUAL",DATE(2026,12,31),EOMONTH(DATE(2026,MATCH(B8,{"JANEIRO";"FEVEREIRO";"MARÇO";"ABRIL";"MAIO";"JUNHO";"JULHO";"AGOSTO";"SETEMBRO";"OUTUBRO";"NOVEMBRO";"DEZEMBRO"},0),1),0)) -> 46173 | L5: Período Final: | M5: =IF(I8="ANUAL",DATE(2026,12,31),EOMONTH(DATE(2026,MATCH(I8,{"JANEIRO";"FEVEREIRO";"MARÇO";"ABRIL";"MAIO";"JUNHO";"JULHO";"AGOSTO";"SETEMBRO";"OUTUBRO";"NOVEMBRO";"DEZEMBRO"},0),1),0)) -> 46387 | S5: Receita | T5: Saidas | U5: Total | X5: Mês | Y5: A Receber Iluminação | Z5: A Pagar Iluminação | AA5: Saldo
R6: 45658 | S6: 178852.4 | T6: 194936.14 | U6: -16083.74 | X6: mai/26 | Y6: {=SUMPRODUCT((MID('[1]A receer iluminação'!$E$2:$E$271,4,2)="05")*(MID('[1]A receer iluminação'!$E$2:$E$271,7,4)="2026")*('[1]A receer iluminação'!$D$2:$D$271))} -> 160141.83 | Z6: {=SUMPRODUCT((MID('[1]a pagar iluminação'!$G$2:$G$384,4,2)="05")*(MID('[1]a pagar iluminação'!$G$2:$G$384,7,4)="2026")*('[1]a pagar iluminação'!$F$2:$F$384))} -> 154894.47 | AA6: =Y6-Z6 -> 5247.36
D7: RECEITA BRUTA | E7: =SUMIFS('ENTRADAS - FIN - ilumi'!D:D,'ENTRADAS - FIN - ilumi'!A:A,">="&E4,'ENTRADAS - FIN - ilumi'!A:A,"<="&E5)+SUMIFS('Entradas- fin- import'!D:D,'Entradas- fin- import'!A:A,">="&E4,'Entradas- fin- import'!A:A,"<="&E5) -> 234006.5 | L7: RECEITA BRUTA | M7: =SUMIFS('SAÍDA NFE ILUMI'!D:D,'SAÍDA NFE ILUMI'!A:A,">="&M4,'SAÍDA NFE ILUMI'!A:A,"<="&M5)+SUMIFS('Saídas-NFE-import'!D:D,'Saídas-NFE-import'!A:A,">="&M4,'Saídas-NFE-import'!A:A,"<="&M5) -> 1120588.9 | R7: 45689 | S7: 263463.81 | T7: 237438.03 | U7: 26025.78 | X7: jun/26 | Y7: {=SUMPRODUCT((MID('[1]A receer iluminação'!$E$2:$E$271,4,2)="06")*(MID('[1]A receer iluminação'!$E$2:$E$271,7,4)="2026")*('[1]A receer iluminação'!$D$2:$D$271))} -> 103947.86 | Z7: {=SUMPRODUCT((MID('[1]a pagar iluminação'!$G$2:$G$384,4,2)="06")*(MID('[1]a pagar iluminação'!$G$2:$G$384,7,4)="2026")*('[1]a pagar iluminação'!$F$2:$F$384))} -> 105849.64 | AA7: =Y7-Z7 -> -1901.78
A8: Mês | B8: Maio | D8: (-) IMPOSTOS (Simples Nacional) | E8: =SUMIFS('SAIDAS-FIN-ilumi'!D:D,'SAIDAS-FIN-ilumi'!C:C,"IMPOSTOS",'SAIDAS-FIN-ilumi'!A:A,">="&E4,'SAIDAS-FIN-ilumi'!A:A,"<="&E5)+SUMIFS('Saidas-fin-import'!D:D,'Saidas-fin-import'!C:C,"IMPOSTOS",'Saidas-fin-import'!A:A,">="&E4,'Saidas-fin-import'!A:A,"<="&E5) -> 21474.37 | H8: Mês | I8: Anual | L8: RECEITA SNF | M8: =SUMIFS('SAÍDA NFE ILUMI'!I:I,'SAÍDA NFE ILUMI'!J:J,"SNF",'SAÍDA NFE ILUMI'!F:F,">="&M4,'SAÍDA NFE ILUMI'!F:F,"<="&M5)+SUMIFS('Saídas-NFE-import'!D:D,'Saídas-NFE-import'!E:E,"SNF",'Saídas-NFE-import'!A:A,">="&M4,'Saídas-NFE-import'!A:A,"<="&M5) -> 23074.52 | R8: 45717 | S8: 269184.65 | T8: 286911.49 | U8: -17726.84 | X8: jul/26 | Y8: {=SUMPRODUCT((MID('[1]A receer iluminação'!$E$2:$E$271,4,2)="07")*(MID('[1]A receer iluminação'!$E$2:$E$271,7,4)="2026")*('[1]A receer iluminação'!$D$2:$D$271))} -> 25437.6 | Z8: {=SUMPRODUCT((MID('[1]a pagar iluminação'!$G$2:$G$384,4,2)="07")*(MID('[1]a pagar iluminação'!$G$2:$G$384,7,4)="2026")*('[1]a pagar iluminação'!$F$2:$F$384))} -> 55832.64 | AA8: =Y8-Z8 -> -30395.04
D9: RECEITA LÍQUIDA | E9: =E7-E8 -> 212532.13 | L9: Total de Receitas | M9: =M7+M8 -> 1143663.4 | R9: 45748 | S9: 287664.75 | T9: 286158.99 | U9: 1505.76 | X9: ago/26 | Y9: {=SUMPRODUCT((MID('[1]A receer iluminação'!$E$2:$E$271,4,2)="08")*(MID('[1]A receer iluminação'!$E$2:$E$271,7,4)="2026")*('[1]A receer iluminação'!$D$2:$D$271))} -> 3883.53 | Z9: {=SUMPRODUCT((MID('[1]a pagar iluminação'!$G$2:$G$384,4,2)="08")*(MID('[1]a pagar iluminação'!$G$2:$G$384,7,4)="2026")*('[1]a pagar iluminação'!$F$2:$F$384))} -> 51118.63 | AA9: =Y9-Z9 -> -47235.1
L10: (-) IMPOSTOS (Simples Nacional) | M10: =M7*0.1 -> 112058.89 | R10: 45778 | S10: 291184.18 | T10: 254171.23 | U10: 37012.95 | X10: set/26 | Y10: {=SUMPRODUCT((MID('[1]A receer iluminação'!$E$2:$E$271,4,2)="09")*(MID('[1]A receer iluminação'!$E$2:$E$271,7,4)="2026")*('[1]A receer iluminação'!$D$2:$D$271))} -> 0 | Z10: {=SUMPRODUCT((MID('[1]a pagar iluminação'!$G$2:$G$384,4,2)="09")*(MID('[1]a pagar iluminação'!$G$2:$G$384,7,4)="2026")*('[1]a pagar iluminação'!$F$2:$F$384))} -> 51118.63 | AA10: =Y10-Z10 -> -51118.63
D11: (-) CUSTO DAS MERCADORIAS (FORNECEDORES) | E11: =SUMIFS('SAIDAS-FIN-ilumi'!D:D,'SAIDAS-FIN-ilumi'!C:C,"FORNECEDORES",'SAIDAS-FIN-ilumi'!A:A,">="&E4,'SAIDAS-FIN-ilumi'!A:A,"<="&E5)+SUMIFS('Saidas-fin-import'!D:D,'Saidas-fin-import'!C:C,"FORNECEDORES",'Saidas-fin-import'!A:A,">="&E4,'Saidas-fin-import'!A:A,"<="&E5) -> 110059.13 | L11: RECEITA LÍQUIDA | M11: =M9-M10 -> 1031604.5 | R11: 45809 | S11: 176965.13 | T11: 231904.48 | U11: -54939.35 | X11: TOTAL | Y11: =SUM(Y6:Y10) -> 293410.82 | Z11: =SUM(Z6:Z10) -> 418814.01 | AA11: =Y11-Z11 -> -125403.19
A12: Total | B12: =B15-B18+B23 -> 115480 | D12: LUCRO BRUTO | E12: =E9-E11 -> 102473 | H12: Total | I12: =I15-I18 -> 496307.84 | R12: 45839 | S12: 273854.26 | T12: 280092.19 | U12: -6237.93
L13: (-) CUSTO DAS MERCADORIAS (FORNECEDORES) | M13: =SUMIFS('ENTRADA NFE ILUMI'!D:D,'ENTRADA NFE ILUMI'!A:A,">="&M4,'ENTRADA NFE ILUMI'!A:A,"<="&M5)+SUMIFS('Entradas-NFE-Import'!D:D,'Entradas-NFE-Import'!A:A,">="&M4,'Entradas-NFE-Import'!A:A,"<="&M5) -> 624281.03 | R13: 45870 | S13: 267965.26 | T13: 276673.9 | U13: -8708.64 | X13: Mês | Y13: A Receber Importação | Z13: A Pagar Importação | AA13: Saldo
D14: DESPESAS OPERACIONAIS: | L14: LUCRO BRUTO | M14: =M11-M13 -> 407323.47 | R14: 45901 | S14: 329082.75 | T14: 321969.12 | U14: 7113.63 | X14: mai/26 | Y14: {=SUMPRODUCT((VALUE(MID('[1]a reverber importação'!$G$2:$G$40,4,2))=5)*(VALUE(MID('[1]a reverber importação'!$G$2:$G$40,7,4))=2026)*('[1]a reverber importação'!$F$2:$F$40))} -> 68690.63 | Z14: {=SUMPRODUCT((VALUE(MID('[1]a pagar importaçãp'!$G$2:$G$55,4,2))=5)*(VALUE(MID('[1]a pagar importaçãp'!$G$2:$G$55,7,4))=2026)*('[1]a pagar importaçãp'!$F$2:$F$55))} -> 18896.66 | AA14: =Y14-Z14 -> 49793.97
A15: Entrada | B15: =SUMIFS('ENTRADAS - FIN - ilumi'!D:D,'ENTRADAS - FIN - ilumi'!A:A,">="&E4,'ENTRADAS - FIN - ilumi'!A:A,"<="&E5)+SUMIFS('Entradas- fin- import'!D:D,'Entradas- fin- import'!A:A,">="&E4,'Entradas- fin- import'!A:A,"<="&E5) -> 234006.5 | D15: BANCO | E15: =SUMIFS('SAIDAS-FIN-ilumi'!D:D,'SAIDAS-FIN-ilumi'!C:C,"BANCO",'SAIDAS-FIN-ilumi'!A:A,">="&E4,'SAIDAS-FIN-ilumi'!A:A,"<="&E5)+SUMIFS('Saidas-fin-import'!D:D,'Saidas-fin-import'!C:C,"BANCO",'Saidas-fin-import'!A:A,">="&E4,'Saidas-fin-import'!A:A,"<="&E5) -> 892.9 | H15: VENDAS | I15: =SUMIFS('SAÍDA NFE ILUMI'!D:D,'SAÍDA NFE ILUMI'!A:A,">="&M4,'SAÍDA NFE ILUMI'!A:A,"<="&M5)+SUMIFS('Saídas-NFE-import'!D:D,'Saídas-NFE-import'!A:A,">="&M4,'Saídas-NFE-import'!A:A,"<="&M5) -> 1120588.9 | R15: 45931 | S15: 240017.04 | T15: 237779.23 | U15: 2237.81 | X15: 46199 | Y15: {=SUMPRODUCT((VALUE(MID('[1]a reverber importação'!$G$2:$G$40,4,2))=6)*(VALUE(MID('[1]a reverber importação'!$G$2:$G$40,7,4))=2026)*('[1]a reverber importação'!$F$2:$F$40))} -> 70252.61 | Z15: {=SUMPRODUCT((VALUE(MID('[1]a pagar importaçãp'!$G$2:$G$55,4,2))=6)*(VALUE(MID('[1]a pagar importaçãp'!$G$2:$G$55,7,4))=2026)*('[1]a pagar importaçãp'!$F$2:$F$55))} -> 25391.83 | AA15: =Y15-Z15 -> 44860.78
D16: BRINDES | E16: =SUMIFS('SAIDAS-FIN-ilumi'!D:D,'SAIDAS-FIN-ilumi'!C:C,"BRINDES",'SAIDAS-FIN-ilumi'!A:A,">="&E4,'SAIDAS-FIN-ilumi'!A:A,"<="&E5)+SUMIFS('Saidas-fin-import'!D:D,'Saidas-fin-import'!C:C,"BRINDES",'Saidas-fin-import'!A:A,">="&E4,'Saidas-fin-import'!A:A,"<="&E5) -> 0 | L16: DESPESAS OPERACIONAIS: | R16: 45962 | S16: 242434.72 | T16: 240876.24 | U16: 1558.48 | X16: 46229 | Y16: {=SUMPRODUCT((VALUE(MID('[1]a reverber importação'!$G$2:$G$40,4,2))=7)*(VALUE(MID('[1]a reverber importação'!$G$2:$G$40,7,4))=2026)*('[1]a reverber importação'!$F$2:$F$40))} -> 7431.23 | Z16: {=SUMPRODUCT((VALUE(MID('[1]a pagar importaçãp'!$G$2:$G$55,4,2))=7)*(VALUE(MID('[1]a pagar importaçãp'!$G$2:$G$55,7,4))=2026)*('[1]a pagar importaçãp'!$F$2:$F$55))} -> 21657.83 | AA16: =Y16-Z16 -> -14226.6
D17: CARTÃO DE CRÉDITO | E17: =SUMIFS('SAIDAS-FIN-ilumi'!D:D,'SAIDAS-FIN-ilumi'!C:C,"CARTÃO DE CRÉDITO",'SAIDAS-FIN-ilumi'!A:A,">="&E4,'SAIDAS-FIN-ilumi'!A:A,"<="&E5)+SUMIFS('Saidas-fin-import'!D:D,'Saidas-fin-import'!C:C,"CARTÃO DE CRÉDITO",'Saidas-fin-import'!A:A,">="&E4,'Saidas-fin-import'!A:A,"<="&E5) -> 12871.28 | L17: BANCO | M17: =SUMIFS('SAIDAS-FIN-ilumi'!D:D,'SAIDAS-FIN-ilumi'!C:C,"BANCO",'SAIDAS-FIN-ilumi'!A:A,">="&M4,'SAIDAS-FIN-ilumi'!A:A,"<="&M5)+SUMIFS('Saidas-fin-import'!D:D,'Saidas-fin-import'!C:C,"BANCO",'Saidas-fin-import'!A:A,">="&M4,'Saidas-fin-import'!A:A,"<="&M5) -> 2329.68 | R17: 45992 | S17: 349038.01 | T17: 258682.45 | U17: 90355.56 | X17: ago/26 | Y17: {=SUMPRODUCT((VALUE(MID('[1]a reverber importação'!$G$2:$G$40,4,2))=8)*(VALUE(MID('[1]a reverber importação'!$G$2:$G$40,7,4))=2026)*('[1]a reverber importação'!$F$2:$F$40))} -> 516.33 | Z17: {=SUMPRODUCT((VALUE(MID('[1]a pagar importaçãp'!$G$2:$G$55,4,2))=8)*(VALUE(MID('[1]a pagar importaçãp'!$G$2:$G$55,7,4))=2026)*('[1]a pagar importaçãp'!$F$2:$F$55))} -> 11438.66 | AA17: =Y17-Z17 -> -10922.33
A18: Saídas | B18: =SUMIFS('Saidas-fin-import'!D:D,'Saidas-fin-import'!A:A,">="&E4,'Saidas-fin-import'!A:A,"<="&E5)+SUMIFS('SAIDAS-FIN-ilumi'!D:D,'SAIDAS-FIN-ilumi'!A:A,">="&E4,'SAIDAS-FIN-ilumi'!A:A,"<="&E5) -> 226634.15 | D18: CONSUMO | E18: =SUMIFS('SAIDAS-FIN-ilumi'!D:D,'SAIDAS-FIN-ilumi'!C:C,"CONSUMO",'SAIDAS-FIN-ilumi'!A:A,">="&E4,'SAIDAS-FIN-ilumi'!A:A,"<="&E5)+SUMIFS('Saidas-fin-import'!D:D,'Saidas-fin-import'!C:C,"CONSUMO",'Saidas-fin-import'!A:A,">="&E4,'Saidas-fin-import'!A:A,"<="&E5) -> 180 | H18: COMPRAS | I18: =SUMIFS('Entradas-NFE-Import'!D:D,'Entradas-NFE-Import'!A:A,">="&M4,'Entradas-NFE-Import'!A:A,"<="&M5)+SUMIFS('ENTRADA NFE ILUMI'!D:D,'ENTRADA NFE ILUMI'!A:A,">="&M4,'ENTRADA NFE ILUMI'!A:A,"<="&M5) -> 624281.03 | L18: BRINDES | M18: =SUMIFS('SAIDAS-FIN-ilumi'!D:D,'SAIDAS-FIN-ilumi'!C:C,"BRINDES",'SAIDAS-FIN-ilumi'!A:A,">="&M4,'SAIDAS-FIN-ilumi'!A:A,"<="&M5)+SUMIFS('Saidas-fin-import'!D:D,'Saidas-fin-import'!C:C,"BRINDES",'Saidas-fin-import'!A:A,">="&M4,'Saidas-fin-import'!A:A,"<="&M5) -> 1327 | R18: 46023 | S18: 145868.92 | T18: 191227.24 | U18: -45358.32 | X18: set/26 | Y18: {=SUMPRODUCT((VALUE(MID('[1]a reverber importação'!$G$2:$G$40,4,2))=9)*(VALUE(MID('[1]a reverber importação'!$G$2:$G$40,7,4))=2026)*('[1]a reverber importação'!$F$2:$F$40))} -> 0 | Z18: {=SUMPRODUCT((VALUE(MID('[1]a pagar importaçãp'!$G$2:$G$55,4,2))=9)*(VALUE(MID('[1]a pagar importaçãp'!$G$2:$G$55,7,4))=2026)*('[1]a pagar importaçãp'!$F$2:$F$55))} -> 11438.66 | AA18: =Y18-Z18 -> -11438.66
D19: CONTABILIDADE | E19: =SUMIFS('SAIDAS-FIN-ilumi'!D:D,'SAIDAS-FIN-ilumi'!C:C,"CONTABILIDADE",'SAIDAS-FIN-ilumi'!A:A,">="&E4,'SAIDAS-FIN-ilumi'!A:A,"<="&E5)+SUMIFS('Saidas-fin-import'!D:D,'Saidas-fin-import'!C:C,"CONTABILIDADE",'Saidas-fin-import'!A:A,">="&E4,'Saidas-fin-import'!A:A,"<="&E5) -> 0 | L19: CARTÃO DE CRÉDITO | M19: =SUMIFS('SAIDAS-FIN-ilumi'!D:D,'SAIDAS-FIN-ilumi'!C:C,"CARTÃO DE CRÉDITO",'SAIDAS-FIN-ilumi'!A:A,">="&M4,'SAIDAS-FIN-ilumi'!A:A,"<="&M5)+SUMIFS('Saidas-fin-import'!D:D,'Saidas-fin-import'!C:C,"CARTÃO DE CRÉDITO",'Saidas-fin-import'!A:A,">="&M4,'Saidas-fin-import'!A:A,"<="&M5) -> 50110.21 | R19: 46054 | S19: 163770.63 | T19: 178174.64 | U19: -14404.01 | X19: TOTAL | Y19: =SUM(Y14:Y18) -> 146890.8 | Z19: =SUM(Z14:Z18) -> 88823.64 | AA19: =Y19-Z19 -> 58067.16
D20: DEVOLUÇÃO | E20: =SUMIFS('SAIDAS-FIN-ilumi'!D:D,'SAIDAS-FIN-ilumi'!C:C,"DEVOLUÇÃO",'SAIDAS-FIN-ilumi'!A:A,">="&E4,'SAIDAS-FIN-ilumi'!A:A,"<="&E5)+SUMIFS('Saidas-fin-import'!D:D,'Saidas-fin-import'!C:C,"DEVOLUÇÃO",'Saidas-fin-import'!A:A,">="&E4,'Saidas-fin-import'!A:A,"<="&E5) -> 0 | L20: CONSUMO | M20: =SUMIFS('SAIDAS-FIN-ilumi'!D:D,'SAIDAS-FIN-ilumi'!C:C,"CONSUMO",'SAIDAS-FIN-ilumi'!A:A,">="&M4,'SAIDAS-FIN-ilumi'!A:A,"<="&M5)+SUMIFS('Saidas-fin-import'!D:D,'Saidas-fin-import'!C:C,"CONSUMO",'Saidas-fin-import'!A:A,">="&M4,'Saidas-fin-import'!A:A,"<="&M5) -> 2063.89 | R20: 46082 | S20: 221147.61 | T20: 228194.43 | U20: -7046.82
A21: Saldo total 2025 ilu | B21: 34572.78 | D21: EMPRÉSTIMO CAPITAL DE GIRO ITAÚ | E21: =SUMIFS('SAIDAS-FIN-ilumi'!D:D,'SAIDAS-FIN-ilumi'!C:C,"EMPRÉSTIMO CAPITAL DE GIRO ITAÚ",'SAIDAS-FIN-ilumi'!A:A,">="&E4,'SAIDAS-FIN-ilumi'!A:A,"<="&E5)+SUMIFS('Saidas-fin-import'!D:D,'Saidas-fin-import'!C:C,"EMPRÉSTIMO CAPITAL DE GIRO ITAÚ",'Saidas-fin-import'!A:A,">="&E4,'Saidas-fin-import'!A:A,"<="&E5) -> 0 | L21: CONTABILIDADE | M21: =SUMIFS('SAIDAS-FIN-ilumi'!D:D,'SAIDAS-FIN-ilumi'!C:C,"CONTABILIDADE",'SAIDAS-FIN-ilumi'!A:A,">="&M4,'SAIDAS-FIN-ilumi'!A:A,"<="&M5)+SUMIFS('Saidas-fin-import'!D:D,'Saidas-fin-import'!C:C,"CONTABILIDADE",'Saidas-fin-import'!A:A,">="&M4,'Saidas-fin-import'!A:A,"<="&M5) -> 2500 | R21: 46113 | S21: 319989.8 | T21: 339610.08 | U21: -19620.28
A22: Saldo total 2025 imp | B22: 73534.87 | D22: EMPRÉSTIMO CAPITAL DE GIRO BRADESCO | E22: =SUMIFS('SAIDAS-FIN-ilumi'!D:D,'SAIDAS-FIN-ilumi'!C:C,"EMPRÉSTIMO CAPITAL DE GIRO BRADESCO",'SAIDAS-FIN-ilumi'!A:A,">="&E4,'SAIDAS-FIN-ilumi'!A:A,"<="&E5)+SUMIFS('Saidas-fin-import'!D:D,'Saidas-fin-import'!C:C,"EMPRÉSTIMO CAPITAL DE GIRO BRADESCO",'Saidas-fin-import'!A:A,">="&E4,'Saidas-fin-import'!A:A,"<="&E5) -> 6441.56 | L22: DEVOLUÇÃO | M22: =SUMIFS('SAIDAS-FIN-ilumi'!D:D,'SAIDAS-FIN-ilumi'!C:C,"DEVOLUÇÃO",'SAIDAS-FIN-ilumi'!A:A,">="&M4,'SAIDAS-FIN-ilumi'!A:A,"<="&M5)+SUMIFS('Saidas-fin-import'!D:D,'Saidas-fin-import'!C:C,"DEVOLUÇÃO",'Saidas-fin-import'!A:A,">="&M4,'Saidas-fin-import'!A:A,"<="&M5) -> 400 | R22: 46143 | S22: 269520.26 | T22: =252799.9925 -> 252799.99 | U22: 16720.268
B23: =B21+B22 -> 108107.65 | D23: EMPRÉSTIMO PRONAMP | E23: =SUMIFS('SAIDAS-FIN-ilumi'!D:D,'SAIDAS-FIN-ilumi'!C:C,"EMPRÉSTIMO PRONAMP",'SAIDAS-FIN-ilumi'!A:A,">="&E4,'SAIDAS-FIN-ilumi'!A:A,"<="&E5)+SUMIFS('Saidas-fin-import'!D:D,'Saidas-fin-import'!C:C,"EMPRÉSTIMO PRONAMP",'Saidas-fin-import'!A:A,">="&E4,'Saidas-fin-import'!A:A,"<="&E5) -> 3700.52 | L23: EMPRÉSTIMO CAPITAL DE GIRO ITAÚ | M23: =SUMIFS('SAIDAS-FIN-ilumi'!D:D,'SAIDAS-FIN-ilumi'!C:C,"EMPRÉSTIMO CAPITAL DE GIRO ITAÚ",'SAIDAS-FIN-ilumi'!A:A,">="&M4,'SAIDAS-FIN-ilumi'!A:A,"<="&M5)+SUMIFS('Saidas-fin-import'!D:D,'Saidas-fin-import'!C:C,"EMPRÉSTIMO CAPITAL DE GIRO ITAÚ",'Saidas-fin-import'!A:A,">="&M4,'Saidas-fin-import'!A:A,"<="&M5) -> 5103.49 | R23: 46174 | S23: 262741.42 | T23: 256416.48 | U23: 6324.9333
D24: FUNCIONÁRIOS | E24: =SUMIFS('SAIDAS-FIN-ilumi'!D:D,'SAIDAS-FIN-ilumi'!C:C,"FUNCIONÁRIOS",'SAIDAS-FIN-ilumi'!A:A,">="&E4,'SAIDAS-FIN-ilumi'!A:A,"<="&E5)+SUMIFS('Saidas-fin-import'!D:D,'Saidas-fin-import'!C:C,"FUNCIONÁRIOS",'Saidas-fin-import'!A:A,">="&E4,'Saidas-fin-import'!A:A,"<="&E5) -> 18141.22 | H24: Import | L24: EMPRÉSTIMO CAPITAL DE GIRO BRADESCO | M24: =SUMIFS('SAIDAS-FIN-ilumi'!D:D,'SAIDAS-FIN-ilumi'!C:C,"EMPRÉSTIMO CAPITAL DE GIRO BRADESCO",'SAIDAS-FIN-ilumi'!A:A,">="&M4,'SAIDAS-FIN-ilumi'!A:A,"<="&M5)+SUMIFS('Saidas-fin-import'!D:D,'Saidas-fin-import'!C:C,"EMPRÉSTIMO CAPITAL DE GIRO BRADESCO",'Saidas-fin-import'!A:A,">="&M4,'Saidas-fin-import'!A:A,"<="&M5) -> 31535 | R24: 46204 | S24: 265397.97 | T24: 257602.64 | U24: 7795.3366
A25: Import | D25: FUNCIONÁRIOS (VR) | E25: =SUMIFS('SAIDAS-FIN-ilumi'!D:D,'SAIDAS-FIN-ilumi'!C:C,"FUNCIONÁRIOS (VR)",'SAIDAS-FIN-ilumi'!A:A,">="&E4,'SAIDAS-FIN-ilumi'!A:A,"<="&E5)+SUMIFS('Saidas-fin-import'!D:D,'Saidas-fin-import'!C:C,"FUNCIONÁRIOS (VR)",'Saidas-fin-import'!A:A,">="&E4,'Saidas-fin-import'!A:A,"<="&E5) -> 560 | H25: Entrada Import | I25: =SUMIFS('Saídas-NFE-import'!D:D,'Saídas-NFE-import'!A:A,">="&M4,'Saídas-NFE-import'!A:A,"<="&M5) -> 314772.1 | L25: EMPRÉSTIMO PRONAMP | M25: =SUMIFS('SAIDAS-FIN-ilumi'!D:D,'SAIDAS-FIN-ilumi'!C:C,"EMPRÉSTIMO PRONAMP",'SAIDAS-FIN-ilumi'!A:A,">="&M4,'SAIDAS-FIN-ilumi'!A:A,"<="&M5)+SUMIFS('Saidas-fin-import'!D:D,'Saidas-fin-import'!C:C,"EMPRÉSTIMO PRONAMP",'Saidas-fin-import'!A:A,">="&M4,'Saidas-fin-import'!A:A,"<="&M5) -> 10862.02 | R25: 46235 | S25: 269643.02 | T25: 255770.83 | U25: 13872.19
A26: Entrada Import | B26: =SUMIFS('Entradas- fin- import'!D:D,'Entradas- fin- import'!A:A,">="&E4,'Entradas- fin- import'!A:A,"<="&E5) -> 80008.32 | D26: GASTOS FIXOS | E26: =SUMIFS('SAIDAS-FIN-ilumi'!D:D,'SAIDAS-FIN-ilumi'!C:C,"GASTOS FIXOS",'SAIDAS-FIN-ilumi'!A:A,">="&E4,'SAIDAS-FIN-ilumi'!A:A,"<="&E5)+SUMIFS('Saidas-fin-import'!D:D,'Saidas-fin-import'!C:C,"GASTOS FIXOS",'Saidas-fin-import'!A:A,">="&E4,'Saidas-fin-import'!A:A,"<="&E5) -> 6520.59 | H26: Saída Import | I26: =SUMIFS('Entradas-NFE-Import'!D:D,'Entradas-NFE-Import'!A:A,">="&M4,'Entradas-NFE-Import'!A:A,"<="&M5) -> 158557.2 | L26: FUNCIONÁRIOS | M26: =SUMIFS('SAIDAS-FIN-ilumi'!D:D,'SAIDAS-FIN-ilumi'!C:C,"FUNCIONÁRIOS",'SAIDAS-FIN-ilumi'!A:A,">="&M4,'SAIDAS-FIN-ilumi'!A:A,"<="&M5)+SUMIFS('Saidas-fin-import'!D:D,'Saidas-fin-import'!C:C,"FUNCIONÁRIOS",'Saidas-fin-import'!A:A,">="&M4,'Saidas-fin-import'!A:A,"<="&M5) -> 74538.89 | R26: 46266 | S26: 278206.61 | T26: 253871.57 | U26: 24335.037
A27: Saída Import | B27: =SUMIFS('Saidas-fin-import'!D:D,'Saidas-fin-import'!A:A,">="&E4,'Saidas-fin-import'!A:A,"<="&E5) -> 70645.67 | D27: IMPORTAÇÃO | E27: =SUMIFS('SAIDAS-FIN-ilumi'!D:D,'SAIDAS-FIN-ilumi'!C:C,"IMPORTAÇÃO",'SAIDAS-FIN-ilumi'!A:A,">="&E4,'SAIDAS-FIN-ilumi'!A:A,"<="&E5)+SUMIFS('Saidas-fin-import'!D:D,'Saidas-fin-import'!C:C,"IMPORTAÇÃO",'Saidas-fin-import'!A:A,">="&E4,'Saidas-fin-import'!A:A,"<="&E5) -> 3200 | H27: Total Import | I27: =I25-I26 -> 156214.9 | L27: FUNCIONÁRIOS (VR) | M27: =SUMIFS('SAIDAS-FIN-ilumi'!D:D,'SAIDAS-FIN-ilumi'!C:C,"FUNCIONÁRIOS (VR)",'SAIDAS-FIN-ilumi'!A:A,">="&M4,'SAIDAS-FIN-ilumi'!A:A,"<="&M5)+SUMIFS('Saidas-fin-import'!D:D,'Saidas-fin-import'!C:C,"FUNCIONÁRIOS (VR)",'Saidas-fin-import'!A:A,">="&M4,'Saidas-fin-import'!A:A,"<="&M5) -> 1560
A28: Total Import | B28: =B26-B27 -> 9362.65 | D28: INVESTIMENTO | E28: =SUMIFS('SAIDAS-FIN-ilumi'!D:D,'SAIDAS-FIN-ilumi'!C:C,"INVESTIMENTO",'SAIDAS-FIN-ilumi'!A:A,">="&E4,'SAIDAS-FIN-ilumi'!A:A,"<="&E5)+SUMIFS('Saidas-fin-import'!D:D,'Saidas-fin-import'!C:C,"INVESTIMENTO",'Saidas-fin-import'!A:A,">="&E4,'Saidas-fin-import'!A:A,"<="&E5) -> 0 | L28: GASTOS FIXOS | M28: =SUMIFS('SAIDAS-FIN-ilumi'!D:D,'SAIDAS-FIN-ilumi'!C:C,"GASTOS FIXOS",'SAIDAS-FIN-ilumi'!A:A,">="&M4,'SAIDAS-FIN-ilumi'!A:A,"<="&M5)+SUMIFS('Saidas-fin-import'!D:D,'Saidas-fin-import'!C:C,"GASTOS FIXOS",'Saidas-fin-import'!A:A,">="&M4,'Saidas-fin-import'!A:A,"<="&M5) -> 45679.28
D29: MANUTENÇÃO | E29: =SUMIFS('SAIDAS-FIN-ilumi'!D:D,'SAIDAS-FIN-ilumi'!C:C,"MANUTENÇÃO",'SAIDAS-FIN-ilumi'!A:A,">="&E4,'SAIDAS-FIN-ilumi'!A:A,"<="&E5)+SUMIFS('Saidas-fin-import'!D:D,'Saidas-fin-import'!C:C,"MANUTENÇÃO",'Saidas-fin-import'!A:A,">="&E4,'Saidas-fin-import'!A:A,"<="&E5) -> 1900 | H29: Iluminação | L29: IMPORTAÇÃO | M29: =SUMIFS('SAIDAS-FIN-ilumi'!D:D,'SAIDAS-FIN-ilumi'!C:C,"IMPORTAÇÃO",'SAIDAS-FIN-ilumi'!A:A,">="&M4,'SAIDAS-FIN-ilumi'!A:A,"<="&M5)+SUMIFS('Saidas-fin-import'!D:D,'Saidas-fin-import'!C:C,"IMPORTAÇÃO",'Saidas-fin-import'!A:A,">="&M4,'Saidas-fin-import'!A:A,"<="&M5) -> 58200
A30: Iluminação | D30: MARKETING | E30: =SUMIFS('SAIDAS-FIN-ilumi'!D:D,'SAIDAS-FIN-ilumi'!C:C,"MARKETING",'SAIDAS-FIN-ilumi'!A:A,">="&E4,'SAIDAS-FIN-ilumi'!A:A,"<="&E5)+SUMIFS('Saidas-fin-import'!D:D,'Saidas-fin-import'!C:C,"MARKETING",'Saidas-fin-import'!A:A,">="&E4,'Saidas-fin-import'!A:A,"<="&E5) -> 0 | H30: Entrada Iluminação | I30: =SUMIFS('SAÍDA NFE ILUMI'!D:D,'SAÍDA NFE ILUMI'!A:A,">="&M4,'SAÍDA NFE ILUMI'!A:A,"<="&M5) -> 805816.77 | L30: INVESTIMENTO | M30: =SUMIFS('SAIDAS-FIN-ilumi'!D:D,'SAIDAS-FIN-ilumi'!C:C,"INVESTIMENTO",'SAIDAS-FIN-ilumi'!A:A,">="&M4,'SAIDAS-FIN-ilumi'!A:A,"<="&M5)+SUMIFS('Saidas-fin-import'!D:D,'Saidas-fin-import'!C:C,"INVESTIMENTO",'Saidas-fin-import'!A:A,">="&M4,'Saidas-fin-import'!A:A,"<="&M5) -> 7306.14
A31: Entrada Iluminação | B31: =SUMIFS('ENTRADAS - FIN - ilumi'!D:D,'ENTRADAS - FIN - ilumi'!A:A,">="&E4,'ENTRADAS - FIN - ilumi'!A:A,"<="&E5) -> 153998.18 | D31: MATERIAL DE ESCRITÓRIO | E31: =SUMIFS('SAIDAS-FIN-ilumi'!D:D,'SAIDAS-FIN-ilumi'!C:C,"MATERIAL DE ESCRITÓRIO",'SAIDAS-FIN-ilumi'!A:A,">="&E4,'SAIDAS-FIN-ilumi'!A:A,"<="&E5)+SUMIFS('Saidas-fin-import'!D:D,'Saidas-fin-import'!C:C,"MATERIAL DE ESCRITÓRIO",'Saidas-fin-import'!A:A,">="&E4,'Saidas-fin-import'!A:A,"<="&E5) -> 0 | H31: Saída Iluminação | I31: =SUMIFS('ENTRADA NFE ILUMI'!D:D,'ENTRADA NFE ILUMI'!A:A,">="&M4,'ENTRADA NFE ILUMI'!A:A,"<="&M5) -> 465723.83 | L31: MANUTENÇÃO | M31: =SUMIFS('SAIDAS-FIN-ilumi'!D:D,'SAIDAS-FIN-ilumi'!C:C,"MANUTENÇÃO",'SAIDAS-FIN-ilumi'!A:A,">="&M4,'SAIDAS-FIN-ilumi'!A:A,"<="&M5)+SUMIFS('Saidas-fin-import'!D:D,'Saidas-fin-import'!C:C,"MANUTENÇÃO",'Saidas-fin-import'!A:A,">="&M4,'Saidas-fin-import'!A:A,"<="&M5) -> 3735 | R31: mai/26 | S31: =Y6+Y14 -> 228832.46 | T31: =Z6+Z14 -> 173791.13 | U31: =S31-T31 -> 55041.33
A32: Saída Iluminação | B32: =SUMIFS('SAIDAS-FIN-ilumi'!D:D,'SAIDAS-FIN-ilumi'!A:A,">="&E4,'SAIDAS-FIN-ilumi'!A:A,"<="&E5) -> 155988.48 | D32: MOVIMENTO | E32: =SUMIFS('SAIDAS-FIN-ilumi'!D:D,'SAIDAS-FIN-ilumi'!C:C,"MOVIMENTO",'SAIDAS-FIN-ilumi'!A:A,">="&E4,'SAIDAS-FIN-ilumi'!A:A,"<="&E5)+SUMIFS('Saidas-fin-import'!D:D,'Saidas-fin-import'!C:C,"MOVIMENTO",'Saidas-fin-import'!A:A,">="&E4,'Saidas-fin-import'!A:A,"<="&E5) -> 5521.36 | H32: Total Iluminação | I32: =I30-I31 -> 340092.94 | L32: MARKETING | M32: =SUMIFS('SAIDAS-FIN-ilumi'!D:D,'SAIDAS-FIN-ilumi'!C:C,"MARKETING",'SAIDAS-FIN-ilumi'!A:A,">="&M4,'SAIDAS-FIN-ilumi'!A:A,"<="&M5)+SUMIFS('Saidas-fin-import'!D:D,'Saidas-fin-import'!C:C,"MARKETING",'Saidas-fin-import'!A:A,">="&M4,'Saidas-fin-import'!A:A,"<="&M5) -> 2007 | R32: 46199 | S32: =Y7+Y15 -> 174200.47 | T32: =Z7+Z15 -> 131241.47 | U32: =S32-T32 -> 42959
A33: Total Iluminação | B33: =B31-B32 -> -1990.3 | D33: PUBLICIDADE | E33: =SUMIFS('SAIDAS-FIN-ilumi'!D:D,'SAIDAS-FIN-ilumi'!C:C,"PUBLICIDADE",'SAIDAS-FIN-ilumi'!A:A,">="&E4,'SAIDAS-FIN-ilumi'!A:A,"<="&E5)+SUMIFS('Saidas-fin-import'!D:D,'Saidas-fin-import'!C:C,"PUBLICIDADE",'Saidas-fin-import'!A:A,">="&E4,'Saidas-fin-import'!A:A,"<="&E5) -> 0 | G33: =(H38/H39) -> 3125 | L33: MATERIAL DE ESCRITÓRIO | M33: =SUMIFS('SAIDAS-FIN-ilumi'!D:D,'SAIDAS-FIN-ilumi'!C:C,"MATERIAL DE ESCRITÓRIO",'SAIDAS-FIN-ilumi'!A:A,">="&M4,'SAIDAS-FIN-ilumi'!A:A,"<="&M5)+SUMIFS('Saidas-fin-import'!D:D,'Saidas-fin-import'!C:C,"MATERIAL DE ESCRITÓRIO",'Saidas-fin-import'!A:A,">="&M4,'Saidas-fin-import'!A:A,"<="&M5) -> 1242 | R33: 46229 | S33: =Y8+Y16 -> 32868.83 | T33: =Z8+Z16 -> 77490.47 | U33: =S33-T33 -> -44621.64
D34: SEGURO DE EMPRÉSTIMO | E34: =SUMIFS('SAIDAS-FIN-ilumi'!D:D,'SAIDAS-FIN-ilumi'!C:C,"SEGURO DE EMPRÉSTIMO",'SAIDAS-FIN-ilumi'!A:A,">="&E4,'SAIDAS-FIN-ilumi'!A:A,"<="&E5)+SUMIFS('Saidas-fin-import'!D:D,'Saidas-fin-import'!C:C,"SEGURO DE EMPRÉSTIMO",'Saidas-fin-import'!A:A,">="&E4,'Saidas-fin-import'!A:A,"<="&E5) -> 109.79 | G34: =G33+(1+0.65*0.1075) -> 3126.0699 | L34: MOVIMENTO | M34: =SUMIFS('SAIDAS-FIN-ilumi'!D:D,'SAIDAS-FIN-ilumi'!C:C,"MOVIMENTO",'SAIDAS-FIN-ilumi'!A:A,">="&M4,'SAIDAS-FIN-ilumi'!A:A,"<="&M5)+SUMIFS('Saidas-fin-import'!D:D,'Saidas-fin-import'!C:C,"MOVIMENTO",'Saidas-fin-import'!A:A,">="&M4,'Saidas-fin-import'!A:A,"<="&M5) -> 77021.36 | R34: ago/26 | S34: =Y9+Y17 -> 4399.86 | T34: =Z9+Z17 -> 62557.29 | U34: =S34-T34 -> -58157.43
D35: SEGURO DE VIDA SÓCIO | E35: =SUMIFS('SAIDAS-FIN-ilumi'!D:D,'SAIDAS-FIN-ilumi'!C:C,"SEGURO DE VIDA SÓCIO",'SAIDAS-FIN-ilumi'!A:A,">="&E4,'SAIDAS-FIN-ilumi'!A:A,"<="&E5)+SUMIFS('Saidas-fin-import'!D:D,'Saidas-fin-import'!C:C,"SEGURO DE VIDA SÓCIO",'Saidas-fin-import'!A:A,">="&E4,'Saidas-fin-import'!A:A,"<="&E5) -> 969.71 | G35: Max Iluminação | L35: PUBLICIDADE | M35: =SUMIFS('SAIDAS-FIN-ilumi'!D:D,'SAIDAS-FIN-ilumi'!C:C,"PUBLICIDADE",'SAIDAS-FIN-ilumi'!A:A,">="&M4,'SAIDAS-FIN-ilumi'!A:A,"<="&M5)+SUMIFS('Saidas-fin-import'!D:D,'Saidas-fin-import'!C:C,"PUBLICIDADE",'Saidas-fin-import'!A:A,">="&M4,'Saidas-fin-import'!A:A,"<="&M5) -> 147 | R35: TOTAL | S35: =SUM(S31:S34) -> 440301.62 | T35: =SUM(T31:T34) -> 445080.36 | U35: =SUM(U31:U34) -> -4778.74
D36: SEGURO SÓCIO CARRO | E36: =SUMIFS('SAIDAS-FIN-ilumi'!D:D,'SAIDAS-FIN-ilumi'!C:C,"SEGURO SÓCIO CARRO",'SAIDAS-FIN-ilumi'!A:A,">="&E4,'SAIDAS-FIN-ilumi'!A:A,"<="&E5)+SUMIFS('Saidas-fin-import'!D:D,'Saidas-fin-import'!C:C,"SEGURO SÓCIO CARRO",'Saidas-fin-import'!A:A,">="&E4,'Saidas-fin-import'!A:A,"<="&E5) -> 0 | L36: SEGURO DE EMPRÉSTIMO | M36: =SUMIFS('SAIDAS-FIN-ilumi'!D:D,'SAIDAS-FIN-ilumi'!C:C,"SEGURO DE EMPRÉSTIMO",'SAIDAS-FIN-ilumi'!A:A,">="&M4,'SAIDAS-FIN-ilumi'!A:A,"<="&M5)+SUMIFS('Saidas-fin-import'!D:D,'Saidas-fin-import'!C:C,"SEGURO DE EMPRÉSTIMO",'Saidas-fin-import'!A:A,">="&M4,'Saidas-fin-import'!A:A,"<="&M5) -> 548.95
D37: SÓCIOS | E37: =SUMIFS('SAIDAS-FIN-ilumi'!D:D,'SAIDAS-FIN-ilumi'!C:C,"SÓCIOS",'SAIDAS-FIN-ilumi'!A:A,">="&E4,'SAIDAS-FIN-ilumi'!A:A,"<="&E5)+SUMIFS('Saidas-fin-import'!D:D,'Saidas-fin-import'!C:C,"SÓCIOS",'Saidas-fin-import'!A:A,">="&E4,'Saidas-fin-import'!A:A,"<="&E5) -> 16500 | G37: Capital de Giro Bradesco | I37: Capital de Giro Itaú | L37: SEGURO DE VIDA SÓCIO | M37: =SUMIFS('SAIDAS-FIN-ilumi'!D:D,'SAIDAS-FIN-ilumi'!C:C,"SEGURO DE VIDA SÓCIO",'SAIDAS-FIN-ilumi'!A:A,">="&M4,'SAIDAS-FIN-ilumi'!A:A,"<="&M5)+SUMIFS('Saidas-fin-import'!D:D,'Saidas-fin-import'!C:C,"SEGURO DE VIDA SÓCIO",'Saidas-fin-import'!A:A,">="&M4,'Saidas-fin-import'!A:A,"<="&M5) -> 2909.13 | T37: =T31/T22*0.1 -> 0.068746493
D38: TRANSPORTES | E38: =SUMIFS('SAIDAS-FIN-ilumi'!D:D,'SAIDAS-FIN-ilumi'!C:C,"TRANSPORTES",'SAIDAS-FIN-ilumi'!A:A,">="&E4,'SAIDAS-FIN-ilumi'!A:A,"<="&E5)+SUMIFS('Saidas-fin-import'!D:D,'Saidas-fin-import'!C:C,"TRANSPORTES",'Saidas-fin-import'!A:A,">="&E4,'Saidas-fin-import'!A:A,"<="&E5) -> 6186.68 | G38: Valor Total inicial | H38: 150000 | I38: Valor Total inicial | J38: 92187.62 | L38: SEGURO SÓCIO CARRO | M38: =SUMIFS('SAIDAS-FIN-ilumi'!D:D,'SAIDAS-FIN-ilumi'!C:C,"SEGURO SÓCIO CARRO",'SAIDAS-FIN-ilumi'!A:A,">="&M4,'SAIDAS-FIN-ilumi'!A:A,"<="&M5)+SUMIFS('Saidas-fin-import'!D:D,'Saidas-fin-import'!C:C,"SEGURO SÓCIO CARRO",'Saidas-fin-import'!A:A,">="&M4,'Saidas-fin-import'!A:A,"<="&M5) -> 1863.46
D39: TRANSPORTES IMPORTAÇÃO | E39: =SUMIFS('SAIDAS-FIN-ilumi'!D:D,'SAIDAS-FIN-ilumi'!C:C,"TRANSPORTES IMPORTAÇÃO",'SAIDAS-FIN-ilumi'!A:A,">="&E4,'SAIDAS-FIN-ilumi'!A:A,"<="&E5)+SUMIFS('Saidas-fin-import'!D:D,'Saidas-fin-import'!C:C,"TRANSPORTES IMPORTAÇÃO",'Saidas-fin-import'!A:A,">="&E4,'Saidas-fin-import'!A:A,"<="&E5) -> 883.39 | G39: Total de parcelas | H39: 48 | I39: Total de parcelas | J39: 48 | L39: SÓCIOS | M39: =SUMIFS('SAIDAS-FIN-ilumi'!D:D,'SAIDAS-FIN-ilumi'!C:C,"SÓCIOS",'SAIDAS-FIN-ilumi'!A:A,">="&M4,'SAIDAS-FIN-ilumi'!A:A,"<="&M5)+SUMIFS('Saidas-fin-import'!D:D,'Saidas-fin-import'!C:C,"SÓCIOS",'Saidas-fin-import'!A:A,">="&M4,'Saidas-fin-import'!A:A,"<="&M5) -> 90052.61
D40: PLANO DE SAÚDE | E40: =SUMIFS('SAIDAS-FIN-ilumi'!D:D,'SAIDAS-FIN-ilumi'!C:C,"PLANO DE SAÚDE",'SAIDAS-FIN-ilumi'!A:A,">="&E4,'SAIDAS-FIN-ilumi'!A:A,"<="&E5) -> 0 | G40: Parcelas pagas | H40: =COUNTIF('SAIDAS-FIN-ilumi'!B:B,"EMPRÉSTIMO CAPITAL DE GIRO BRADESCO")+41 -> 41 | I40: Parcelas pagas | J40: =COUNTIF('SAIDAS-FIN-ilumi'!C:C,"EMPRÉSTIMO CAPITAL DE GIRO ITAÚ")+2 -> 4 | L40: TRANSPORTES | M40: =SUMIFS('SAIDAS-FIN-ilumi'!D:D,'SAIDAS-FIN-ilumi'!C:C,"TRANSPORTES",'SAIDAS-FIN-ilumi'!A:A,">="&M4,'SAIDAS-FIN-ilumi'!A:A,"<="&M5)+SUMIFS('Saidas-fin-import'!D:D,'Saidas-fin-import'!C:C,"TRANSPORTES",'Saidas-fin-import'!A:A,">="&M4,'Saidas-fin-import'!A:A,"<="&M5) -> 29509.08
D41: Outras Despesas Operacionais | E41: =SUMIFS('SAIDAS-FIN-ilumi'!D:D,'SAIDAS-FIN-ilumi'!C:C,"OUTRAS DESPESAS",'SAIDAS-FIN-ilumi'!A:A,">="&E4,'SAIDAS-FIN-ilumi'!A:A,"<="&E5) -> 0 | G41: Valor Parcela c/ juros | H41: =G33+G34 -> 6251.0699 | I41: Valor Parcela c/ juros | J41: =(J38/J39)*(1+0.49%+10.75%) -> 2136.4481 | L41: TRANSPORTES IMPORTAÇÃO | M41: =SUMIFS('SAIDAS-FIN-ilumi'!D:D,'SAIDAS-FIN-ilumi'!C:C,"TRANSPORTES IMPORTAÇÃO",'SAIDAS-FIN-ilumi'!A:A,">="&M4,'SAIDAS-FIN-ilumi'!A:A,"<="&M5)+SUMIFS('Saidas-fin-import'!D:D,'Saidas-fin-import'!C:C,"TRANSPORTES IMPORTAÇÃO",'Saidas-fin-import'!A:A,">="&M4,'Saidas-fin-import'!A:A,"<="&M5) -> 4945.26
D42: Total Despesas Operacionais | E42: =SUM(E15:E41) -> 84579 | G42: Parcelas restantes | H42: =H39-H40 -> 7 | I42: Parcelas restantes | J42: =J39-J40 -> 44 | L42: Outras Despesas Operacionais | M42: =SUMIFS('SAIDAS-FIN-ilumi'!L:L,'SAIDAS-FIN-ilumi'!K:K,"OUTRAS DESPESAS",'SAIDAS-FIN-ilumi'!I:I,">="&M6,'SAIDAS-FIN-ilumi'!I:I,"<="&M7) -> 0
D43: RESULTADO OPERACIONAL | E43: =E12-E42 -> 17894 | G43: Valor restante | H43: =SUMIF('SAIDAS-FIN-ilumi'!C:C,"EMPRÉSTIMO CAPITAL DE GIRO BRADESCO",'SAIDAS-FIN-ilumi'!D:D) -> 31535 | I43: Valor restante | J43: =J38-J44 -> 87084.13 | L43: Total Despesas Operacionais | M43: =SUM(M17:M42) -> 507496.45
G44: Valor pago | H44: =H38-H43 -> 118465 | I44: Valor pago | J44: =SUMIF('SAIDAS-FIN-ilumi'!C:C,"EMPRÉSTIMO CAPITAL DE GIRO ITAÚ",'SAIDAS-FIN-ilumi'!D:D) -> 5103.49 | L44: RESULTADO OPERACIONAL | M44: =M14-M43 -> -100172.98
D45: MARGEM BRUTA (%) | E45: =IF(E9=0,0,E12/E9) -> 0.48215298 | G45: Acrescimo | H45: =(H44+H43)*0.75 -> 112500 | I45: Acrescimo | J45: =(J44+J43)*0.59 -> 54390.696 | L45: MARGEM BRUTA (%) | M45: =IF(M11=0,0,M14/M11) -> 0.39484461
D46: MARGEM LÍQUIDA (%) | E46: =IF(E7=0,0,E43/E7) -> 0.076467961 | G46: Valor final com acrescimmo | H46: =H38+H45 -> 262500 | I46: Valor final com acrescimmo | J46: =J38+J45 -> 146578.32
G47: Data inicial | H47: 44988 | I47: Data inicial | J47: 46106
G48: Data Final prevista | H48: 46237 | I48: Data Final prevista | J48: 47539
G50: Empréstimo Max Importação
G52: Pronamp | I52: Capital de Giro FGI
G53: Valor Total inicial | H53: 116965.8 | I53: Valor Total inicial | J53: 139755.03
G54: Total de parcelas | H54: 48 | I54: Total de parcelas | J54: 48
G55: Parcelas pagas | H55: =COUNTIF('Saidas-fin-import'!C:C,"EMPRÉSTIMO PRONAMP")+14 -> 17 | I55: Parcelas pagas | J55: =COUNTIF('Saidas-fin-import'!C:C,"EMPRÉSTIMOS FGI")+2 -> 5
G56: Valor Parcela c/ juros | H56: =(H53/H54)*(1+1.62%+10.75%) -> 2738.2181 | I56: Valor Parcela c/ juros | J56: =(J53/J54)*(1+1.62%) -> 2958.7304
G57: Parcelas restantes | H57: =H54-H55 -> 31 | I57: Parcelas restantes | J57: =J54-J55 -> 43
G58: Valor pago | H58: =SUMIF('Saidas-fin-import'!C:C,"EMPRÉSTIMO PRONAMP",'Saidas-fin-import'!D:D)+47315.47 -> 58177.49 | I58: Valor pago | J58: =SUMIF('Saidas-fin-import'!C:C,"EMPRÉSTIMOS FGI",'Saidas-fin-import'!D:D)+5275.86 -> 14801.49
G59: Valor restante | H59: =H53-H58 -> 58788.31 | I59: Valor restante | J59: =J53-J58 -> 124953.54
G60: Acrescimo | H60: =(H58+H59)*1.172 -> 137083.92 | I60: Acrescimo | J60: =(J58+J59)*1.62 -> 226403.15
G61: Valor final com acrescimmo | H61: =H53+H60 -> 254049.72 | J61: =J53+J60 -> 366158.18
G62: Data inicial | H62: 45994 | I62: Data inicial | J62: 46024
G63: Data Final prevista | H63: 47133 | I63: Data Final prevista | J63: 47455

Sheet Resumo Mensal Ilumini
A1: Max Led Iluminação
I2: Receira de Dez. | J2: 34572.78
H3: Financeiro
A4: DRE Financeiro | D4: DRE NFE | H4: MÊS | I4: Receita | J4: Saida | K4: TOTAL c. Dez | L4: TOTAL c. Dez | M4: Evolução %
H5: 46023 | I5: =SUMIF('ENTRADAS - FIN - ilumi'!F:F,"Janeiro",'ENTRADAS - FIN - ilumi'!D:D) -> 132275.4 | J5: =SUMIF('SAIDAS-FIN-ilumi'!F:F,"Janeiro",'SAIDAS-FIN-ilumi'!D:D) -> 116350.31 | K5: =I5-J5 -> 15925.09 | L5: =I5-J5 -> 15925.09 | M5: =IF(J2=0,0,(L5-J2)/J2) -> -0.53937491
A6: Entradas Fin ilumi | B6: Saidas Fin Ilu | D6: Entradas ilu NFE | E6: Saidas ilu NFE | H6: 46054 | I6: =SUMIF('ENTRADAS - FIN - ilumi'!F:F,"Fevereiro",'ENTRADAS - FIN - ilumi'!D:D) -> 126679.25 | J6: =SUMIF('SAIDAS-FIN-ilumi'!F:F,"Fevereiro",'SAIDAS-FIN-ilumi'!D:D) -> 133410.26 | K6: =I6-J6 -> -6731.01 | L6: =I6-J6 -> -6731.01 | M6: =IF(J2=0,0,(L6-J2)/J2) -> -1.194691
H7: 46082 | I7: =SUMIF('ENTRADAS - FIN - ilumi'!F:F,"MARÇO",'ENTRADAS - FIN - ilumi'!D:D) -> 183424.12 | J7: =SUMIF('SAIDAS-FIN-ilumi'!F:F,"Março",'SAIDAS-FIN-ilumi'!D:D) -> 192968.08 | K7: =I7-J7 -> -9543.96 | L7: =I7-J7 -> -9543.96 | M7: =IF(J2=0,0,(L7-J2)/J2) -> -1.2760542
A8: Mês | B8: Anual | D8: Mês | E8: Anual | H8: 46113 | I8: =SUMIF('ENTRADAS - FIN - ilumi'!F:F,"Abril",'ENTRADAS - FIN - ilumi'!D:D) -> 214380.68 | J8: =SUMIF('SAIDAS-FIN-ilumi'!F:F,"Abril",'SAIDAS-FIN-ilumi'!D:D) -> 231574.3 | K8: =I8-J8 -> -17193.62 | L8: =I8-J8 -> -17193.62 | M8: =IF(J2=0,0,(L8-J2)/J2) -> -1.4973167
H9: 46143 | I9: =SUMIF('ENTRADAS - FIN - ilumi'!F:F,"Maio",'ENTRADAS - FIN - ilumi'!D:D) -> 153998.18 | J9: =SUMIF('SAIDAS-FIN-ilumi'!F:F,"Maio",'SAIDAS-FIN-ilumi'!D:D) -> 155988.48 | K9: =I9-J9 -> -1990.3 | L9: =I9-J9 -> -1990.3 | M9: =IF(I8=0,0,(I9-I8)/I8) -> -0.28166018
H10: 46174 | I10: =SUMIF('ENTRADAS - FIN - ilumi'!F:F,"Junho",'ENTRADAS - FIN - ilumi'!D:D) -> 0 | J10: =SUMIF('SAIDAS-FIN-ilumi'!F:F,"Junho ",'SAIDAS-FIN-ilumi'!D:D) -> 0 | K10: =I10-J10 -> 0 | L10: =I10-J10 -> 0 | M10: =IF(I9=0,0,(I10-I9)/I9) -> -1
A11: Entrada | B11: =SUMIFS('ENTRADAS - FIN - ilumi'!D:D,'ENTRADAS - FIN - ilumi'!A:A,">="&$B$22,'ENTRADAS - FIN - ilumi'!A:A,"<="&$B$23) -> 810757.63 | H11: 46204 | I11: =SUMIF('ENTRADAS - FIN - ilumi'!F:F,"Julho",'ENTRADAS - FIN - ilumi'!D:D) -> 0 | J11: =SUMIF('SAIDAS-FIN-ilumi'!F:F,"Julho",'SAIDAS-FIN-ilumi'!D:D) -> 0 | K11: =I11-J11 -> 0 | L11: =I11-J11 -> 0 | M11: =IF(I10=0,0,(I11-I10)/I10) -> 0
D12: Total | E12: =E15-E18 -> 340092.94 | H12: 46235 | I12: =SUMIF('ENTRADAS - FIN - ilumi'!F:F,"Agosto",'ENTRADAS - FIN - ilumi'!D:D) -> 0 | J12: =SUMIF('SAIDAS-FIN-ilumi'!F:F,"Agosto",'SAIDAS-FIN-ilumi'!D:D) -> 0 | K12: =I12-J12 -> 0 | L12: =I12-J12 -> 0 | M12: =IF(I11=0,0,(I12-I11)/I11) -> 0
A13: Saídas | B13: =SUMIFS('SAIDAS-FIN-ilumi'!D:D,'SAIDAS-FIN-ilumi'!A:A,">="&$B$22,'SAIDAS-FIN-ilumi'!A:A,"<="&$B$23) -> 830291.43 | H13: 46266 | I13: =SUMIF('ENTRADAS - FIN - ilumi'!F:F,"Setembro",'ENTRADAS - FIN - ilumi'!D:D) -> 0 | J13: =SUMIF('SAIDAS-FIN-ilumi'!F:F,"Setembro",'SAIDAS-FIN-ilumi'!D:D) -> 0 | K13: =I13-J13 -> 0 | L13: =I13-J13 -> 0 | M13: =IF(I12=0,0,(I13-I12)/I12) -> 0
H14: 46296 | I14: =SUMIF('ENTRADAS - FIN - ilumi'!F:F,"Outubro",'ENTRADAS - FIN - ilumi'!D:D) -> 0 | J14: =SUMIF('SAIDAS-FIN-ilumi'!F:F,"Outubro",'SAIDAS-FIN-ilumi'!D:D) -> 0 | K14: =I14-J14 -> 0 | L14: =I14-J14 -> 0 | M14: =IF(I13=0,0,(I14-I13)/I13) -> 0
A15: Total | B15: =B11-B13 -> -19533.8 | D15: VENDAS | E15: =SUMIFS('SAÍDA NFE ILUMI'!D:D,'SAÍDA NFE ILUMI'!A:A,">="&$E$22,'SAÍDA NFE ILUMI'!A:A,"<="&$E$23) -> 805816.77 | H15: 46327 | I15: =SUMIF('ENTRADAS - FIN - ilumi'!F:F,"Novembro",'ENTRADAS - FIN - ilumi'!D:D) -> 0 | J15: =SUMIF('SAIDAS-FIN-ilumi'!F:F,"Novembro",'SAIDAS-FIN-ilumi'!D:D) -> 0 | K15: =I15-J15 -> 0 | L15: =I15-J15 -> 0 | M15: =IF(I14=0,0,(I15-I14)/I14) -> 0
H16: 46357 | I16: =SUMIF('ENTRADAS - FIN - ilumi'!F:F,"Dezembro",'ENTRADAS - FIN - ilumi'!D:D) -> 0 | J16: =SUMIF('SAIDAS-FIN-ilumi'!F:F,"Dezembro",'SAIDAS-FIN-ilumi'!D:D) -> 0 | K16: =I16-J16 -> 0 | L16: =I16-J16 -> 0 | M16: =IF(I15=0,0,(I16-I15)/I15) -> 0
H17: Total | I17: =SUM(I5:I16) -> 810757.63 | J17: =SUM(J5:J16) -> 830291.43 | K17: =SUM(K5:K16) -> -19533.8 | L17: =SUM(L5:L16) -> -19533.8
A18: Receira de Dez. | B18: 34572.78 | D18: COMPRAS | E18: =SUMIFS('ENTRADA NFE ILUMI'!D:D,'ENTRADA NFE ILUMI'!A:A,">="&$E$22,'ENTRADA NFE ILUMI'!A:A,"<="&$E$23) -> 465723.83
A19: Total com dezembro | B19: =B11+B18-B13 -> 15038.98 | H19: Projeções de Receita
H20: 46143 | I20: =_xlfn.FORECAST.LINEAR(H20,I5:I8,H5:H8) -> 239986.22
H21: 46174 | I21: =_xlfn.FORECAST.LINEAR(H21,I5:I8,H5:H8) -> 271315.39
A22: Período Inicial: | B22: =IF(B8="ANUAL",DATE(2026,1,1),DATE(2026,MATCH(B8,{"JANEIRO";"FEVEREIRO";"MARÇO";"ABRIL";"MAIO";"JUNHO";"JULHO";"AGOSTO";"SETEMBRO";"OUTUBRO";"NOVEMBRO";"DEZEMBRO"},0),1)) -> 46023 | D22: Período Inicial: | E22: =IF(E8="ANUAL",DATE(2026,1,1),DATE(2026,MATCH(E8,{"JANEIRO";"FEVEREIRO";"MARÇO";"ABRIL";"MAIO";"JUNHO";"JULHO";"AGOSTO";"SETEMBRO";"OUTUBRO";"NOVEMBRO";"DEZEMBRO"},0),1)) -> 46023 | H22: 46204 | I22: =_xlfn.FORECAST.LINEAR(H22,I5:I8,H5:H8) -> 301633.93
A23: Período Final: | B23: =IF(B8="ANUAL",DATE(2026,12,31),EOMONTH(DATE(2026,MATCH(B8,{"JANEIRO";"FEVEREIRO";"MARÇO";"ABRIL";"MAIO";"JUNHO";"JULHO";"AGOSTO";"SETEMBRO";"OUTUBRO";"NOVEMBRO";"DEZEMBRO"},0),1),0)) -> 46387 | D23: Período Final: | E23: =IF(E8="ANUAL",DATE(2026,12,31),EOMONTH(DATE(2026,MATCH(E8,{"JANEIRO";"FEVEREIRO";"MARÇO";"ABRIL";"MAIO";"JUNHO";"JULHO";"AGOSTO";"SETEMBRO";"OUTUBRO";"NOVEMBRO";"DEZEMBRO"},0),1),0)) -> 46387 | H23: 46235 | I23: =_xlfn.FORECAST.LINEAR(H23,I5:I8,H5:H8) -> 332963.09
H24: 46266 | I24: =_xlfn.FORECAST.LINEAR(H24,I5:I8,H5:H8) -> 364292.25
A25: RECEITA BRUTA | B25: =SUMIFS('ENTRADAS - FIN - ilumi'!D:D,'ENTRADAS - FIN - ilumi'!A:A,">="&B22,'ENTRADAS - FIN - ilumi'!A:A,"<="&B23) -> 810757.63 | D25: RECEITA BRUTA | E25: =SUMIFS('SAÍDA NFE ILUMI'!D:D,'SAÍDA NFE ILUMI'!A:A,">="&E22,'SAÍDA NFE ILUMI'!A:A,"<="&E23) -> 805816.77 | H25: 46296 | I25: =_xlfn.FORECAST.LINEAR(H25,I5:I8,H5:H8) -> 394610.8
A26: (-) IMPOSTOS (Simples Nacional) | B26: =SUMIFS('SAIDAS-FIN-ilumi'!D:D,'SAIDAS-FIN-ilumi'!C:C,"IMPOSTOS",'SAIDAS-FIN-ilumi'!A:A,">="&B22,'SAIDAS-FIN-ilumi'!A:A,"<="&B23) -> 103256.71 | D26: RECEITA SNF | E26: =SUMIFS('SAÍDA NFE ILUMI'!I:I,'SAÍDA NFE ILUMI'!J:J,"SNF",'SAÍDA NFE ILUMI'!F:F,">="&E22,'SAÍDA NFE ILUMI'!F:F,"<="&E23) -> 23074.52
A27: RECEITA LÍQUIDA | B27: =B25-B26 -> 707500.92 | D27: Total de Receitas | E27: =E25+E26 -> 828891.29
D28: (-) IMPOSTOS (Simples Nacional) | E28: =SUMIFS('SAIDAS-FIN-ilumi'!D:D,'SAIDAS-FIN-ilumi'!C:C,"IMPOSTOS",'SAIDAS-FIN-ilumi'!A:A,">="&E22,'SAIDAS-FIN-ilumi'!A:A,"<="&E23) -> 103256.71 | H28: =(I33/I34) -> 3125
A29: (-) CUSTO DAS MERCADORIAS (FORNECEDORES) | B29: =SUMIFS('SAIDAS-FIN-ilumi'!D:D,'SAIDAS-FIN-ilumi'!C:C,"FORNECEDORES",'SAIDAS-FIN-ilumi'!A:A,">="&B22,'SAIDAS-FIN-ilumi'!A:A,"<="&B23) -> 436248.53 | D29: RECEITA LÍQUIDA | E29: =E27-E28 -> 725634.58 | H29: =H28+(1+0.65*0.1075) -> 3126.0699
A30: LUCRO BRUTO | B30: =B27-B29 -> 271252.39 | H30: Max Iluminação
D31: (-) CUSTO DAS MERCADORIAS (FORNECEDORES) | E31: =SUMIFS('ENTRADA NFE ILUMI'!D:D,'ENTRADA NFE ILUMI'!A:A,">="&E22,'ENTRADA NFE ILUMI'!A:A,"<="&E23) -> 465723.83
A32: DESPESAS OPERACIONAIS: | D32: LUCRO BRUTO | E32: =E29-E31 -> 259910.75 | H32: Capital de Giro Bradesco | J32: Capital de Giro Itaú
A33: BANCO | B33: =SUMIFS('SAIDAS-FIN-ilumi'!D:D,'SAIDAS-FIN-ilumi'!C:C,"BANCO",'SAIDAS-FIN-ilumi'!A:A,">="&B22,'SAIDAS-FIN-ilumi'!A:A,"<="&B23) -> 2093.66 | H33: Valor Total inicial | I33: 150000 | J33: Valor Total inicial | K33: 92187.62 | M33: Valor restante
A34: CARTÃO DE CRÉDITO | B34: =SUMIFS('SAIDAS-FIN-ilumi'!D:D,'SAIDAS-FIN-ilumi'!C:C,"CARTÃO DE CRÉDITO",'SAIDAS-FIN-ilumi'!A:A,">="&B22,'SAIDAS-FIN-ilumi'!A:A,"<="&B23) -> 3508.61 | D34: DESPESAS OPERACIONAIS: | H34: Total de parcelas | I34: 48 | J34: Total de parcelas | K34: 48 | M34: Valor pago | N34: Valor pago
A35: CONSUMO | B35: =SUMIFS('SAIDAS-FIN-ilumi'!D:D,'SAIDAS-FIN-ilumi'!C:C,"CONSUMO",'SAIDAS-FIN-ilumi'!A:A,">="&B22,'SAIDAS-FIN-ilumi'!A:A,"<="&B23) -> 1741.18 | D35: Devolução | E35: =SUMIFS('SAÍDA NFE ILUMI'!I:I,'SAÍDA NFE ILUMI'!J:J,"DEVOLUÇÕES",'SAÍDA NFE ILUMI'!F:F,">="&E22,'SAÍDA NFE ILUMI'!F:F,"<="&E23) -> 880.2 | H35: Parcelas pagas | I35: =COUNTIF('SAIDAS-FIN-ilumi'!C:C,"EMPRÉSTIMO CAPITAL DE GIRO BRADESCO")+41 -> 46 | J35: Parcelas pagas | K35: =COUNTIF('SAIDAS-FIN-ilumi'!C:C,"EMPRÉSTIMO CAPITAL DE GIRO ITAÚ")+2 -> 4 | N35: Valor restante
A36: CONTABILIDADE | B36: =SUMIFS('SAIDAS-FIN-ilumi'!D:D,'SAIDAS-FIN-ilumi'!C:C,"CONTABILIDADE",'SAIDAS-FIN-ilumi'!A:A,">="&B22,'SAIDAS-FIN-ilumi'!A:A,"<="&B23) -> 2500 | D36: BANCO | E36: =SUMIFS('SAIDAS-FIN-ilumi'!D:D,'SAIDAS-FIN-ilumi'!C:C,"BANCO",'SAIDAS-FIN-ilumi'!A:A,">="&E22,'SAIDAS-FIN-ilumi'!A:A,"<="&E23) -> 2093.66 | H36: Valor Parcela c/ juros | I36: =H28+H29 -> 6251.0699 | J36: Valor Parcela c/ juros | K36: =(K33/K34)*(1+0.49%+10.75%) -> 2136.4481 | M36: Acrescimo | N36: Acrescimo
A37: DEVOLUÇÃO | B37: =SUMIFS('SAIDAS-FIN-ilumi'!D:D,'SAIDAS-FIN-ilumi'!C:C,"DEVOLUÇÃO",'SAIDAS-FIN-ilumi'!A:A,">="&B22,'SAIDAS-FIN-ilumi'!A:A,"<="&B23) -> 400 | D37: CARTÃO DE CRÉDITO | E37: =SUMIFS('SAIDAS-FIN-ilumi'!D:D,'SAIDAS-FIN-ilumi'!C:C,"CARTÃO DE CRÉDITO",'SAIDAS-FIN-ilumi'!A:A,">="&E22,'SAIDAS-FIN-ilumi'!A:A,"<="&E23) -> 3508.61 | H37: Parcelas restantes | I37: =I34-I35 -> 2 | J37: Parcelas restantes | K37: =K34-K35 -> 44 | M37: Valor final com acrescimmo | N37: Valor final com acrescimmo
A38: EMPRÉSTIMO CAPITAL DE GIRO ITAÚ | B38: =SUMIFS('SAIDAS-FIN-ilumi'!D:D,'SAIDAS-FIN-ilumi'!C:C,"EMPRÉSTIMO CAPITAL DE GIRO ITAÚ",'SAIDAS-FIN-ilumi'!A:A,">="&B22,'SAIDAS-FIN-ilumi'!A:A,"<="&B23) -> 5103.49 | D38: CONSUMO | E38: =SUMIFS('SAIDAS-FIN-ilumi'!D:D,'SAIDAS-FIN-ilumi'!C:C,"CONSUMO",'SAIDAS-FIN-ilumi'!A:A,">="&E22,'SAIDAS-FIN-ilumi'!A:A,"<="&E23) -> 1741.18 | H38: Valor restante | I38: =SUMIF('SAIDAS-FIN-ilumi'!C:C,"EMPRÉSTIMO CAPITAL DE GIRO BRADESCO",'SAIDAS-FIN-ilumi'!D:D) -> 31535 | J38: Valor restante | K38: =K33-K39 -> 87084.13
A39: EMPRÉSTIMO CAPITAL DE GIRO BRADESCO | B39: =SUMIFS('SAIDAS-FIN-ilumi'!D:D,'SAIDAS-FIN-ilumi'!C:C,"EMPRÉSTIMO CAPITAL DE GIRO BRADESCO",'SAIDAS-FIN-ilumi'!A:A,">="&B22,'SAIDAS-FIN-ilumi'!A:A,"<="&B23) -> 31535 | D39: CONTABILIDADE | E39: =SUMIFS('SAIDAS-FIN-ilumi'!D:D,'SAIDAS-FIN-ilumi'!C:C,"CONTABILIDADE",'SAIDAS-FIN-ilumi'!A:A,">="&E22,'SAIDAS-FIN-ilumi'!A:A,"<="&E23) -> 2500 | H39: Valor pago | I39: =I33-I38 -> 118465 | J39: Valor pago | K39: =SUMIF('SAIDAS-FIN-ilumi'!C:C,"EMPRÉSTIMO CAPITAL DE GIRO ITAÚ",'SAIDAS-FIN-ilumi'!D:D) -> 5103.49
A40: FUNCIONÁRIOS | B40: =SUMIFS('SAIDAS-FIN-ilumi'!D:D,'SAIDAS-FIN-ilumi'!C:C,"FUNCIONÁRIOS",'SAIDAS-FIN-ilumi'!A:A,">="&B22,'SAIDAS-FIN-ilumi'!A:A,"<="&B23) -> 48236.13 | D40: EMPRÉSTIMO CAPITAL DE GIRO ITAÚ | E40: =SUMIFS('SAIDAS-FIN-ilumi'!D:D,'SAIDAS-FIN-ilumi'!C:C,"EMPRÉSTIMO CAPITAL DE GIRO ITAÚ",'SAIDAS-FIN-ilumi'!A:A,">="&E22,'SAIDAS-FIN-ilumi'!A:A,"<="&E23) -> 5103.49 | H40: Acrescimo | I40: =(I39+I38)*0.75 -> 112500 | J40: Acrescimo | K40: =(K39+K38)*0.59 -> 54390.696
A41: FUNCIONÁRIOS (VR) | B41: =SUMIFS('SAIDAS-FIN-ilumi'!D:D,'SAIDAS-FIN-ilumi'!C:C,"FUNCIONÁRIOS (VR)",'SAIDAS-FIN-ilumi'!A:A,">="&B22,'SAIDAS-FIN-ilumi'!A:A,"<="&B23) -> 1560 | D41: EMPRÉSTIMO CAPITAL DE GIRO BRADESCO | E41: =SUMIFS('SAIDAS-FIN-ilumi'!D:D,'SAIDAS-FIN-ilumi'!C:C,"EMPRÉSTIMO CAPITAL DE GIRO BRADESCO",'SAIDAS-FIN-ilumi'!A:A,">="&E22,'SAIDAS-FIN-ilumi'!A:A,"<="&E23) -> 31535 | H41: Valor final com acrescimmo | I41: =I33+I40 -> 262500 | J41: Valor final com acrescimmo | K41: =K33+K40 -> 146578.32
A42: GASTOS FIXOS | B42: =SUMIFS('SAIDAS-FIN-ilumi'!D:D,'SAIDAS-FIN-ilumi'!C:C,"GASTOS FIXOS",'SAIDAS-FIN-ilumi'!A:A,">="&B22,'SAIDAS-FIN-ilumi'!A:A,"<="&B23) -> 35375.61 | D42: FUNCIONÁRIOS | E42: =SUMIFS('SAIDAS-FIN-ilumi'!D:D,'SAIDAS-FIN-ilumi'!C:C,"FUNCIONÁRIOS",'SAIDAS-FIN-ilumi'!A:A,">="&E22,'SAIDAS-FIN-ilumi'!A:A,"<="&E23) -> 48236.13 | H42: Data inicial | I42: 44988 | J42: Data inicial | K42: 46106
A43: IMPORTAÇÃO | B43: =SUMIFS('SAIDAS-FIN-ilumi'!D:D,'SAIDAS-FIN-ilumi'!C:C,"IMPORTAÇÃO",'SAIDAS-FIN-ilumi'!A:A,">="&B22,'SAIDAS-FIN-ilumi'!A:A,"<="&B23) -> 30000 | D43: FUNCIONÁRIOS (VR) | E43: =SUMIFS('SAIDAS-FIN-ilumi'!D:D,'SAIDAS-FIN-ilumi'!C:C,"FUNCIONÁRIOS (VR)",'SAIDAS-FIN-ilumi'!A:A,">="&E22,'SAIDAS-FIN-ilumi'!A:A,"<="&E23) -> 1560 | H43: Data Final prevista | I43: 46237 | J43: Data Final prevista | K43: 47539
A44: INVESTIMENTO | B44: =SUMIFS('SAIDAS-FIN-ilumi'!D:D,'SAIDAS-FIN-ilumi'!C:C,"INVESTIMENTO",'SAIDAS-FIN-ilumi'!A:A,">="&B22,'SAIDAS-FIN-ilumi'!A:A,"<="&B23) -> 3167.68 | D44: GASTOS FIXOS | E44: =SUMIFS('SAIDAS-FIN-ilumi'!D:D,'SAIDAS-FIN-ilumi'!C:C,"GASTOS FIXOS",'SAIDAS-FIN-ilumi'!A:A,">="&E22,'SAIDAS-FIN-ilumi'!A:A,"<="&E23) -> 35375.61
A45: MANUTENÇÃO | B45: =SUMIFS('SAIDAS-FIN-ilumi'!D:D,'SAIDAS-FIN-ilumi'!C:C,"MANUTENÇÃO",'SAIDAS-FIN-ilumi'!A:A,">="&B22,'SAIDAS-FIN-ilumi'!A:A,"<="&B23) -> 1585 | D45: IMPORTAÇÃO | E45: =SUMIFS('SAIDAS-FIN-ilumi'!D:D,'SAIDAS-FIN-ilumi'!C:C,"IMPORTAÇÃO",'SAIDAS-FIN-ilumi'!A:A,">="&E22,'SAIDAS-FIN-ilumi'!A:A,"<="&E23) -> 30000
A46: MARKETING | B46: =SUMIFS('SAIDAS-FIN-ilumi'!D:D,'SAIDAS-FIN-ilumi'!C:C,"MARKETING",'SAIDAS-FIN-ilumi'!A:A,">="&B22,'SAIDAS-FIN-ilumi'!A:A,"<="&B23) -> 2007 | D46: INVESTIMENTO | E46: =SUMIFS('SAIDAS-FIN-ilumi'!D:D,'SAIDAS-FIN-ilumi'!C:C,"INVESTIMENTO",'SAIDAS-FIN-ilumi'!A:A,">="&E22,'SAIDAS-FIN-ilumi'!A:A,"<="&E23) -> 3167.68
A47: MOVIMENTO | B47: =SUMIFS('SAIDAS-FIN-ilumi'!D:D,'SAIDAS-FIN-ilumi'!C:C,"MOVIMENTO",'SAIDAS-FIN-ilumi'!A:A,">="&B22,'SAIDAS-FIN-ilumi'!A:A,"<="&B23) -> 41166.36 | D47: MANUTENÇÃO | E47: =SUMIFS('SAIDAS-FIN-ilumi'!D:D,'SAIDAS-FIN-ilumi'!C:C,"MANUTENÇÃO",'SAIDAS-FIN-ilumi'!A:A,">="&E22,'SAIDAS-FIN-ilumi'!A:A,"<="&E23) -> 1585
A48: PUBLICIDADE | B48: =SUMIFS('SAIDAS-FIN-ilumi'!D:D,'SAIDAS-FIN-ilumi'!C:C,"PUBLICIDADE",'SAIDAS-FIN-ilumi'!A:A,">="&B22,'SAIDAS-FIN-ilumi'!A:A,"<="&B23) -> 147 | D48: MARKETING | E48: =SUMIFS('SAIDAS-FIN-ilumi'!D:D,'SAIDAS-FIN-ilumi'!C:C,"MARKETING",'SAIDAS-FIN-ilumi'!A:A,">="&E22,'SAIDAS-FIN-ilumi'!A:A,"<="&E23) -> 2007
A49: SEGURO DE VIDA SÓCIO | B49: =SUMIFS('SAIDAS-FIN-ilumi'!D:D,'SAIDAS-FIN-ilumi'!C:C,"SEGURO DE VIDA SÓCIO",'SAIDAS-FIN-ilumi'!A:A,">="&B22,'SAIDAS-FIN-ilumi'!A:A,"<="&B23) -> 2909.13 | D49: MOVIMENTO | E49: =SUMIFS('SAIDAS-FIN-ilumi'!D:D,'SAIDAS-FIN-ilumi'!C:C,"MOVIMENTO",'SAIDAS-FIN-ilumi'!A:A,">="&E22,'SAIDAS-FIN-ilumi'!A:A,"<="&E23) -> 41166.36
A50: SEGURO SÓCIO CARRO | B50: =SUMIFS('SAIDAS-FIN-ilumi'!D:D,'SAIDAS-FIN-ilumi'!C:C,"SEGURO SÓCIO CARRO",'SAIDAS-FIN-ilumi'!A:A,">="&B22,'SAIDAS-FIN-ilumi'!A:A,"<="&B23) -> 1863.46 | D50: PUBLICIDADE | E50: =SUMIFS('SAIDAS-FIN-ilumi'!D:D,'SAIDAS-FIN-ilumi'!C:C,"PUBLICIDADE",'SAIDAS-FIN-ilumi'!A:A,">="&E22,'SAIDAS-FIN-ilumi'!A:A,"<="&E23) -> 147
A51: SÓCIOS | B51: =SUMIFS('SAIDAS-FIN-ilumi'!D:D,'SAIDAS-FIN-ilumi'!C:C,"SÓCIOS",'SAIDAS-FIN-ilumi'!A:A,">="&B22,'SAIDAS-FIN-ilumi'!A:A,"<="&B23) -> 36550.37 | D51: SEGURO DE VIDA SÓCIO | E51: =SUMIFS('SAIDAS-FIN-ilumi'!D:D,'SAIDAS-FIN-ilumi'!C:C,"SEGURO DE VIDA SÓCIO",'SAIDAS-FIN-ilumi'!A:A,">="&E22,'SAIDAS-FIN-ilumi'!A:A,"<="&E23) -> 2909.13
A52: TRANSPORTES | B52: =SUMIFS('SAIDAS-FIN-ilumi'!D:D,'SAIDAS-FIN-ilumi'!C:C,"TRANSPORTES",'SAIDAS-FIN-ilumi'!A:A,">="&B22,'SAIDAS-FIN-ilumi'!A:A,"<="&B23) -> 22339.08 | D52: SEGURO SÓCIO CARRO | E52: =SUMIFS('SAIDAS-FIN-ilumi'!D:D,'SAIDAS-FIN-ilumi'!C:C,"SEGURO SÓCIO CARRO",'SAIDAS-FIN-ilumi'!A:A,">="&E22,'SAIDAS-FIN-ilumi'!A:A,"<="&E23) -> 1863.46
A53: PLANO DE SAÚDE | B53: =SUMIFS('SAIDAS-FIN-ilumi'!D:D,'SAIDAS-FIN-ilumi'!C:C,"PLANO DE SAÚDE",'SAIDAS-FIN-ilumi'!A:A,">="&B22,'SAIDAS-FIN-ilumi'!A:A,"<="&B23) -> 10121.8 | D53: SÓCIOS | E53: =SUMIFS('SAIDAS-FIN-ilumi'!D:D,'SAIDAS-FIN-ilumi'!C:C,"SÓCIOS",'SAIDAS-FIN-ilumi'!A:A,">="&E22,'SAIDAS-FIN-ilumi'!A:A,"<="&E23) -> 36550.37
A54: Outras Despesas Operacionais | B54: =SUMIFS('SAIDAS-FIN-ilumi'!D:D,'SAIDAS-FIN-ilumi'!C:C,"OUTROS",'SAIDAS-FIN-ilumi'!A:A,">="&B22,'SAIDAS-FIN-ilumi'!A:A,"<="&B23) -> 0 | D54: TRANSPORTES | E54: =SUMIFS('SAIDAS-FIN-ilumi'!D:D,'SAIDAS-FIN-ilumi'!C:C,"TRANSPORTES",'SAIDAS-FIN-ilumi'!A:A,">="&E22,'SAIDAS-FIN-ilumi'!A:A,"<="&E23) -> 22339.08
A55: Total Despesas Operacionais | B55: =SUM(B33:B52) -> 273788.76
D56: Outras Despesas Operacionais | E56: =SUMIFS('SAIDAS-FIN-ilumi'!D:D,'SAIDAS-FIN-ilumi'!C:C,"OUTROS",'SAIDAS-FIN-ilumi'!A:A,">="&E22,'SAIDAS-FIN-ilumi'!A:A,"<="&E23) -> 0
A57: RESULTADO OPERACIONAL | B57: =B30-B55 -> -2536.37 | D57: Total Despesas Operacionais | E57: =SUM(E35:E56) -> 274268.96
A59: MARGEM BRUTA (%) | B59: =IF(B27=0,0,B30/B27) -> 0.38339511 | D59: RESULTADO OPERACIONAL | E59: =E32-E57 -> -14358.21
A60: MARGEM LÍQUIDA (%) | B60: =IF(B25=0,0,B57/B25) -> -0.0031283949
D61: MARGEM BRUTA (%) | E61: =IF(E29=0,0,E32/E29) -> 0.35818407
D62: MARGEM LÍQUIDA (%) | E62: =IF(E25=0,0,E59/E25) -> -0.017818207

Sheet Resumo Mensal  import
A1: Max Led Import
H2: Receita de Dezembro | I2: 73534.87
A4: DRE Financeiro | D4: DRE NFE | G4: MÊS | H4: Receita | I4: Saída | J4: Total | K4: Total c/ 2025 | L4: Evolução %
G5: 46023 | H5: =SUMIF('Entradas- fin- import'!E:E,"Janeiro",'Entradas- fin- import'!D:D) -> 13593.52 | I5: =SUMIF('Saidas-fin-import'!E:E,"Janeiro",'Saidas-fin-import'!D:D) -> 74876.93 | J5: =H5-I5 -> -61283.41 | K5: =I2+H5-I5 -> 12251.46 | L5: =IF(I2=0,0,(H5-I2)/I2) -> -0.81514185
A6: Entradas Import FIN | B6: Saidas Import fin | D6: Entradas Import NFE | E6: Saidas Import NFE | G6: 46054 | H6: =SUMIF('Entradas- fin- import'!E:E,"Fevereiro",'Entradas- fin- import'!D:D) -> 37091.38 | I6: =SUMIF('Saidas-fin-import'!E:E,"Fevereiro",'Saidas-fin-import'!D:D) -> 44764.38 | J6: =J5+G6-H6 -> -52320.79 | K6: =K5+H6-I6 -> 4578.46 | L6: =IF(H5=0,0,(H6-H5)/H5) -> 1.7286075
G7: 46082 | H7: =SUMIF('Entradas- fin- import'!E:E,"mArço",'Entradas- fin- import'!D:D) -> 37723.49 | I7: =SUMIF('Saidas-fin-import'!E:E,"Março",'Saidas-fin-import'!D:D) -> 35226.35 | J7: =J6+G7-H7 -> -43962.28 | K7: =K6+H7-I7 -> 7075.6 | L7: =IF(H6=0,0,(H7-H6)/H6) -> 0.017041965
A8: Mês | B8: Anual | D8: Mês | E8: Anual | G8: 46113 | H8: =SUMIF('Entradas- fin- import'!E:E,"Abril",'Entradas- fin- import'!D:D) -> 105609.12 | I8: =SUMIF('Saidas-fin-import'!E:E,"Abril",'Saidas-fin-import'!D:D) -> 108035.78 | J8: =J7+G8-H8 -> -103458.4 | K8: =K7+H8-I8 -> 4648.94 | L8: =IF(H7=0,0,(H8-H7)/H7) -> 1.7995586
G9: 46143 | H9: =SUMIF('Entradas- fin- import'!E:E,G9,'Entradas- fin- import'!C:C) -> 0 | I9: =SUMIF('Saidas-fin-import'!E:E,"Maio",'Saidas-fin-import'!D:D) -> 70645.67 | J9: - | K9: - | L9: =IF(H8=0,0,(H9-H8)/H8) -> -1
G10: 46174 | H10: =SUMIF('Entradas- fin- import'!E:E,G10,'Entradas- fin- import'!C:C) -> 0 | I10: =SUMIF('Saidas-fin-import'!E:E,"Junho",'Saidas-fin-import'!D:D) -> 0 | J10: - | K10: - | L10: =IF(H9=0,0,(H10-H9)/H9) -> 0
A11: Entrada | B11: =SUMIFS('Entradas- fin- import'!D:D,'Entradas- fin- import'!A:A,">="&$B$22,'Entradas- fin- import'!A:A,"<="&$B$23) -> 275640.99 | G11: 46204 | H11: =SUMIF('Entradas- fin- import'!E:E,G11,'Entradas- fin- import'!C:C) -> 0 | I11: =SUMIF('Saidas-fin-import'!E:E,"Julho",'Saidas-fin-import'!D:D) -> 0 | J11: - | K11: - | L11: =IF(H10=0,0,(H11-H10)/H10) -> 0
D12: Entrada | E12: =SUMIFS('Saídas-NFE-import'!D:D,'Saídas-NFE-import'!A:A,">="&$E$22,'Saídas-NFE-import'!A:A,"<="&$E$23) -> 314772.1 | G12: 46235 | H12: =SUMIF('Entradas- fin- import'!E:E,G12,'Entradas- fin- import'!C:C) -> 0 | I12: =SUMIF('Saidas-fin-import'!E:E,"Agosto",'Saidas-fin-import'!D:D) -> 0 | J12: - | K12: - | L12: =IF(H11=0,0,(H12-H11)/H11) -> 0
A13: Saídas | B13: =SUMIFS('Saidas-fin-import'!D:D,'Saidas-fin-import'!A:A,">="&$B$22,'Saidas-fin-import'!A:A,"<="&$B$23) -> 336579.78 | G13: 46266 | H13: =SUMIF('Entradas- fin- import'!E:E,G13,'Entradas- fin- import'!C:C) -> 0 | I13: =SUMIF('Saidas-fin-import'!E:E,"Setembro",'Saidas-fin-import'!D:D) -> 0 | J13: - | K13: - | L13: =IF(H12=0,0,(H13-H12)/H12) -> 0
G14: 46296 | H14: =SUMIF('Entradas- fin- import'!E:E,G14,'Entradas- fin- import'!C:C) -> 0 | I14: =SUMIF('Saidas-fin-import'!E:E,"Outubro",'Saidas-fin-import'!D:D) -> 0 | J14: - | K14: - | L14: =IF(H13=0,0,(H14-H13)/H13) -> 0
A15: Total | B15: =B11-B13 -> -60938.79 | D15: Saídas | E15: =SUMIFS('Entradas-NFE-Import'!D:D,'Entradas-NFE-Import'!A:A,">="&$E$22,'Entradas-NFE-Import'!A:A,"<="&$E$23) -> 158557.2 | G15: 46327 | H15: =SUMIF('Entradas- fin- import'!E:E,G15,'Entradas- fin- import'!C:C) -> 0 | I15: =SUMIF('Saidas-fin-import'!E:E,"Novembro",'Saidas-fin-import'!D:D) -> 0 | J15: - | K15: - | L15: =IF(H14=0,0,(H15-H14)/H14) -> 0
G16: 46357 | H16: =SUMIF('Entradas- fin- import'!E:E,G16,'Entradas- fin- import'!C:C) -> 0 | I16: =SUMIF('Saidas-fin-import'!E:E,"Dezembro",'Saidas-fin-import'!D:D) -> 0 | J16: - | K16: - | L16: =IF(H15=0,0,(H16-H15)/H15) -> 0
G17: Total | H17: =SUM(H5:H16) -> 194017.51 | I17: =SUM(I5:I16) -> 333549.11 | J17: =SUM(J5:J16) -> -261024.88 | K17: =SUM(K5:K16) -> 28554.46
A18: Receita de Dezembro | B18: 73534.87 | D18: Total | E18: =E12-E15 -> 156214.9
A19: Total com dezembro | B19: =B11+B18-B13 -> 12596.08
G20: Projeções de Receita
G21: 46143 | H21: =_xlfn.FORECAST.LINEAR(G21,G5:G8,H5:H8) -> 46065.927
A22: Período Inicial: | B22: =IF(B8="Janeiro",DATE(2026,1,1), IF(B8="Fevereiro",DATE(2026,2,1), IF(B8="Março",DATE(2026,3,1), IF(B8="Abril",DATE(2026,4,1), IF(B8="Maio",DATE(2026,5,1), IF(B8="Junho",DATE(2026,6,1), IF(B8="Julho",DATE(2026,7,1), IF(B8="Agosto",DATE(2026,8,1), IF(B8="Setembro",DATE(2026,9,1), IF(B8="Outubro",DATE(2026,10,1), IF(B8="Novembro",DATE(2026,11,1), IF(B8="Dezembro",DATE(2026,12,1), IF(B8="Anual",DATE(2026,1,1)))))))))))))) -> 46023 | D22: Período Inicial: | E22: =IF(E8="ANUAL",DATE(2026,1,1),DATE(2026,MATCH(E8,{"JANEIRO";"FEVEREIRO";"MARÇO";"ABRIL";"MAIO";"JUNHO";"JULHO";"AGOSTO";"SETEMBRO";"OUTUBRO";"NOVEMBRO";"DEZEMBRO"},0),1)) -> 46023 | G22: 46174 | H22: =_xlfn.FORECAST.LINEAR(G22,G5:G8,H5:H8) -> 46065.954
A23: Período Final: | B23: =IF(B8="ANUAL",DATE(2026,12,31),EOMONTH(DATE(2026,MATCH(B8,{"JANEIRO";"FEVEREIRO";"MARÇO";"ABRIL";"MAIO";"JUNHO";"JULHO";"AGOSTO";"SETEMBRO";"OUTUBRO";"NOVEMBRO";"DEZEMBRO"},0),1),0)) -> 46387 | D23: Período Final: | E23: =IF(E8="ANUAL",DATE(2026,12,31),EOMONTH(DATE(2026,MATCH(E8,{"JANEIRO";"FEVEREIRO";"MARÇO";"ABRIL";"MAIO";"JUNHO";"JULHO";"AGOSTO";"SETEMBRO";"OUTUBRO";"NOVEMBRO";"DEZEMBRO"},0),1),0)) -> 46387 | G23: 46204 | H23: =_xlfn.FORECAST.LINEAR(G23,G5:G8,H5:H8) -> 46065.98
G24: 46235 | H24: =_xlfn.FORECAST.LINEAR(G24,G5:G8,H5:H8) -> 46066.008
A25: RECEITA BRUTA | B25: =SUMIFS('Entradas- fin- import'!D:D,'Entradas- fin- import'!A:A,">="&B22,'Entradas- fin- import'!A:A,"<="&B23) -> 275640.99 | D25: RECEITA BRUTA | E25: =SUMIFS('Saídas-NFE-import'!D:D,'Saídas-NFE-import'!A:A,">="&E22,'Saídas-NFE-import'!A:A,"<="&E23) -> 314772.1
A26: (-) IMPOSTOS (Simples Nacional) | B26: =SUMIFS('Saidas-fin-import'!D:D,'Saidas-fin-import'!C:C,"IMPOSTOS",'Saidas-fin-import'!A:A,">="&B22,'Saidas-fin-import'!A:A,"<="&B23) -> 17864.27 | D26: RECEITA SNF | E26: =SUMIFS('Saídas-NFE-import'!D:D,'Saídas-NFE-import'!E:E,"SNF",'Saídas-NFE-import'!A:A,">="&E22,'Saídas-NFE-import'!A:A,"<="&E23) -> 0
A27: RECEITA LÍQUIDA | B27: =B25-B26 -> 257776.72 | D27: Total de Receitas | E27: =E25+E26 -> 314772.1
D28: (-) IMPOSTOS (Simples Nacional) | E28: =SUMIFS('Saidas-fin-import'!D:D,'Saidas-fin-import'!C:C,"IMPOSTOS",'Saidas-fin-import'!A:A,">="&E22,'Saidas-fin-import'!A:A,"<="&E23) -> 17864.27 | M28: BANCO
A29: (-) CUSTO DAS MERCADORIAS (FORNECEDORES) | B29: =SUMIFS('Saidas-fin-import'!D:D,'Saidas-fin-import'!C:C,"FORNECEDORES",'Saidas-fin-import'!A:A,">="&B22,'Saidas-fin-import'!A:A,"<="&B23) -> 31000.3 | D29: RECEITA LÍQUIDA | E29: =E27-E28 -> 296907.83 | G29: Empréstimo Max Importação | M29: BRINDES
A30: LUCRO BRUTO | B30: =B27-B29 -> 226776.42 | M30: CARTÃO DE CRÉDITO
D31: (-) CUSTO DAS MERCADORIAS (FORNECEDORES) | E31: =SUMIFS('Entradas-NFE-Import'!D:D,'Entradas-NFE-Import'!A:A,">="&E22,'Entradas-NFE-Import'!A:A,"<="&E23) -> 158557.2 | G31: Pronamp | I31: Capital de Giro FGI | M31: CONSUMO
A32: DESPESAS OPERACIONAIS: | D32: LUCRO BRUTO | E32: =E29-E31 -> 138350.63 | G32: Valor Total inicial | H32: 116965.8 | I32: Valor Total inicial | J32: 139755.03 | M32: CONTABILIDADE
A33: BANCO | B33: =SUMIFS('Saidas-fin-import'!D:D,'Saidas-fin-import'!C:C,"BANCO",'Saidas-fin-import'!A:A,">="&B22,'Saidas-fin-import'!A:A,"<="&B23) -> 236.02 | G33: Total de parcelas | H33: 48 | I33: Total de parcelas | J33: 48 | M33: DEVOLUÇÃO
A34: BRINDES | B34: =SUMIFS('Saidas-fin-import'!D:D,'Saidas-fin-import'!C:C,"BRINDES",'Saidas-fin-import'!A:A,">="&B22,'Saidas-fin-import'!A:A,"<="&B23) -> 1327 | D34: DESPESAS OPERACIONAIS: | G34: Parcelas pagas | H34: =COUNTIF('Saidas-fin-import'!C:C,"EMPRÉSTIMO PRONAMP")+14 -> 17 | I34: Parcelas pagas | J34: =COUNTIF('Saidas-fin-import'!C:C,"EMPRÉSTIMOS FGI")+2 -> 5 | M34: EMPRÉSTIMO CAPITAL DE GIRO ITAÚ
A35: CARTÃO DE CRÉDITO | B35: =SUMIFS('Saidas-fin-import'!D:D,'Saidas-fin-import'!C:C,"CARTÃO DE CRÉDITO",'Saidas-fin-import'!A:A,">="&B22,'Saidas-fin-import'!A:A,"<="&B23) -> 46601.6 | D35: Devolução | E35: =SUMIFS('Entradas-NFE-Import'!D:D,'Entradas-NFE-Import'!E:E,"DEVOLUÇÕES",'Entradas-NFE-Import'!A:A,">="&E22,'Entradas-NFE-Import'!A:A,"<="&E23) -> 0 | G35: Valor Parcela c/ juros | H35: =(H32/H33)*(1+1.62%+10.75%) -> 2738.2181 | I35: Valor Parcela c/ juros | J35: =(J32/J33)*(1+1.62%) -> 2958.7304 | M35: EMPRÉSTIMO CAPITAL DE GIRO BRADESCO
A36: CONSUMO | B36: =SUMIFS('Saidas-fin-import'!D:D,'Saidas-fin-import'!C:C,"CONSUMO",'Saidas-fin-import'!A:A,">="&B22,'Saidas-fin-import'!A:A,"<="&B23) -> 322.71 | D36: BANCO | E36: =SUMIFS('Saidas-fin-import'!D:D,'Saidas-fin-import'!C:C,"BANCO",'Saidas-fin-import'!A:A,">="&E22,'Saidas-fin-import'!A:A,"<="&E23) -> 236.02 | G36: Parcelas restantes | H36: =H33-H34 -> 31 | I36: Parcelas restantes | J36: =J33-J34 -> 43 | M36: EMPRÉSTIMO PRONAMP
A37: EMPRÉSTIMO PRONAMP | B37: =SUMIFS('Saidas-fin-import'!D:D,'Saidas-fin-import'!C:C,"EMPRÉSTIMO PRONAMP",'Saidas-fin-import'!A:A,">="&B22,'Saidas-fin-import'!A:A,"<="&B23) -> 10862.02 | D37: BRINDES | E37: =SUMIFS('Saidas-fin-import'!D:D,'Saidas-fin-import'!C:C,"BRINDES",'Saidas-fin-import'!A:A,">="&E22,'Saidas-fin-import'!A:A,"<="&E23) -> 1327 | G37: Valor pago | H37: =SUMIF('Saidas-fin-import'!C:C,"EMPRÉSTIMO PRONAMP",'Saidas-fin-import'!D:D) -> 10862.02 | I37: Valor pago | J37: =SUMIF('Saidas-fin-import'!C:C,"EMPRÉSTIMOS FGI",'Saidas-fin-import'!D:D)+5275.86 -> 14801.49 | M37: FUNCIONÁRIOS
A38: FUNCIONÁRIOS | B38: =SUMIFS('Saidas-fin-import'!D:D,'Saidas-fin-import'!C:C,"FUNCIONÁRIOS",'Saidas-fin-import'!A:A,">="&B22,'Saidas-fin-import'!A:A,"<="&B23) -> 26302.76 | D38: CARTÃO DE CRÉDITO | E38: =SUMIFS('Saidas-fin-import'!D:D,'Saidas-fin-import'!C:C,"CARTÃO DE CRÉDITO",'Saidas-fin-import'!A:A,">="&E22,'Saidas-fin-import'!A:A,"<="&E23) -> 46601.6 | G38: Valor restante | H38: =H32-H37 -> 106103.78 | I38: Valor restante | J38: =J32-J37 -> 124953.54 | M38: FUNCIONÁRIOS (VR)
A39: GASTOS FIXOS | B39: =SUMIFS('Saidas-fin-import'!D:D,'Saidas-fin-import'!C:C,"GASTOS FIXOS",'Saidas-fin-import'!A:A,">="&B22,'Saidas-fin-import'!A:A,"<="&B23) -> 10303.67 | D39: CONSUMO | E39: =SUMIFS('Saidas-fin-import'!D:D,'Saidas-fin-import'!C:C,"CONSUMO",'Saidas-fin-import'!A:A,">="&E22,'Saidas-fin-import'!A:A,"<="&E23) -> 322.71 | G39: Acrescimo | H39: =(H37+H38)*1.172 -> 137083.92 | I39: Acrescimo | J39: =(J37+J38)*1.62 -> 226403.15 | M39: GASTOS FIXOS
A40: IMPORTAÇÃO | B40: =SUMIFS('Saidas-fin-import'!D:D,'Saidas-fin-import'!C:C,"IMPORTAÇÕES",'Saidas-fin-import'!A:A,">="&B22,'Saidas-fin-import'!A:A,"<="&B23) -> 30459.73 | D40: EMPRÉSTIMO PRONAMP | E40: =SUMIFS('Saidas-fin-import'!D:D,'Saidas-fin-import'!C:C,"EMPRÉSTIMO PRONAMP",'Saidas-fin-import'!A:A,">="&E22,'Saidas-fin-import'!A:A,"<="&E23) -> 10862.02 | G40: Valor final com acrescimmo | H40: =H32+H39 -> 254049.72 | J40: =J32+J39 -> 366158.18 | M40: IMPORTAÇÃO
A41: INVESTIMENTO | B41: =SUMIFS('Saidas-fin-import'!D:D,'Saidas-fin-import'!C:C,"INVESTIMENTO",'Saidas-fin-import'!A:A,">="&B22,'Saidas-fin-import'!A:A,"<="&B23) -> 4138.46 | D41: FUNCIONÁRIOS | E41: =SUMIFS('Saidas-fin-import'!D:D,'Saidas-fin-import'!C:C,"FUNCIONÁRIOS",'Saidas-fin-import'!A:A,">="&E22,'Saidas-fin-import'!A:A,"<="&E23) -> 26302.76 | G41: Data inicial | H41: 45994 | I41: Data inicial | J41: 46024 | M41: INVESTIMENTO
A42: MANUTENÇÃO | B42: =SUMIFS('Saidas-fin-import'!D:D,'Saidas-fin-import'!C:C,"MANUTENÇÃO",'Saidas-fin-import'!A:A,">="&B22,'Saidas-fin-import'!A:A,"<="&B23) -> 2150 | D42: GASTOS FIXOS | E42: =SUMIFS('Saidas-fin-import'!D:D,'Saidas-fin-import'!C:C,"GASTOS FIXOS",'Saidas-fin-import'!A:A,">="&E22,'Saidas-fin-import'!A:A,"<="&E23) -> 10303.67 | G42: Data Final prevista | H42: 47133 | I42: Data Final prevista | J42: 47455 | M42: MANUTENÇÃO
A43: MOVIMENTO | B43: =SUMIFS('Saidas-fin-import'!D:D,'Saidas-fin-import'!C:C,"MOVIMENTO",'Saidas-fin-import'!A:A,">="&B22,'Saidas-fin-import'!A:A,"<="&B23) -> 35855 | D43: IMPORTAÇÃO | E43: =SUMIFS('Saidas-fin-import'!D:D,'Saidas-fin-import'!C:C,"IMPORTAÇÕES",'Saidas-fin-import'!A:A,">="&E22,'Saidas-fin-import'!A:A,"<="&E23) -> 30459.73 | M43: MARKETING
A44: MATERIAL DE ESCRITÓRIO | B44: =SUMIFS('Saidas-fin-import'!D:D,'Saidas-fin-import'!C:C,"MATERIAL DE ESCRITÓRIO",'Saidas-fin-import'!A:A,">="&B22,'Saidas-fin-import'!A:A,"<="&B23) -> 1242 | D44: INVESTIMENTO | E44: =SUMIFS('Saidas-fin-import'!D:D,'Saidas-fin-import'!C:C,"INVESTIMENTO",'Saidas-fin-import'!A:A,">="&E22,'Saidas-fin-import'!A:A,"<="&E23) -> 4138.46 | M44: MATERIAL DE ESCRITÓRIO
A45: SEGURO DE EMPRÉSTIMO | B45: =SUMIFS('Saidas-fin-import'!D:D,'Saidas-fin-import'!C:C,"SEGURO DE EMPRÉSTIMO",'Saidas-fin-import'!A:A,">="&B22,'Saidas-fin-import'!A:A,"<="&B23) -> 548.95 | D45: MANUTENÇÃO | E45: =SUMIFS('Saidas-fin-import'!D:D,'Saidas-fin-import'!C:C,"MANUTENÇÃO",'Saidas-fin-import'!A:A,">="&E22,'Saidas-fin-import'!A:A,"<="&E23) -> 2150 | M45: MOVIMENTO
A46: SÓCIOS | B46: =SUMIFS('Saidas-fin-import'!D:D,'Saidas-fin-import'!C:C,"SÓCIOS",'Saidas-fin-import'!A:A,">="&B22,'Saidas-fin-import'!A:A,"<="&B23) -> 53502.24 | D46: MOVIMENTO | E46: =SUMIFS('Saidas-fin-import'!D:D,'Saidas-fin-import'!C:C,"MOVIMENTO",'Saidas-fin-import'!A:A,">="&E22,'Saidas-fin-import'!A:A,"<="&E23) -> 35855 | M46: PUBLICIDADE
A47: TRANSPORTES | B47: =SUMIFS('Saidas-fin-import'!D:D,'Saidas-fin-import'!C:C,"TRANSPORTES",'Saidas-fin-import'!A:A,">="&B22,'Saidas-fin-import'!A:A,"<="&B23) -> 7170 | D47: MATERIAL DE ESCRITÓRIO | E47: =SUMIFS('Saidas-fin-import'!D:D,'Saidas-fin-import'!C:C,"MATERIAL DE ESCRITÓRIO",'Saidas-fin-import'!A:A,">="&E22,'Saidas-fin-import'!A:A,"<="&E23) -> 1242 | M47: SEGURO DE EMPRÉSTIMO
A48: TRANSPORTES IMPORTAÇÃO | B48: =SUMIFS('Saidas-fin-import'!D:D,'Saidas-fin-import'!C:C,"TRANSPORTES IMPORTAÇÃO",'Saidas-fin-import'!A:A,">="&B22,'Saidas-fin-import'!A:A,"<="&B23) -> 4945.26 | D48: SEGURO DE EMPRÉSTIMO | E48: =SUMIFS('Saidas-fin-import'!D:D,'Saidas-fin-import'!C:C,"SEGURO DE EMPRÉSTIMO",'Saidas-fin-import'!A:A,">="&E22,'Saidas-fin-import'!A:A,"<="&E23) -> 548.95 | M48: SEGURO DE VIDA SÓCIO
A49: Outras Despesas Operacionais | B49: =SUMIFS('SAIDAS-FIN-ilumi'!D:D,'SAIDAS-FIN-ilumi'!C:C,"OUTRAS DESPESAS",'SAIDAS-FIN-ilumi'!A:A,">="&B22,'SAIDAS-FIN-ilumi'!A:A,"<="&B23) -> 0 | D49: SÓCIOS | E49: =SUMIFS('Saidas-fin-import'!D:D,'Saidas-fin-import'!C:C,"SÓCIOS",'Saidas-fin-import'!A:A,">="&E22,'Saidas-fin-import'!A:A,"<="&E23) -> 53502.24 | M49: SEGURO SÓCIO CARRO
A50: Total Despesas Operacionais | B50: =SUM(B33:B49) -> 235967.42 | D50: TRANSPORTES | E50: =SUMIFS('Saidas-fin-import'!D:D,'Saidas-fin-import'!C:C,"TRANSPORTES",'Saidas-fin-import'!A:A,">="&E22,'Saidas-fin-import'!A:A,"<="&E23) -> 7170 | M50: SÓCIOS
D51: TRANSPORTES IMPORTAÇÃO | E51: =SUMIFS('Saidas-fin-import'!D:D,'Saidas-fin-import'!C:C,"TRANSPORTES IMPORTAÇÃO",'Saidas-fin-import'!A:A,">="&E22,'Saidas-fin-import'!A:A,"<="&E23) -> 4945.26 | M51: TRANSPORTES
A52: RESULTADO OPERACIONAL | B52: =B30-B50 -> -9191 | D52: Outras Despesas Operacionais | E52: =B49 -> 0 | M52: TRANSPORTES IMPORTAÇÃO
D53: Total Despesas Operacionais | E53: =SUM(E35:E52) -> 235967.42
A54: MARGEM BRUTA (%) | B54: =IF(B27=0,0,B30/B27) -> 0.87973972
A55: MARGEM LÍQUIDA (%) | B55: =IF(B25=0,0,B52/B25) -> -0.033344097 | D55: RESULTADO OPERACIONAL | E55: =E32-E53 -> -97616.79
D57: MARGEM BRUTA (%) | E57: =IF(E29=0,0,E32/E29) -> 0.46597165
D58: MARGEM LÍQUIDA (%) | E58: =IF(E25=0,0,E55/E25) -> -0.31011894

Sheet Entradas- fin- import
A1: DATA | B1: CLIENTE | C1: JUSTIFICATIVA | D1: VALOR
A3: 46027 | B3: J. ROSSAN | C3: 777 | D3: 272 | E3: janeiro | F3: =SUM(D3:D13) -> 15208.68
A4: 46027 | B4: FERRTECH | C4: 768 | D4: 1343.16 | E4: janeiro
A5: 46034 | B5: FERRTECH | C5: 778 | D5: 1762.68 | E5: janeiro
A6: 46034 | B6: TELESHESK | C6: 779 | D6: 480 | E6: janeiro
A7: 46038 | B7: TRANSFIX | C7: 771 | D7: 980 | E7: janeiro
A8: 46038 | B8: ALLPRINT | C8: 770 | D8: 4105 | E8: janeiro
A9: 46038 | B9: TELESHESK | C9: 769 | D9: 3435.92 | E9: janeiro
A10: 46041 | B10: R. BAIÃO | C10: 775 | D10: 700.6 | E10: janeiro
A11: 46043 | B11: extorno cartão de crédito | C11: investimento | D11: 1479.32 | E11: janeiro
A12: 46045 | B12: T.G.L | C12: 776 | D12: 170 | E12: janeiro
A13: 46048 | B13: TELESHESK | C13: 779 | D13: 480 | E13: janeiro
A14: 46056 | B14: R. BAIÃO | C14: 773 | D14: 980.84 | E14: fevereiro | F14: =SUM(D14:D36) -> 37091.38
A15: 46058 | B15: TRANSFIX | C15: 784 | D15: 608.34 | E15: fevereiro
A16: 46058 | B16: FZW | C16: 767 + 11610 | D16: 482.09 | E16: fevereiro
A17: 46059 | B17: LANZA | C17: 783 | D17: 1714 | E17: fevereiro
A18: 46062 | B18: FERRTECH | C18: 778 | D18: 1711.5 | E18: fevereiro
A19: 46062 | B19: SIMPLES CONECT | C19: 782 | D19: 2850 | E19: fevereiro
A20: 46063 | B20: DIGISYSTEM | C20: 786 | D20: 452 | E20: fevereiro
A21: 46063 | B21: TELESHESK | C21: 779 | D21: 480 | E21: fevereiro
A22: 46064 | B22: J.M MÁQUINAS | C22: 785 | D22: 5272.5 | E22: fevereiro
A23: 46064 | B23: DENTSCLER | C23: 787 | D23: 732 | E23: fevereiro
A24: 46066 | B24: TELECHESKI E TELECHESKI LTDA ME - 0000074 | C24: 769/03 | D24: 3435.92 | E24: fevereiro
A25: 46066 | B25: LANZA MEDICAL EQUIP. ODONTO MEDICOS LTDA - 0000452 | C25: 783/02 | D25: 1714 | E25: fevereiro
A26: 46066 | B26: M. POWER IND.E COM. DE ELETR. LTDA - 0000216 | C26: 789/01 | D26: 860 | E26: fevereiro
A27: 46071 | B27: ALLPRINT LATINA AUTOMACAO DE MAQUINAS EA - 0000291 | C27: 770/03 | D27: 4105 | E27: fevereiro
A28: 46071 | B28: DIGISYSTEM IND. DE SIST. ELETRO. LTDA - 0000040 | C28: 786/02 | D28: 452 | E28: fevereiro
A29: 46071 | B29: PROVOLT TECNOLOGIA ELETRONICA LTDA - 0000886 | C29: 790/01 | D29: 1160.5 | E29: fevereiro
A30: 46071 | B30: DIGISYSTEM IND. DE SIST. ELETRO. LTDA - 0000040 | C30: 791/01 | D30: 121.7 | E30: fevereiro
A31: 46073 | B31: LANZA MEDICAL EQUIP. ODONTO ME | C31: 783/03 | D31: 1714 | E31: fevereiro
A32: 46073 | B32: TRANSFIX | C32: 792 | D32: 324.66 | E32: fevereiro
A33: 46076 | B33: SIMPLES CONNECT INDUSTRIA E COMERCIO LTA - 0000308 | C33: 782/02 | D33: 2850 | E33: fevereiro
A34: 46077 | B34: R. BAIÃO | C34: 793 | D34: 462 | E34: fevereiro
A35: 46078 | B35: TRANSFIX | C35: 803 | D35: 608.33 | E35: fevereiro
A36: 46079 | B36: MAX LED | C36: MOVIMENTAÇÃO | D36: 4000 | E36: fevereiro
A37: 46087 | B37: TRANSFIX | C37: 795 | D37: 5610.67 | E37: março | F37: =SUM(D37:D55) -> 37723.49
A38: 46087 | B38: MAX LED | C38: MOVIMENTO | D38: 7000 | E38: março
A39: 46087 | B39: ALLPRINT | C39: 796 | D39: 2581.66 | E39: março
A40: 46092 | B40: FERRTECH EQUIPAMEN | C40: 798/01 | D40: 1316.45 | E40: março
A41: 46092 | B41: FERRTECH EQUIPAMEN | C41: 778/03 | D41: 1751.38 | E41: março
A42: 46093 | B42: ALLPRINT LATINA | C42: 770/04 | D42: 4105 | E42: março
A43: 46093 | B43: J. M. MAQUINAS | C43: 799/01 | D43: 2081.25 | E43: março
A44: 46094 | B44: TRANSFIX | C44: 784 | D44: 608.33 | E44: março
A45: 46098 | B45: FERRTECH EQUIPAMEN | C45: 798 | D45: 1286.47 | E45: março
A46: 46099 | B46: FERRTECH EQUIPAMEN | C46: 800 | D46: 709.5 | E46: março
A47: 46100 | B47: TRANSFIX | C47: 803 + 792 | D47: 899.67 | E47: março
A48: 46104 | B48: ALLPRINT LATINA | C48: 796 | D48: 2581.67 | E48: março
A49: 46104 | B49: FERRTECH EQUIPAMEN | C49: 801 | D49: 543 | E49: março
A50: 46105 | B50: FERRTECH EQUIPAMEN | C50: 798 | D50: 1286.47 | E50: março
A51: 46105 | B51: SIMPLES CONECT | C51: 802 | D51: 1452 | E51: março
A52: 46106 | B52: FERRTECH EQUIPAMEN | C52: 800 | D52: 709.5 | E52: março
A53: 46111 | B53: R.BAIÃO | C53: 793 | D53: 462 | E53: março
A54: 46112 | B54: FERRTECH EQUIPAMEN | C54: 798 | D54: 1286.47 | E54: março
A55: 46112 | B55: SIMPLES CONECT | C55: 802 | D55: 1452 | E55: março
A56: 46113 | B56: TRANSFIX | C56: 795 | D56: 5610.66 | E56: abril | F56: =SUM(D56:D83) -> 105609.12
A57: 46118 | B57: ALLPRINT | C57: 796 | D57: 2581.67 | E57: abril
A58: 46119 | B58: SIMPLES CONECT | C58: 802 | D58: 1452 | E58: abril
A59: 46120 | B59: R.BAIÃO | C59: 804 | D59: 539 | E59: abril
A60: 46122 | B60: TRANSFIX | C60: 805 | D60: 1115 | E60: abril
A61: 46125 | B61: ALLPRINT | C61: 806 | D61: 1722.5 | E61: abril
A62: 46126 | B62: TRANSFIX | C62: 808 | D62: 294 | E62: abril
A63: 46126 | B63: SIMPLES CONECT | C63: 802 | D63: 1452 | E63: abril
A64: 46127 | B64: TAIKOM IMPORT | C64: IMPORTAÇÃO | D64: 5460 | E64: abril
A65: 46128 | B65: TELESHESK | C65: 807 | D65: 6200.34 | E65: abril
A66: 46129 | B66: TRANSFIX | C66: 792 | D66: 324.67 | E66: abril
A67: 46132 | B67: SIMPLES CONECT | C67: 809 | D67: 3720 | E67: abril
A68: 46134 | B68: TGL | C68: 810 | D68: 234 | E68: abril
A69: 46135 | B69: VCP DEVOL | C69: DEVOLUÇÃO | D69: 1479.8 | E69: abril
A70: 46136 | B70: VBN | C70: 823 | D70: 12352.44 | E70: abril
A71: 46139 | B71: TRANSFIX | C71: 805 | D71: 1115 | E71: abril
A72: 46139 | B72: ALLPRINT | C72: 806 | D72: 1722.5 | E72: abril
A73: 46139 | B73: FERRTECH | C73: 814 | D73: 1419.61 | E73: abril
A74: 46140 | B74: VBN | C74: 823/02 | D74: 12352.44 | E74: abril
A75: 46140 | B75: TRANSFIX | C75: 815/03 | D75: 6014.9 | E75: abril
A76: 46140 | B76: TELESHESK | C76: 807 | D76: 6200.33 | E76: abril
A77: 46140 | B77: TRANSFIX | C77: 815/04 | D77: 6014.9 | E77: abril
A78: 46140 | B78: VBN | C78: 823/2 | D78: 12352.44 | E78: abril
A79: 46140 | B79: TRANSFIX | C79: 815/05 | D79: 3364.09 | E79: abril
A80: 46140 | B80: MAX LED ILUM | C80: MOVIMENTAÇÃO | D80: 5500 | E80: abril
A81: 46140 | B81: ELETROFELIX | C81: 811 | D81: 390.33 | E81: abril
A82: 46140 | B82: R.BAIÃO | C82: 793 | D82: 462 | E82: abril
A83: 46141 | B83: J.M MAQUINAS | C83: 813 | D83: 4162.5 | E83: abril | F83: =SUM(D56:D83) -> 105609.12
A84: 46146 | B84: SIMPLES CONECT | C84: 809 | D84: 3720 | E84: maio
A85: 46146 | B85: FERRTECH | C85: 814 | D85: 1419.63 | E85: maio
A86: 46146 | B86: TRANSFIX | C86: 795 | D86: 5610.67 | E86: maio
A87: 46148 | B87: R. BAIÃO | C87: 816 | D87: 949 | E87: maio
A88: 46149 | B88: TRANSFIX | C88: 815 | D88: 6014.9 | E88: maio
A89: 46150 | B89: TAIKON | C89: 825 | D89: 5460 | E89: maio
A90: 46153 | B90: FERRTECH | C90: 814 | D90: 1419.63 | E90: maio
A91: 46156 | B91: TAIKON | C91: 12636 | D91: 8639.5 | E91: maio
A92: 46156 | B92: DIGISYSTEM | C92: 837 | D92: 69 | E92: maio
A93: 46156 | B93: TRANSFIX | C93: 815 | D93: 6014.9 | E93: maio
A94: 46160 | B94: TELESHESK | C94: 807 | D94: 6200.33 | E94: maio
A95: 46160 | B95: SIMPLES CONECT | C95: 809 | D95: 3720 | E95: maio
... A99: 46168 | B99: FERRTECH | C99: 826 | D99: 330 | E99: maio
A100: 46170 | B100: Max(bruno) | C100: I11 | D100: 1220 | E100: maio
A101: 46170 | B101: SIMPLES CONECT | C101: 825 | D101: 13412.5 | E101: maio

Sheet Saidas-fin-import
A1: DATA | B1: DESTINO | C1: JUSTIFICATIVA | D1: VALOR | M1: JUSTIFICATIVA
A2: 46024 | B2: SEGURO DE EMPRÉSTIMO | C2: SEGURO DE EMPRÉSTIMO | D2: 109.79 | E2: janeiro | M2: BANCO
A3: 46024 | B3: CAPITAL DE GIRO | C3: EMPRÉSTIMOS FGI | D3: 2920.88 | E3: janeiro | M3: BRINDES
A4: 46024 | B4: FEDEX | C4: TRANSPORTES IMPORTAÇÃO | D4: 2011.61 | E4: janeiro | M4: CARTÃO DE CRÉDITO
A5: 46024 | B5: BOLETOS | C5: BANCO | D5: 1.7 | E5: janeiro | M5: CONSUMO
A6: 46027 | B6: IDALL | C6: FORNECEDORES | D6: 658.67 | E6: janeiro | M6: EMPRÉSTIMOS FGI
A7: 46027 | B7: MATHEUS | C7: FUNCIONÁRIOS | D7: 250 | E7: janeiro | M7: EMPRÉSTIMO PRONAMP
A8: 46027 | B8: THAMIRES | C8: FUNCIONÁRIOS | D8: 250 | E8: janeiro | M8: FORNECEDORES
A9: 46027 | B9: BOLETOS | C9: BANCO | D9: 3.4 | E9: janeiro | M9: FUNCIONÁRIOS
A10: 46030 | B10: DHL EXPRES | C10: IMPORTAÇÕES | D10: 459.73 | E10: janeiro | M10: GASTOS FIXOS
A11: 46031 | B11: LS | C11: FORNECEDORES | D11: 1114.33 | E11: janeiro | M11: IMPORTAÇÃO
A12: 46034 | B12: BOLETOS | C12: BANCO | D12: 3.4 | E12: janeiro | M12: IMPOSTOS
A13: 46034 | B13: MATERIAL DE ESCRITÓRIO | C13: MATERIAL DE ESCRITÓRIO | D13: 1242 | E13: janeiro | M13: INVESTIMENTO
... A20: 46041 | B20: ALEX | C20: SÓCIOS | D20: 10000 | E20: janeiro | M20: TRANSPORTES IMPORTAÇÃO
A21: 46041 | B21: BOLETOS | C21: BANCO | D21: 3.4 | E21: janeiro
A22: 46042 | B22: DAS | C22: IMPOSTOS | D22: 440.26 | E22: janeiro
A23: 46042 | B23: ELVANI | C23: SÓCIOS | D23: 850 | E23: janeiro
A24: 46043 | B24: ALEX | C24: SÓCIOS | D24: 200 | E24: janeiro
A25: 46043 | B25: SIMENTOR | C25: IMPORTAÇÕES | D25: 30000 | E25: janeiro
A26: 46045 | B26: BOLETOS | C26: BANCO | D26: 1.7 | E26: janeiro
A27: 46048 | B27: LS | C27: FORNECEDORES | D27: 1114.34 | E27: janeiro
A28: 46048 | B28: CARTÃO | C28: SÓCIOS | D28: 17119.18 | E28: janeiro
A29: 46048 | B29: BOLETOS | C29: BANCO | D29: 1.7 | E29: janeiro
A30: 46051 | B30: LEO COMEDES | C30: FUNCIONÁRIOS | D30: 500 | E30: janeiro
A31: 46051 | B31: MARIA | C31: SÓCIOS | D31: 3000 | E31: janeiro | F31: =SUM(D2:D31) -> 77907.6
A32: 46055 | B32: SEGURO DE EMPRÉSTIMO | C32: SEGURO DE EMPRÉSTIMO | D32: 109.79 | E32: fevereiro
A33: 46055 | B33: CAPITAL DE GIRO | C33: EMPRÉSTIMOS FGI | D33: 3019.29 | E33: fevereiro
A34: 46055 | B34: PRICILA | C34: FUNCIONÁRIOS | D34: 190.8 | E34: fevereiro
A35: 46055 | B35: DAIANE | C35: FUNCIONÁRIOS | D35: 190.8 | E35: fevereiro
A36: 46055 | B36: FRANCISCO | C36: FUNCIONÁRIOS | D36: 190.08 | E36: fevereiro
A37: 46055 | B37: GILBERTO | C37: MANUTENÇÃO | D37: 250 | E37: fevereiro
A38: 46055 | B38: BOLETOS | C38: BANCO | D38: 1.7 | E38: fevereiro
A39: 46056 | B39: BOLETOS | C39: BANCO | D39: 1.7 | E39: fevereiro
A40: 46058 | B40: BOLETOS | C40: BANCO | D40: 1.81 | E40: fevereiro
A41: 46059 | B41: FCP | C41: FORNECEDORES | D41: 1121.26 | E41: fevereiro
A42: 46059 | B42: BOLETOS | C42: BANCO | D42: 1.81 | E42: fevereiro
A43: 46062 | B43: BOLETOS | C43: BANCO | D43: 3.62 | E43: fevereiro
A44: 46062 | B44: IDALL | C44: FORNECEDORES | D44: 1266.67 | E44: fevereiro | O44: BANCO
A45: 46062 | B45: LS | C45: FORNECEDORES | D45: 1114.33 | E45: fevereiro
A46: 46063 | B46: BOLETOS | C46: BANCO | D46: 3.62 | E46: fevereiro
A47: 46063 | B47: ALEX | C47: SÓCIOS | D47: 3000 | E47: fevereiro
A48: 46063 | B48: COLEGIO | C48: SÓCIOS | D48: 1166.4 | E48: fevereiro
A49: 46064 | B49: MATHEUS ROCHA EMPRESTIMO | C49: FUNCIONÁRIOS | D49: 2000 | E49: fevereiro
A50: 46064 | B50: GÁS | C50: SÓCIOS | D50: 316.66 | E50: fevereiro
A51: 46064 | B51: BOLETOS | C51: BANCO | D51: 3.62 | E51: fevereiro
A52: 46066 | B52: CAPITAL DE GIRO | C52: EMPRÉSTIMOS FGI | D52: 3585.46 | E52: fevereiro
A53: 46066 | B53: MARIA | C53: SÓCIOS | D53: 2500 | E53: fevereiro
A54: 46066 | B54: BOLETOS | C54: BANCO | D54: 5.43 | E54: fevereiro
A55: 46071 | B55: IA | C55: INVESTIMENTO | D55: 112.82 | E55: fevereiro
A56: 46071 | B56: BOLETOS | C56: BANCO | D56: 9.05 | E56: fevereiro
... A70: 46079 | B70: DHL | C70: TRANSPORTES IMPORTAÇÃO | D70: 1248.66 | E70: fevereiro
A71: 46079 | B71: EDUARDO | C71: FUNCIONÁRIOS | D71: 1000 | E71: fevereiro | F71: =SUM(D32:D71) -> 44764.38
A72: 46083 | B72: SEGURO | C72: SEGURO DE EMPRÉSTIMO | D72: 109.79 | E72: março
A73: 46083 | B73: CAPITAL DE GIRO | C73: EMPRÉSTIMO FGI | D73: 2724.27 | E73: março
A74: 46087 | B74: PRICILA | C74: FUNCIONÁRIOS | D74: 1282.8 | E74: março
A75: 46087 | B75: FRANCISCO | C75: FUNCIONÁRIOS | D75: 1516 | E75: março
A76: 46087 | B76: MPC | C76: FORNECEDORES | D76: 1121.25 | E76: março
A77: 46087 | B77: BOLETOS | C77: BANCO | D77: 1.81 | E77: março
A78: 46091 | B78: IDALL | C78: FORNECEDORES | D78: 1266.67 | E78: março
A79: 46091 | B79: LS | C79: FORNECEDORES | D79: 655 | E79: março
A80: 46092 | B80: BOLETOS | C80: BANCO | D80: 3.62 | E80: março
A81: 46093 | B81: BOLETOS | C81: BANCO | D81: 3.62 | E81: março
A82: 46094 | B82: CAPITAL DE GIRO 14/48 | C82: EMPRÉSTIMO PRONAMP | D82: 3621.21 | E82: março
A83: 46097 | B83: HANSER | C83: FORNECEDORES | D83: 612 | E83: março
... A100: 46111 | B100: BOLETOS | C100: BANCO | D100: 1.81 | E100: março
A101: 46112 | B101: BOLETOS | C101: BANCO | D101: 3.62 | E101: março | F101: =SUM(D72:D101) -> 35226.35
A102: 46113 | B102: WANDO | C102: TRANSPORTES | D102: 1380 | E102: abril
A103: 46114 | B103: SEGURO | C103: SEGURO DE EMPRÉSTIMO | D103: 109.79 | E103: abril
A104: 46114 | B104: CAPITAL DE GIRO | C104: EMPRÉSTIMO FGI | D104: 3019.29 | E104: abril
A105: 46114 | B105: EDUARDO | C105: FUNCIONÁRIOS | D105: 1000 | E105: abril
A106: 46114 | B106: JOSÉ MARIA | C106: FUNCIONÁRIOS | D106: 520.13 | E106: abril
A107: 46114 | B107: DHL | C107: IMPOSTOS | D107: 3724.03 | E107: abril
A108: 46118 | B108: BOLETOS | C108: BANCO | D108: 1.81 | E108: abril
A109: 46119 | B109: INGRID | C109: FUNCIONÁRIOS | D109: 1782.34 | E109: abril
A110: 46119 | B110: FRAN MONALISA | C110: FUNCIONÁRIOS | D110: 1851.25 | E110: abril
A111: 46119 | B111: BOLETOS | C111: BANCO | D111: 1.81 | E111: abril
A112: 46120 | B112: BOLETOS | C112: BANCO | D112: 1.81 | E112: abril
A113: 46122 | B113: IDALL | C113: FORNECEDORES | D113: 1292.42 | E113: abril
... A141: 46142 | B141: GILBERTO | C141: TRANSPORTES | D141: 100 | E141: abril
A142: 46142 | B142: COXINHA PA MENINAS | C142: CONSUMO | D142: 47.71 | E142: abril | F142: =SUM(D102:D142) -> 108035.78
A143: 46146 | B143: IDALL | C143: FORNECEDORES | D143: 1900 | E143: maio
A144: 46146 | B144: LS | C144: FORNECEDORES | D144: 1310 | E144: maio
A145: 46146 | B145: CAPITAL DE GIRO | C145: EMPRÉSTIMO FGI | D145: 3117.76 | E145: maio
A146: 46146 | B146: SEGURO | C146: SEGURO DE EMPRÉSTIMO | D146: 109.79 | E146: maio | M146: BANCO
A147: 46146 | B147: BOLETOS | C147: BANCO | D147: 3.62 | E147: maio | M147: BRINDES
A148: 46146 | B148: ALEX | C148: SÓCIOS | D148: 1000 | E148: maio | M148: CARTÃO DE CRÉDITO
A149: 46147 | B149: IOF NEGATIVO | C149: BANCO | D149: 107.13 | E149: maio | M149: CONSUMO
A150: 46148 | B150: BOLETOS | C150: BANCO | D150: 1.81 | E150: maio | M150: EMPRÉSTIMOS FGI
A151: 46149 | B151: INGRID | C151: FUNCIONÁRIOS | D151: 1494.8 | E151: maio | M151: EMPRÉSTIMO PRONAMP
A152: 46149 | B152: MONALISA | C152: FUNCIONÁRIOS | D152: 1494.8 | E152: maio | M152: FORNECEDORES
A153: 46149 | B153: ZÉ MARIA | C153: FUNCIONÁRIOS | D153: 2502.96 | E153: maio | M153: FUNCIONÁRIOS
A154: 46149 | B154: EDUARDO | C154: FUNCIONÁRIOS | D154: 1000 | E154: maio | M154: GASTOS FIXOS
A155: 46149 | B155: BOLETOS | C155: BANCO | D155: 1.81 | E155: maio | M155: IMPORTAÇÃO
A156: 46150 | B156: LEO | C156: FUNCIONÁRIOS | D156: 1300 | E156: maio | M156: IMPOSTOS
A157: 46153 | B157: BOLETOS | C157: BANCO | D157: 1.81 | E157: maio | M157: INVESTIMENTO
... A164: 46160 | B164: ADRIELE COMISSÃO | C164: SERVIÇOS | D164: 1500 | E164: maio | M164: TRANSPORTES IMPORTAÇÃO
A165: 46160 | B165: WANDO | C165: TRANSPORTES | D165: 1190 | E165: maio
A166: 46160 | B166: IDALL | C166: FORNECEDORES | D166: 1900 | E166: maio
A167: 46160 | B167: GILBERTO | C167: MANUTENÇÃO | D167: 1900 | E167: maio
A168: 46160 | B168: BOLETOS | C168: BANCO | D168: 5.43 | E168: maio
...

Sheet Entradas-NFE-Import
A1: Data | B1: Nfe | C1: Nome | D1: Valor
A2: 46031 | B2: 75376 | C2: IDALL | D2: 3800 | E2: JANEIRO
A3: 46034 | B3: 302 | C3: FCP | D3: 3363.76 | E3: JANEIRO
A4: 46043 | B4: 1 | C4: WORL | D4: 4295.5 | E4: JANEIRO
A5: 46059 | B5: 1 | C5: KUM LI | D5: 9065 | E5: FEVEREIRO
A6: 46059 | B6: 2 | C6: SIMENTOR | D6: 5775 | E6: FEVEREIRO
A7: 46059 | B7: 3 | C7: SIMENTOR | D7: 13191.72 | E7: FEVEREIRO
A8: 46066 | B8: 144 | C8: LS | D8: 1310 | E8: FEVEREIRO
A9: 46078 | B9: 75906 | C9: IDALL | D9: 3800 | E9: FEVEREIRO
A10: 46094 | B10: 18 | C10: SIMENTOR | D10: 15208 | E10: MARÇO
A11: 46104 | B11: 152 | C11: LS | D11: 2620 | E11: MARÇO
A12: 46105 | B12: 76238 | C12: IDALL | D12: 7600 | E12: MARÇO
A13: 46126 | B13: 817 | C13: DI DE IMPORTAÇÃO | D13: 9190.94 | E13: ABRIL
... A19: 46142 | B19: 165 | C19: LS IMP | D19: 3668 | E19: ABRIL
A20: 46149 | B20: I10 | C20: SIMENTOR / MAX LED (0000445) | D20: 22706.09 | E20: MAIO
A21: 46154 | B21: 76757 | C21: IDALL COM. ATAC. DE COMP. ELETR. LTDA (0000011) | D21: 10064 | E21: MAIO
A22: 46168 | B22: 172 | C22: LS COMPONENTES ELETRONICOS LTDA (0000197) | D22: 1572 | E22: MAIO
A23: 46168 | B23: 449 | C23: FCP IMPORTACAO E COMERCIO LTDA (0000398) | D23: 764.49 | E23: MAIO
A24: 46171 | B24: 264029 | C24: ACP COMERCIO ATACADISTA DE COMPONENTES E (0000249) | D24: 5991.6 | E24: MAIO

Sheet Saídas-NFE-import
A1: Data | B1: Nfe | C1: Nome | D1: Valor
A2: 46028 | B2: 781 | C2: R. BAIAO INDUSTRIA E COMERCIO LTDA (0000060) | D2: 980.84 | E2: JANEIRO
A3: 46031 | B3: 782 | C3: SIMPLES CONNECT INDUSTRIA E COMERCIO LTA (0000308) | D3: 5700 | E3: JANEIRO
A4: 46031 | B4: 783 | C4: LANZA MEDICAL EQUIP. ODONTO MEDICOS LTDA (0000452) | D4: 5142 | E4: JANEIRO
A5: 46034 | B5: 784 | C5: TRANSFIX ASSISTENCIA TECN. E VENDAS EQUI (0000199) | D5: 1825 | E5: JANEIRO
A6: 46035 | B6: 785 | C6: J.M. MAQUINAS AUTOMOTIVAS EIRELI (0000387) | D6: 5272.5 | E6: JANEIRO
A7: 46035 | B7: 786 | C7: DIGISYSTEM IND. DE SIST. ELETRO. LTDA (0000040) | D7: 904 | E7: JANEIRO
A8: 46036 | B8: 787 | C8: DENTSCLER IND. DE APAR. ODONTO. EIRELLI (0000390) | D8: 732 | E8: JANEIRO
A9: 46038 | B9: 789 | C9: M. POWER IND.E COM. DE ELETR. LTDA (0000216) | D9: 860 | E9: JANEIRO
A10: 46038 | B10: 790 | C10: PROVOLT TECNOLOGIA ELETRONICA LTDA (0000886) | D10: 1160.5 | E10: JANEIRO
A11: 46043 | B11: 791 | C11: DIGISYSTEM IND. DE SIST. ELETRO. LTDA (0000040) | D11: 121.7 | E11: JANEIRO
A12: 46045 | B12: 792 | C12: TRANSFIX ASSISTENCIA TECN. E VENDAS EQUI (0000199) | D12: 974 | E12: JANEIRO
A13: 46050 | B13: 793 | C13: R. BAIAO INDUSTRIA E COMERCIO LTDA (0000060) | D13: 1386 | E13: JANEIRO
... A67: 46171 | B67: 859 | C67: MARTINS MARTINS SERVICOS ASSOCIADOS LTDA (0001381) | D67: 1500 | E67: MAIO

Sheet ENTRADAS - FIN - ilumi
A1: Data | B1: Cliente | C1: Nota | D1: Valor | E1: Banco | F1: Mês
A2: 46024 | B2: RUSSER BRASIL | C2: 11853 | D2: 175 | E2: ITAÚ | F2: Janeiro | G2: =SUM(D2:D115) -> 132275.4
A3: 46024 | B3: BASSOMED EQUIPAMENTOS MEDICOS E ODONTOLO - 0000660 | C3: 11850/01 | D3: 594.35 | E3: ITAÚ | F3: Janeiro
A4: 46024 | B4: BASSOMED EQUIPAMENTOS MEDICOS E ODONTOLO - 0000660 | C4: 11762/04 | D4: 1255.08 | E4: ITAÚ | F4: Janeiro
A5: 46024 | B5: ALLPRINT LATINA AUTOMACAO DE MAQUINAS EA - 0000291 | C5: 11861/01 | D5: 1875 | E5: ITAÚ | F5: Janeiro
A6: 46024 | B6: SSAT SINALIZACAO E ADESIVOS EIRELI EPP - 0000072 | C6: 11836/01 | D6: 1016.84 | E6: ITAÚ | F6: Janeiro
A7: 46024 | B7: NEW TRAFFIC CONTROL TEC. E INOVACAO LTDA - 0000773 | C7: 11825/02 | D7: 1331.67 | E7: ITAÚ | F7: Janeiro
A8: 46024 | B8: BASSOMED EQUIPAMENTOS MEDICOS E ODONTOLO - 0000660 | C8: 11808/02 | D8: 2142.07 | E8: ITAÚ | F8: Janeiro
A9: 46024 | B9: CARINE G RODRIGUES - 0000764 | C9: 11846/01 | D9: 2180.96 | E9: ITAÚ | F9: Janeiro
A10: 46024 | B10: CITTA ELETRONICA IND. E COM. LTDA ME - 0000532 | C10: 11810/02 | D10: 843.67 | E10: ITAÚ | F10: Janeiro
A11: 46024 | B11: NEW TRAFFIC CONTROL TEC. E INOVACAO LTDA - 0000773 | C11: 11855/01 | D11: 797 | E11: ITAÚ | F11: Janeiro
A12: 46027 | B12: DENTSCLER IND. DE APAR. ODONTO. EIRELLI - 0000390 | C12: 11827/02 | D12: 373.25 | E12: ITAÚ | F12: Janeiro
A13: 46027 | B13: S.T.E.E. TECNOLOGIA ELETROELETRONICA LT - 0000062 | C13: 11862/01 | D13: 853.9 | E13: ITAÚ | F13: Janeiro
A14: 46027 | B14: SPECTO PAINEIS ELETRONICO LTDA - 0000071 | C14: 11718/02 | D14: 769.25 | E14: ITAÚ | F14: Janeiro
... A32: 46028 | B32: COMP TOTAL DEVOLÇÃO | C32: DEVOLUÇÃO | D32: 35 | E32: ITAÚ | F32: Janeiro
A33: 46029 | B33: HIGTHZ | C33: 11813 | D33: 23.76 | E33: ITAÚ | F33: Janeiro
A34: 46029 | B34: CHARLES | C34: SNF | D34: 160 | E34: ITAÚ | F34: Janeiro
A35: 46029 | B35: CURTIS | C35: 11885 | D35: 316 | E35: ITAÚ | F35: Janeiro
A36: 46029 | B36: BASSOMED EQUIPAMENTOS MEDICOS E ODONTOLO - 0000660 | C36: 11886/01 | D36: 2396.4 | E36: ITAÚ | F36: Janeiro
A37: 46029 | B37: T.G.L. ELETRO ELETRONICO LTDA - ME - 0000073 | C37: 11802/03 | D37: 376.67 | E37: ITAÚ | F37: Janeiro
A38: 46029 | B38: CITTA ELETRONICA IND. E COM. LTDA ME - 0000532 | C38: 11882/01 | D38: 589 | E38: ITAÚ | F38: Janeiro
A39: 46029 | B39: BASSOMED EQUIPAMENTOS MEDICOS E ODONTOLO - 0000660 | C39: 11808/03 | D39: 2142.07 | E39: ITAÚ | F39: Janeiro
A40: 46029 | B40: CARINE G RODRIGUES - 0000764 | C40: 11846/02 | D40: 659.52 | E40: ITAÚ | F40: Janeiro
A41: 46030 | B41: E DE OLIVEIRA | C41: 11919 | D41: 232 | E41: ITAÚ | F41: Janeiro
A42: 46030 | B42: FERRTECH EQUIPAMENTOS ELETRONICA LTDA -E - 0000081 | C42: 11815/03 | D42: 532.77 | E42: ITAÚ | F42: Janeiro
A43: 46030 | B43: ALIGERA EQUIPAMENTOS DIGITAIS LTDA - 0000188 | C43: 11896/01 | D43: 250 | E43: ITAÚ | F43: Janeiro
A44: 46030 | B44: BASSOMED EQUIPAMENTOS MEDICOS E ODONTOLO - 0000660 | C44: 11850/02 | D44: 594.35 | E44: ITAÚ | F44: Janeiro
A45: 46030 | B45: CITTA ELETRONICA IND. E COM. LTDA ME - 0000532 | C45: 11810/03 | D45: 843.67 | E45: ITAÚ | F45: Janeiro
A46: 46030 | B46: ELETROFELIX INDUSTRIA E COMERCIO LTDA - 0000477 | C46: 11800/03 | D46: 723.23 | E46: ITAÚ | F46: Janeiro
A47: 46030 | B47: CONDUVOX TELEMATICA LTDA - 0000031 | C47: 11895/01 | D47: 481.94 | E47: ITAÚ | F47: Janeiro
A48: 46031 | B48: SEMI-DIGITAL LTDA - 0000450 | C48: 11798/01 | D48: 270 | E48: ITAÚ | F48: Janeiro
A49: 46031 | B49: IMPACTO COMPONENTES ELETRO ELETRRONICOS - 0000154 | C49: 11901/01 | D49: 252 | E49: ITAÚ | F49: Janeiro
A50: 46031 | B50: FOCUS TECNOLOGIA E SOLUCOES LTDA - 0000742 | C50: 11883/01 | D50: 340.84 | E50: ITAÚ | F50: Janeiro
A51: 46031 | B51: NEW TRAFFIC CONTROL TEC. E INOVACAO LTDA - 0000773 | C51: 11825/03 | D51: 1331.67 | E51: ITAÚ | F51: Janeiro
A52: 46031 | B52: NEW TRAFFIC CONTROL TEC. E INOVACAO LTDA - 0000773 | C52: 11855/02 | D52: 797 | E52: ITAÚ | F52: Janeiro
A53: 46031 | B53: FZW INNOVATION LTDA - 0000848 | C53: 11811 | D53: 1943.46 | E53: ITAÚ | F53: Janeiro
... A66: 46035 | B66: CHARLES | C66: SNF | D66: 160 | E66: ITAÚ | F66: Janeiro
A67: 46035 | B67: Taikon JAGUARY | C67: 11973 | D67: 4029 | E67: ITAÚ | F67: Janeiro
A68: 46036 | B68: VALNEI | C68: 11959 | D68: 253.2 | E68: ITAÚ | F68: Janeiro
A69: 46036 | B69: PRODUPARK EQUIP. ELETRO. E IMP. LTDA - 0000056 | C69: 11725/01 | D69: 1359.74 | E69: ITAÚ | F69: Janeiro
A70: 46036 | B70: PRODUPARK EQUIP. ELETRO. E IMP. LTDA - 0000056 | C70: 11725/02 | D70: 1300.95 | E70: ITAÚ | F70: Janeiro
A71: 46036 | B71: PRODUPARK EQUIP. ELETRO. E IMP. LTDA - 0000056 | C71: 11725/03 | D71: 1242.15 | E71: ITAÚ | F71: Janeiro
A72: 46036 | B72: BASSOMED EQUIPAMENTOS MEDICOS E ODONTOLO - 0000660 | C72: 11886/02 | D72: 2396.4 | E72: ITAÚ | F72: Janeiro
A73: 46036 | B73: SEBASTIAO CESAR GRASSI ELETRONICOS - M.. - 0000279 | C73: 11925/01 | D73: 1153.8 | E73: ITAÚ | F73: Janeiro
A74: 46037 | B74: CHARLES | C74: SNF | D74: 489.5 | E74: ITAÚ | F74: Janeiro
A75: 46037 | B75: LSR | C75: 11968 | D75: 93.2 | E75: ITAÚ | F75: Janeiro
A76: 46038 | B76: NIATRON IND. E COM. DE EQUIP. ELETRO. - 0000143 | C76: 11761/03 | D76: 811.07 | E76: ITAÚ | F76: Janeiro
A77: 46038 | B77: ACHEI COMPONENTES ELETRONICOS - 0000503 | C77: 11777/03 | D77: 1012.38 | E77: ITAÚ | F77: Janeiro
A78: 46038 | B78: TELECHESKI E TELECHESKI LTDA ME - 0000074 | C78: 11779/02 | D78: 485 | E78: ITAÚ | F78: Janeiro
A79: 46038 | B79: SSAT SINALIZACAO E ADESIVOS EIRELI EPP - 0000072 | C79: 11836/02 | D79: 1016.83 | E79: ITAÚ | F79: Janeiro
A80: 46038 | B80: RALCOMP COMP. ELETRONICOS EIRELI ME - 0000474 | C80: 11775/03 | D80: 880 | E80: ITAÚ | F80: Janeiro
A81: 46038 | B81: HIGTHZ | C81: 11945 | D81: 56 | E81: ITAÚ | F81: Janeiro
A82: 46041 | B82: PRODUTOS ELETRONICOS FRATA LTDA - 0000223 | C82: 11849 | D82: 1540 | E82: ITAÚ | F82: Janeiro
A83: 46041 | B83: NEW TRAFFIC CONTROL TEC. E INOVACAO LTDA - 0000773 | C83: 11854 | D83: 476.67 | E83: ITAÚ | F83: Janeiro
A84: 46041 | B84: SIMPLES CONECT | C84: 11913 | D84: 481 | E84: ITAÚ | F84: Janeiro
A85: 46041 | B85: SEBASTIAO CESAR GRASSI ELETRONICOS - M.. - 0000279 | C85: 11925 | D85: 1153.81 | E85: ITAÚ | F85: Janeiro
A86: 46042 | B86: ROYALCOMP | C86: 11712 | D86: 1150 | E86: ITAÚ | F86: Janeiro
A87: 46043 | B87: ALLPRINT LATINA AUTOMACAO DE MAQUINAS EA - 0000291 | C87: 11650 | D87: 785.77 | E87: ITAÚ | F87: Janeiro
A88: 46043 | B88: BASSOMED EQUIPAMENTOS MEDICOS E ODONTOLO - 0000660 | C88: 11886 | D88: 2396.4 | E88: ITAÚ | F88: Janeiro
A89: 46043 | B89: MCM | C89: 11995 | D89: 1500 | E89: ITAÚ | F89: Janeiro
A90: 46044 | B90: MCM | C90: 12013 | D90: 5039.6 | E90: ITAÚ | F90: Janeiro
A91: 46044 | B91: FERRTECH EQUIPAMENTOS ELETRONICA LTDA -E - 0000081 | C91: 11920 | D91: 333.36 | E91: ITAÚ | F91: Janeiro
A92: 46044 | B92: NEW TEC | C92: 45 | D92: 160 | E92: ITAÚ | F92: Janeiro
... A103: 46051 | B103: ACHEI COMPONENTES ELETRONICOS - 0000503 | C103: 12040 | D103: 163.5 | E103: ITAÚ | F103: Janeiro
A104: 46051 | B104: CRDS | C104: 12033 E 794 | D104: 319.5 | E104: ITAÚ | F104: Janeiro
A105: 46051 | B105: NEXXO | C105: 11757 | D105: 32 | E105: ITAÚ | F105: Janeiro
A106: 46051 | B106: EASTEC | C106: 11814 | D106: 120 | E106: ITAÚ | F106: Janeiro
A107: 46051 | B107: E DE OLIVEIRA | C107: 12038 | D107: 301 | E107: ITAÚ | F107: Janeiro
A108: 46051 | B108: T.G.L. ELETRO ELETRONICO LTDA - ME - 0000073 | C108: 11910 | D108: 2040 | E108: ITAÚ | F108: Janeiro
A109: 46052 | B109: LIFE | C109: 11836 | D109: 1016.83 | E109: ITAÚ | F109: Janeiro
A110: 46052 | B110: SSAT SINALIZACAO E ADESIVOS EIRELI EPP - 0000072 | C110: 11830 | D110: 2566.68 | E110: ITAÚ | F110: Janeiro
A111: 46024 | B111: POWERFLEET | C111: 11834 | D111: 3850 | E111: BRADESCO | F111: Janeiro
A112: 46038 | B112: GISLENE | C112: 37 | D112: 380.34 | E112: BRADESCO | F112: Janeiro
A113: 46041 | B113: MAX LED ILUM. BRAD | C113: MOVIMENTO | D113: 10000 | E113: BRADESCO | F113: Janeiro
A114: 46043 | B114: GISLENE | C114: 37 | D114: 380.33 | E114: BRADESCO | F114: Janeiro
A115: 46050 | B115: GISLENE | C115: 37 | D115: 380.33 | E115: BRADESCO | F115: Janeiro
A116: 46055 | B116: ACHEI | C116: 11777 | D116: 1012.38 | E116: ITAÚ | F116: Fevereiro | G116: =SUM(D116:D236) -> 126679.25
A117: 46055 | B117: PRODUTOS FRATA | C117: 11849 | D117: 1540 | E117: ITAÚ | F117: Fevereiro
A118: 46055 | B118: SIMPLES CONECT | C118: 11913 | D118: 481 | E118: ITAÚ | F118: Fevereiro
A119: 46056 | B119: NEW TRAFIC | C119: 11854 | D119: 476.67 | E119: ITAÚ | F119: Fevereiro
A120: 46056 | B120: COMLINK | C120: 11916 | D120: 2550 | E120: ITAÚ | F120: Fevereiro
A121: 46056 | B121: PREMIX | C121: 12052 | D121: 265.5 | E121: ITAÚ | F121: Fevereiro
A122: 46057 | B122: MARTINS | C122: 797 | D122: 1000 | E122: ITAÚ | F122: Fevereiro
A123: 46057 | B123: EDERSON LP | C123: 11917 | D123: 1087.61 | E123: ITAÚ | F123: Fevereiro
A124: 46058 | B124: FZW | C124: 11811 | D124: 1925.37 | E124: ITAÚ | F124: Fevereiro
A125: 46058 | B125: R.BAIÃO | C125: 11918 | D125: 5385.97 | E125: ITAÚ | F125: Fevereiro
A126: 46058 | B126: NIATRON | C126: 11921 | D126: 476.7 | E126: ITAÚ | F126: Fevereiro
A127: 46058 | B127: FERRTECH | C127: 11922 | D127: 542 | E127: ITAÚ | F127: Fevereiro
A128: 46058 | B128: FIBERWAM | C128: 11923 | D128: 407 | E128: ITAÚ | F128: Fevereiro
A129: 46058 | B129: TRANSFIX | C129: 11953 + 11935 | D129: 1067.66 | E129: ITAÚ | F129: Fevereiro
A130: 46059 | B130: NEW TEC | C130: snf 45,46,47 | D130: 393.5 | E130: ITAÚ | F130: Fevereiro
A131: 46059 | B131: WKS TECHNOLOGY DO BRASIL - 0000208 | C131: 11924/01 | D131: 409.32 | E131: ITAÚ | F131: Fevereiro
A132: 46059 | B132: CRISTOFOLI EQUIP. DE BIOSSEGURANCA LTDA - 0000146 | C132: 11926/01 | D132: 325 | E132: ITAÚ | F132: Fevereiro
A133: 46059 | B133: CRISTOFOLI EQUIP. DE BIOSSEGURANCA LTDA - 0000146 | C133: 11927/01 | D133: 650 | E133: ITAÚ | F133: Fevereiro
A134: 46059 | B134: ARIELTEK INDUSTRIA E COMERCIO LTDA - 0000314 | C134: 11928/01 | D134: 834 | E134: ITAÚ | F134: Fevereiro
A135: 46059 | B135: BASSOMED EQUIPAMENTOS MEDICOS E ODONTOLO - 0000660 | C135: 11929/01 | D135: 986.1 | E135: ITAÚ | F135: Fevereiro
A136: 46059 | B136: SIMPLES CONNECT INDUSTRIA E COMERCIO LTA - 0000308 | C136: 11930/01 | D136: 442 | E136: ITAÚ | F136: Fevereiro
A137: 46059 | B137: M. POWER IND.E COM. DE ELETR. LTDA - 0000216 | C137: 11931/01 | D137: 552 | E137: ITAÚ | F137: Fevereiro
A138: 46059 | B138: BIQUAD | C138: 12108 | D138: 175 | E138: ITAÚ | F138: Fevereiro
A139: 46062 | B139: HIGTHZ | C139: 12063 | D139: 62 | E139: ITAÚ | F139: Fevereiro
...

Sheet SAIDAS-FIN-ilumi
A1: Data | B1: Destino | C1: Categoria | D1: Valor | E1: Banco | F1: Mês | L1: Categoria
A2: 46024 | B2: CIKA ELETRONICA | C2: FORNECEDORES | D2: 955.53 | E2: ITAÚ | F2: Janeiro | G2: =SUM(D2:D141) -> 116350.31 | L2: BANCO
A3: 46024 | B3: ALLSEMI TECNOLOGIA E EIRELI | C3: FORNECEDORES | D3: 905.25 | E3: ITAÚ | F3: Janeiro | G3: =SUMIF(C:C,"FORNECEDORES",D:D) -> 436248.53 | L3: CARTÃO DE CRÉDITO
A4: 46024 | B4: ZENNER | C4: FORNECEDORES | D4: 350 | E4: ITAÚ | F4: Janeiro | L4: CONSUMO
A5: 46024 | B5: BOLETOS | C5: BANCO | D5: 15.3 | E5: ITAÚ | F5: Janeiro | L5: CONTABILIDADE
A6: 46024 | B6: JOSÉ PINHEIRO MERCUR | C6: FORNECEDORES | D6: 850 | E6: ITAÚ | F6: Janeiro | L6: DEVOLUÇÃO
A7: 46024 | B7: LECOMP COMERCIAL DE COMPONENTE | C7: FORNECEDORES | D7: 528.8 | E7: ITAÚ | F7: Janeiro | L7: EMPRÉSTIMO
A8: 46024 | B8: TRICOMP COMERCIAL E LTDA | C8: FORNECEDORES | D8: 418.56 | E8: ITAÚ | F8: Janeiro | L8: EMPRÉSTIMO CAPITAL DE GIRO ITAÚ
A9: 46024 | B9: ALLNETSYS COMERCIO I S LTDA | C9: FORNECEDORES | D9: 401.4 | E9: ITAÚ | F9: Janeiro | L9: EMPRÉSTIMO CAPITAL DE GIRO BRADESCO
A10: 46024 | B10: IDALL COMERCIO ATACADISTA DE C | C10: FORNECEDORES | D10: 570 | E10: ITAÚ | F10: Janeiro | L10: FORNECEDORES
A11: 46024 | B11: MEGAPIX | C11: FORNECEDORES | D11: 610 | E11: ITAÚ | F11: Janeiro | L11: FUNCIONÁRIOS
A12: 46024 | B12: DLT SUPRIMENTOS | C12: FORNECEDORES | D12: 391 | E12: ITAÚ | F12: Janeiro | L12: FUNCIONÁRIOS (VR)
A13: 46027 | B13: LECOMP COMERCIAL DE COMPONENTE | C13: FORNECEDORES | D13: 550 | E13: ITAÚ | F13: Janeiro | L13: GASTOS FIXOS
A14: 46027 | B14: IDALL COMERCIO ATACADISTA DE C | C14: FORNECEDORES | D14: 800 | E14: ITAÚ | F14: Janeiro | L14: IMPORTAÇÃO
A15: 46027 | B15: ACP C A COMP ELETRONICOS LTDA | C15: FORNECEDORES | D15: 452.67 | E15: ITAÚ | F15: Janeiro | L15: IMPOSTOS
... A24: 46027 | B24: ELLO PRESTACAO DE SERVICOS LTD | C24: FUNCIONÁRIOS | D24: 70 | E24: ITAÚ | F24: Janeiro | L24: TRANSPORTES
A25: 46027 | B25: ZENNER | C25: FORNECEDORES | D25: 141 | E25: ITAÚ | F25: Janeiro
A26: 46027 | B26: MATHEUS COND | C26: FUNCIONÁRIOS | D26: 250 | E26: ITAÚ | F26: Janeiro
A27: 46027 | B27: CORREIOS | C27: TRANSPORTES | D27: 1928.84 | E27: ITAÚ | F27: Janeiro
A28: 46027 | B28: BOLETOS | C28: BANCO | D28: 28.87 | E28: ITAÚ | F28: Janeiro | L28: INVESTIMENTO
A29: 46028 | B29: BOLETOS | C29: BANCO | D29: 10.2 | E29: ITAÚ | F29: Janeiro | L29: INVESTIMENTO
A30: 46028 | B30: COMP TOTAL C I C ELETRONICOS | C30: FORNECEDORES | D30: 35 | E30: ITAÚ | F30: Janeiro | L30: INVESTIMENTO
A31: 46028 | B31: MEGAPIX | C31: FORNECEDORES | D31: 28 | E31: ITAÚ | F31: Janeiro | L31: INVESTIMENTO
A32: 46028 | B32: ALLNETSYS COMERCIO I S LTDA | C32: FORNECEDORES | D32: 75 | E32: ITAÚ | F32: Janeiro | L32: INVESTIMENTO
A33: 46028 | B33: MKB ELETRONICA LTDA | C33: FORNECEDORES | D33: 1159.86 | E33: ITAÚ | F33: Janeiro | L33: INVESTIMENTO
A34: 46028 | B34: ALLNETSYS COMERCIO I S LTDA | C34: FORNECEDORES | D34: 305 | E34: ITAÚ | F34: Janeiro | L34: INVESTIMENTO
A35: 46028 | B35: COMP TOTAL C I C ELETRONICOS | C35: FORNECEDORES | D35: 215.13 | E35: ITAÚ | F35: Janeiro | L35: INVESTIMENTO
A36: 46029 | B36: DISPLAY MAX ELETRONICA LTDA | C36: FORNECEDORES | D36: 93 | E36: ITAÚ | F36: Janeiro
A37: 46029 | B37: FADAMAR | C37: INVESTIMENTO | D37: 800 | E37: ITAÚ | F37: Janeiro | L37: MANUTENÇÃO
A38: 46029 | B38: TRYNIT WWG4 COBR | C38: FORNECEDORES | D38: 177.1 | E38: ITAÚ | F38: Janeiro | L38: MANUTENÇÃO
A39: 46029 | B39: ZENER COMPONENTES ELETRONIC LT | C39: FORNECEDORES | D39: 558.5 | E39: ITAÚ | F39: Janeiro | L39: MANUTENÇÃO
A40: 46029 | B40: BOLETOS | C40: BANCO | D40: 17.64 | E40: ITAÚ | F40: Janeiro | L40: MANUTENÇÃO
A41: 46030 | B41: LECOMP COMERCIAL DE COMPONENTE | C41: FORNECEDORES | D41: 486.5 | E41: ITAÚ | F41: Janeiro | L41: MARKETING
A42: 46030 | B42: ACP C A COMP ELETRONICOS LTDA | C42: FORNECEDORES | D42: 533.93 | E42: ITAÚ | F42: Janeiro | L42: MARKETING
A43: 46030 | B43: VETRONIC COM ELETRONICA LTDA | C43: FORNECEDORES | D43: 774.38 | E43: ITAÚ | F43: Janeiro | L43: MOVIMENTO
A44: 46030 | B44: REIMOLD INDUSTRIA E COMERCIO D | C44: FORNECEDORES | D44: 1847.75 | E44: ITAÚ | F44: Janeiro | L44: MOVIMENTO
A45: 46030 | B45: DISPLAY MAX ELETRONICA LTDA | C45: FORNECEDORES | D45: 607.53 | E45: ITAÚ | F45: Janeiro | L45: MOVIMENTO
A46: 46030 | B46: TRYNIT CREDERE CONS | C46: FORNECEDORES | D46: 264 | E46: ITAÚ | F46: Janeiro | L46: MOVIMENTO
A47: 46030 | B47: TRICOMP COMERCIAL E LTDA | C47: FORNECEDORES | D47: 633.2 | E47: ITAÚ | F47: Janeiro | L47: MOVIMENTO
A48: 46030 | B48: MKB SENSORES LTDA | C48: FORNECEDORES | D48: 945.24 | E48: ITAÚ | F48: Janeiro | L48: MOVIMENTO
... A71: 46034 | B71: SINDICATO DOS COMERCIARIOS DE | C71: FUNCIONÁRIOS | D71: 47.37 | E71: ITAÚ | F71: Janeiro | L71: TRANSPORTES
A72: 46034 | B72: COMP TOTAL C I C ELETRONICOS | C72: FORNECEDORES | D72: 451.13 | E72: ITAÚ | F72: Janeiro
A73: 46034 | B73: COMP TOTAL C I C ELETRONICOS | C73: FORNECEDORES | D73: 553.81 | E73: ITAÚ | F73: Janeiro
A74: 46034 | B74: MULT COMERCIAL LTDA | C74: FORNECEDORES | D74: 35 | E74: ITAÚ | F74: Janeiro
A75: 46034 | B75: ACP C A COMP ELETRONICOS LTDA | C75: FORNECEDORES | D75: 601.2 | E75: ITAÚ | F75: Janeiro
A76: 46034 | B76: ACP C A COMP ELETRONICOS LTDA | C76: FORNECEDORES | D76: 544.3 | E76: ITAÚ | F76: Janeiro
A77: 46034 | B77: BOLETOS | C77: BANCO | D77: 11.9 | E77: ITAÚ | F77: Janeiro
A78: 46035 | B78: BING | C78: FORNECEDORES | D78: 529.5 | E78: ITAÚ | F78: Janeiro
A79: 46035 | B79: TRICOMP COMERCIAL E LTDA | C79: FORNECEDORES | D79: 286.66 | E79: ITAÚ | F79: Janeiro
A80: 46035 | B80: BOLETOS | C80: BANCO | D80: 5.1 | E80: ITAÚ | F80: Janeiro
A81: 46036 | B81: BOLETOS | C81: BANCO | D81: 8.5 | E81: ITAÚ | F81: Janeiro
A82: 46036 | B82: ACP C A COMP ELETRONICOS LTDA | C82: FORNECEDORES | D82: 2064.71 | E82: ITAÚ | F82: Janeiro
A83: 46036 | B83: ACP C A COMP ELETRONICOS LTDA | C83: FORNECEDORES | D83: 717.27 | E83: ITAÚ | F83: Janeiro
... A138: 46052 | B138: BOLETOS | C138: BANCO | D138: 3.4 | E138: ITAÚ | F138: Janeiro
A139: 46036 | B139: CAPITAL DE GIRO | C139: EMPRÉSTIMO CAPITAL DE GIRO BRADESCO | D139: 6175.89 | E139: BRADESCO | F139: Janeiro | H139: 40
A140: 46037 | B140: CAPITALIZAÇÃO | C140: BANCO | D140: 209.66 | E140: BRADESCO | F140: Janeiro
A141: 46044 | B141: MARCELO SITE | C141: MARKETING | D141: 1207 | E141: BRADESCO | F141: Janeiro
A142: 46055 | B142: JOSÉ PINHEIRO | C142: FORNECEDORES | D142: 1176 | E142: ITAÚ | F142: Fevereiro | G142: =SUM(D142:D290) -> 133410.26
A143: 46055 | B143: LECOMP | C143: FORNECEDORES | D143: 466.5 | E143: ITAÚ | F143: Fevereiro
A144: 46055 | B144: BOLETOS | C144: BANCO | D144: 5.1 | E144: ITAÚ | F144: Fevereiro
A145: 46056 | B145: BOLETOS | C145: BANCO | D145: 3.4 | E145: ITAÚ | F145: Fevereiro
A146: 46056 | B146: FILCRIL | C146: FORNECEDORES | D146: 791.35 | E146: ITAÚ | F146: Fevereiro
A147: 46056 | B147: DISPLAY MAX | C147: FORNECEDORES | D147: 1253.33 | E147: ITAÚ | F147: Fevereiro
A148: 46056 | B148: ACP | C148: FORNECEDORES | D148: 2064.71 | E148: ITAÚ | F148: Fevereiro
A149: 46056 | B149: COMP TOTAL | C149: FORNECEDORES | D149: 181.05 | E149: ITAÚ | F149: Fevereiro
A150: 46056 | B150: BOLETOS | C150: BANCO | D150: 1.7 | E150: ITAÚ | F150: Fevereiro
A151: 46057 | B151: ZENER | C151: FORNECEDORES | D151: 612.5 | E151: ITAÚ | F151: Fevereiro
A152: 46057 | B152: ALLNETS | C152: FORNECEDORES | D152: 150 | E152: ITAÚ | F152: Fevereiro
A153: 46058 | B153: IUVEM FIDC MUL | C153: GASTOS FIXOS | D153: 1270 | E153: ITAÚ | F153: Fevereiro
A154: 46058 | B154: EMP. BRASIL CORREIOS | C154: TRANSPORTES | D154: 1523.39 | E154: ITAÚ | F154: Fevereiro
... A289: 46071 | B289: CAPITALIZAÇÃO | C289: INVESTIMENTO | D289: 209.66 | E289: BRADESCO | F289: Fevereiro
A290: 46071 | B290: CAPITAL DE GIRO | C290: EMPRÉSTIMO CAPITAL DE GIRO BRADESCO | D290: 6241.39 | E290: BRADESCO | F290: Fevereiro | H290: 41
A291: 46086 | B291: LECOMP | C291: FORNECEDORES | D291: 83 | E291: BRADESCO | F291: Março | G291: =SUM(D291:D492) -> 192968.08
A292: 46092 | B292: LECOMP | C292: FORNECEDORES | D292: 50 | E292: BRADESCO | F292: Março
A293: 46097 | B293: CAPITALIZAÇÃO | C293: INVESTIMENTO | D293: 218.6 | E293: BRADESCO | F293: Março
A294: 46097 | B294: CAPITAL DE GIRO | C294: EMPRÉSTIMO CAPITAL DE GIRO BRADESCO | D294: 6303.62 | E294: BRADESCO | F294: Março | H294: 42
A295: 46106 | B295: MDS | C295: FORNECEDORES | D295: 268.5 | E295: BRADESCO | F295: Março
A296: 46108 | B296: LECOMP | C296: FORNECEDORES | D296: 70 | E296: BRADESCO | F296: Março
A297: 46111 | B297: WILSON | C297: TRANSPORTES | D297: 240 | E297: BRADESCO | F297: Março
A298: 46083 | B298: COMP TOTAL | C298: FORNECEDORES | D298: 90.53 | E298: ITAÚ | F298: Março
A299: 46083 | B299: IDALL COM | C299: FORNECEDORES | D299: 682.47 | E299: ITAÚ | F299: Março
A300: 46083 | B300: LECOMP COM | C300: FORNECEDORES | D300: 316.87 | E300: ITAÚ | F300: Março
A301: 46083 | B301: DISPLAY MAX | C301: FORNECEDORES | D301: 570 | E301: ITAÚ | F301: Março
A302: 46083 | B302: DISPLAY MAX | C302: FORNECEDORES | D302: 660.8 | E302: ITAÚ | F302: Março
A303: 46083 | B303: LECOMP COM | C303: FORNECEDORES | D303: 425 | E303: ITAÚ | F303: Março
A304: 46083 | B304: LECOMP COM | C304: FORNECEDORES | D304: 450 | E304: ITAÚ | F304: Março
A305: 46083 | B305: ORANGE E BLACK | C305: FORNECEDORES | D305: 890 | E305: ITAÚ | F305: Março
A306: 46083 | B306: DISPLAY MAX | C306: FORNECEDORES | D306: 60 | E306: ITAÚ | F306: Março
... A413: 46100 | B413: BOLETOS | C413: BANCO | D413: 7.24 | E413: ITAÚ | F413: Março
A414: 46100 | B414: JOSÉ WILLARES | D414: 40 | E414: ITAÚ | F414: Março
A415: 46101 | B415: TRICOMP COMERCIAL E LTDA | C415: FORNECEDORES | D415: 328.6 | E415: ITAÚ | F415: Março
A416: 46101 | B416: ZENER COMPONENTES ELETRONIC LT | C416: FORNECEDORES | D416: 575 | E416: ITAÚ | F416: Março
A417: 46101 | B417: DAS IMP | C417: IMPOSTOS | D417: 13588.94 | E417: ITAÚ | F417: Março
A418: 46101 | B418: DARF | C418: IMPOSTOS | D418: 1046.45 | E418: ITAÚ | F418: Março
A419: 46101 | B419: FGTS | C419: IMPOSTOS | D419: 554.25 | E419: ITAÚ | F419: Março
A420: 46101 | B420: VALE MATHEUS SOUZA | C420: FUNCIONÁRIOS | D420: 720 | E420: ITAÚ | F420: Março
A421: 46101 | B421: VALE THAMIRES | C421: FUNCIONÁRIOS | D421: 855.2 | E421: ITAÚ | F421: Março
A422: 46101 | B422: PREVIDENCIA | C422: INVESTIMENTO | D422: 473.47 | E422: ITAÚ | F422: Março
A423: 46101 | B423: PREVIDENCIA | C423: INVESTIMENTO | D423: 496.24 | E423: ITAÚ | F423: Março
A424: 46101 | B424: BOLETOS | C424: BANCO | D424: 12.67 | E424: ITAÚ | F424: Março
...

Sheet ENTRADA NFE ILUMI
A1: Data | B1: Cliente | C1: Nota | D1: Valor | E1: Mês
A2: 46029 | B2: 16954 | C2: FILCRILL COMPS ELETRS IMP E EXP EIRELLI (0000048) | D2: 791.35 | E2: Janeiro
A3: 46029 | B3: 258188 | C3: ACP COMERCIO ATACADISTA DE COMPONENTES E (0000249) | D3: 1610.87 | E3: Janeiro
A4: 46029 | B4: 84539 | C4: COMP TOTAL COM. E IMP. DE COMP. ELETRON. (0000267) | D4: 181.05 | E4: Janeiro
A5: 46030 | B5: 197630 | C5: DISPLAY MAX ELETRONICA LTDA (0000318) | D5: 93 | E5: Janeiro
A6: 46030 | B6: 23467 | C6: ZENER COMPONENTES ELETRONICOS LTDA - ME (0000317) | D6: 612.5 | E6: Janeiro
A7: 46030 | B7: 75348 | C7: IDALL COM. ATAC. DE COMP. ELETR. LTDA (0000011) | D7: 1982.2 | E7: Janeiro
A8: 46030 | B8: 84851 | C8: MEGAPIX COMP. ELETRONICOS LTDA-EPP (0000275) | D8: 28 | E8: Janeiro
A9: 46031 | B9: 45349 | C9: ALLSEMI TECNOLOGIA ELETRONICA LTDA (0000299) | D9: 1079.58 | E9: Janeiro
A10: 46034 | B10: 115266 | C10: LECOMP Com. de Comp. Eletronicos LTDA (0000312) | D10: 272 | E10: Janeiro
A11: 46034 | B11: 258290 | C11: ACP COMERCIO ATACADISTA DE COMPONENTES E (0000249) | D11: 1319.59 | E11: Janeiro
A12: 46034 | B12: 75375 | C12: IDALL COM. ATAC. DE COMP. ELETR. LTDA (0000011) | D12: 6646.2 | E12: Janeiro
A13: 46035 | B13: 2033 | C13: CX COMERCIAL EIRELI EPP (0000329) | D13: 365.4 | E13: Janeiro
... A508: 46171 | B508: 9128 | C508: TRYNIT LED COMPONENTES ELETRONICOS EIREL (0000259) | D508: 240.62 | E508: Maio

Sheet SAÍDA NFE ILUMI
A1: Data | B1: Nfe | C1: Nome | D1: Valor | L1: justificativa de nfs
A2: 46028 | B2: 11916 | C2: COMLINK EQUIPAMENTOS ELETRONICOS LTDA (0000028) | D2: 5100 | F2: 46030 | G2: 39 | H2: GISLENE JAEN (0000084) | I2: 208.8 | J2: SNF | L2: cancelada | M2: 119520 | N2: cancelada | O2: 12016
A3: 46028 | B3: 11917 | C3: EDERSON VARANDA BORGES LTDA (0000785) | D3: 1062.85 | F3: 46035 | G3: 40 | H3: NEW-TEC COMERCIO DE ELETRONICOS LTDA (0000944) | I3: 160 | J3: SNF | L3: cancelada | M3: 12002
A4: 46028 | B4: 11918 | C4: R. BAIAO INDUSTRIA E COMERCIO LTDA (0000060) | D4: 16157.91 | F4: 46035 | G4: 41 | H4: NEW-TEC COMERCIO DE ELETRONICOS LTDA (0000944) | I4: 160 | J4: SNF | L4: cancelada | M4: 12003
A5: 46030 | B5: 11919 | C5: E DE OLIVEIRA BARBOSA ELETRONICA (0000898) | D5: 232 | F5: 46037 | G5: 42 | H5: NEW-TEC COMERCIO DE ELETRONICOS LTDA (0000944) | I5: 489.5 | J5: SNF | L5: cancelada | M5: 12004
A6: 46030 | B6: 11920 | C6: FERRTECH EQUIPAMENTOS ELETRONICA LTDA -E (0000081) | D6: 221.46 | F6: 46042 | G6: 43 | H6: CP DOS SANTOS (0000438) | I6: 7817.2 | J6: SNF | L6: DEVOLUÇÕES RECEBIDAS
A7: 46030 | B7: 11921 | C7: NIATRON IND. E COM. DE EQUIP. ELETRO. (0000143) | D7: 476.7 | F7: 46044 | G7: 45 | H7: NEW-TEC COMERCIO DE ELETRONICOS LTDA (0000944) | I7: 160 | J7: SNF | L7: 46048 | M7: 3747 | N7: SSAT SINALIZACAO E ADESIVOS EIRELI EPP ( (0000072) | O7: 400
A8: 46030 | B8: 11922 | C8: FERRTECH EQUIPAMENTOS ELETRONICA LTDA -E (0000081) | D8: 542 | F8: 46049 | G8: 46 | H8: NEW-TEC COMERCIO DE ELETRONICOS LTDA (0000944) | I8: 169 | J8: SNF | L8: 46043 | M8: 8250 | N8: MDI | O8: 452
A9: 46030 | B9: 11923 | C9: FIBERWAN IND. DE EQUIP. ELETTR. LTDA-EPP (0000411) | D9: 407 | F9: 46051 | G9: 47 | H9: NEW-TEC COMERCIO DE ELETRONICOS LTDA (0000944) | I9: 55.9 | J9: SNF | L9: 46041 | M9: 35076 | N9: CONDUVOX | O9: 28.2
A10: 46030 | B10: 11924 | C10: WKS TECHNOLOGY DO BRASIL (0000208) | D10: 400 | F10: 46048 | G10: 3747 | H10: SSAT SINALIZACAO E ADESIVOS EIRELI EPP ( (0000072) | I10: 400 | J10: DEVOLUÇÕES | O10: 880.2
A11: 46030 | B11: 11925 | C11: SEBASTIAO CESAR GRASSI ELETRONICOS - M.. (0000279) | D11: 2307.61 | F11: 46043 | G11: 8250 | H11: MDI | I11: 452 | J11: DEVOLUÇÕES | L11: SNF
A12: 46031 | B12: 11926 | C12: CRISTOFOLI EQUIP. DE BIOSSEGURANÇA LTDA (0000146) | D12: 325 | F12: 46041 | G12: 35076 | H12: CONDUVOX | I12: 28.2 | J12: DEVOLUÇÕES | L12: 46030 | M12: 39 | N12: GISLENE JAEN (0000084) | O12: 208.8
A13: 46031 | B13: 11927 | C13: CRISTOFOLI EQUIP. DE BIOSSEGURANÇA LTDA (0000146) | D13: 650 | F13: 46065 | G13: 48 | H13: CP DOS SANTOS (0000438) | I13: 7000 | J13: SNF | L13: 46035 | M13: 40 | N13: NEW-TEC COMERCIO DE ELETRONICOS LTDA (0000944) | O13: 160
A14: 46031 | B14: 11928 | C14: ARIELTEK INDUSTRIA E COMERCIO LTDA (0000314) | D14: 834 | F14: 46066 | G14: 12058 | H14: JAIRO FURBINO DOS SANTOS (0000739) | I14: 668 | J14: SNF | L14: 46035 | M14: 41 | N14: NEW-TEC COMERCIO DE ELETRONICOS LTDA (0000944) | O14: 160
A15: 46031 | B15: 11929 | C15: BASSOMED EQUIPAMENTOS MEDICOS E ODONTOLO (0000660) | D15: 986.1 | F15: 46094 | G15: 49 | H15: JAIRO FURBINO DOS SANTOS (0000739) | I15: 420 | J15: SNF | L15: 46037 | M15: 42 | N15: NEW-TEC COMERCIO DE ELETRONICOS LTDA (0000944) | O15: 489.5
A16: 46031 | B16: 11930 | C16: SIMPLES CONNECT INDUSTRIA E COMERCIO LTA (0000308) | D16: 442 | F16: 46094 | G16: 50 | H16: NEW-TEC COMERCIO DE ELETRONICOS LTDA (0000944) | I16: 221 | J16: SNF | L16: 46042 | M16: 43 | N16: CP DOS SANTOS (0000438) | O16: 7817.2
A17: 46031 | B17: 11931 | C17: M. POWER IND.E COM. DE ELETR. LTDA (0000216) | D17: 1104 | F17: 46094 | G17: 51 | H17: NEW-TEC COMERCIO DE ELETRONICOS LTDA (0000944) | I17: 170 | J17: SNF | L17: 46044 | M17: 45 | N17: NEW-TEC COMERCIO DE ELETRONICOS LTDA (0000944) | O17: 160
A18: 46031 | B18: 11932 | C18: FERRTECH EQUIPAMENTOS ELETRONICA LTDA -E (0000081) | D18: 19.92 | F18: 46094 | G18: 52 | H18: NEW-TEC COMERCIO DE ELETRONICOS LTDA (0000944) | I18: 35 | J18: SNF | L18: 46049 | M18: 46 | N18: NEW-TEC COMERCIO DE ELETRONICOS LTDA (0000944) | O18: 169
A19: 46034 | B19: 11934 | C19: CONSTRUTEC FACILITIES COM. E SERV. DE EN (0000033) | D19: 109.68 | F19: 46100 | G19: 53 | H19: NEW-TEC COMERCIO DE ELETRONICOS LTDA (0000944) | I19: 60 | J19: SNF | L19: 46051 | M19: 47 | N19: NEW-TEC COMERCIO DE ELETRONICOS LTDA (0000944) | O19: 55.9
A20: 46034 | B20: 11935 | C20: TRANSFIX ASSISTENCIA TECN. E VENDAS EQUI (0000199) | D20: 2978 | F20: 46107 | G20: M12063 | H20: GABRIEL FREITAS DE LIMA MATOS (0000700) | I20: 296 | J20: SNF | O20: 9220.4
A21: 46034 | B21: 11936 | C21: ELETROFELIX INDUSTRIA E COMERCIO LTDA (0000477) | D21: 653.5 | F21: 46113 | G21: 54 | H21: NEW-TEC COMERCIO DE ELETRONICOS LTDA (0000944) | I21: 245 | J21: SNF
A22: 46034 | B22: 11937 | C22: MOTOPPAR INDUSTRIA E COMERCIO DE AUTOMAT (0001056) | D22: 570 | F22: 46119 | G22: 7 | H22: JAIRO FURBINO DOS SANTOS (0000739) | I22: 806 | J22: SNF
A23: 46034 | B23: 11938 | C23: FZW INNOVATION LTDA (0000848) | D23: 3083.36 | F23: 46121 | G23: 55 | H23: NEW-TEC COMERCIO DE ELETRONICOS LTDA (0000944) | I23: 160 | J23: SNF | L23: MERCADO FULL
A24: 46034 | B24: 11939 | C24: EXPOENTE TECNOLOGIA ELETRONICA LTDA (0000079) | D24: 548.9 | F24: 46122 | G24: 56 | H24: NEW-TEC COMERCIO DE ELETRONICOS LTDA (0000944) | I24: 96.6 | J24: SNF | L24: 46028 | M24: 1705 | N24: ROSAIR | O24: 129.99
A25: 46034 | B25: 11940 | C25: NEW TRAFFIC CONTROL TEC. E INOVACAO LTDA (0000773) | D25: 1224 | F25: 46125 | G25: 8 | H25: JAIRO FURBINO DOS SANTOS (0000739) | I25: 247.42 | J25: SNF | L25: 46029 | M25: 1707 | N25: LADEMIR | O25: 14.99
A26: 46034 | B26: 11941 | C26: MDI PROD E SISTEMAS LTDA (0000101) | D26: 654.2 | F26: 46126 | G26: 9 | H26: GISLENE JAEN (0000084) | I26: 2498.4 | J26: SNF | L26: 46037 | M26: 1709 | N26: ANTONIO | O26: 24.98
A27: 46035 | B27: 11942 | C27: R. BAIAO INDUSTRIA E COMERCIO LTDA (0000060) | D27: 1858.5 | F27: 46126 | G27: M10 | H27: NEW-TEC COMERCIO DE ELETRONICOS LTDA (0000944) | I27: 165 | J27: SNF | L27: 46041 | M27: 1719 | N27: EDUARDO | O27: 19.95
A28: 46035 | B28: 11943 | C28: J.M. MAQUINAS AUTOMOTIVAS EIRELI (0000387) | D28: 4432.1 | F28: 46128 | G28: 1 | H28: NEW-TEC COMERCIO DE ELETRONICOS LTDA (0000944) | I28: 180 | J28: SNF | L28: 46044 | M28: 1722 | N28: RAMOM | O28: 37.13
A29: 46035 | B29: 11944 | C29: FZW INNOVATION LTDA (0000848) | D29: 509.3 | F29: 46135 | G29: 6 | H29: NEW-TEC COMERCIO DE ELETRONICOS LTDA (0000944) | I29: 337.5 | J29: SNF | L29: 46044 | M29: 1724 | N29: OSVALDO FULL | O29: 26.93
A30: 46035 | B30: 11945 | C30: HIGHZ VALE INDUSTRIA ELETRONICA LTDA (0000526) | D30: 56 | F30: 46136 | G30: 7 | H30: NEW-TEC COMERCIO DE ELETRONICOS LTDA (0000944) | I30: 160 | J30: SNF | O30: 253.97
A31: 46035 | B31: 11946 | C31: B. P. S. SISTEMAS DE AUTOMACAO LTDA (0000010) | D31: 567.8 | F31: 46136 | G31: 8 | H31: GISLENE JAEN (0000084) | I31: 88.2 | J31: SNF
A32: 46035 | B32: 11947 | C32: OSVALDO VENTURINI PINTO (0001060) | D32: 67.96
A33: 46035 | B33: 11948 | C33: ELIANE APARECIDA RIBEIRO MARTINS (0001059) | D33: 33.98
A34: 46035 | B34: 11949 | C34: DENTSCLER IND. DE APAR. ODONTO. EIRELLI (0000390) | D34: 2039
A35: 46035 | B35: 11950 | C35: ALLPRINT LATINA AUTOMACAO DE MAQUINAS EA (0000291) | D35: 1716
A36: 46035 | B36: 11951 | C36: PRODUTOS ELETRONICOS FRATA LTDA (0000223) | D36: 13551
A37: 46035 | B37: 11953 | C37: TRANSFIX ASSISTENCIA TECN. E VENDAS EQUI (0000199) | D37: 75
A38: 46035 | B38: 11954 | C38: DIGISYSTEM IND. DE SIST. ELETRO. LTDA (0000040) | D38: 3039.5
A39: 46035 | B39: 11955 | C39: CITTA ELETRONICA IND. E COM. LTDA ME (0000532) | D39: 338.5
A40: 46036 | B40: 11956 | C40: SSAT SINALIZACAO E ADESIVOS EIRELI EPP (0000072) | D40: 5405
A41: 46036 | B41: 11957 | C41: CONDUVOX TELEMATICA LTDA (0000031) | D41: 265
A42: 46036 | B42: 11958 | C42: EVOLUTEC INDUSTRIA E COMERCIO DE ELETROA (0000229) | D42: 223.6
A43: 46036 | B43: 11959 | C43: VALNEI VIEIRA DA SILVA 00391345630 (0000070) | D43: 253.2
... A712: 46171 | B712: 12696 | C712: SSAT SINALIZACAO E ADESIVOS EIRELI EPP (0000072) | D712: 2779.6

Sheet Piperline
A4: Empresa | B4: Mês Previsto | C4: Valor Previsto | D4: Status

Sheet Planilha3
